Workbook

Sheet New Matches
B1: Job Details | J1: Match Details (from PF Export: Project Report)
A2: Key - Job Code | B2: Job Family | C2: Job Sub-Family | D2: Date | E2: Job Level | F2: Current Job Title | G2: New Job Title | H2: Key | I2: Job Code | J2: Job Title | K2: Job Code | L2: Source | M2: Scope | N2: Curr | O2: Base 25th | P2: Base 50th | Q2: Base 75th | R2: AZL Avg | S2: AZL % | T2: TCC 25th | U2: TCC 50th | V2: TCC 75th | W2: Avg Base | X2: Base to Market | Y2: Avg Base to Market | Z2: Inc Count | AA2: Comment
A3: =I3 -> AR-AR-M2-2 | B3: Actuarial | C3: Actuarial | D3: 45715 | E3: M2 | F3: =IFERROR(VLOOKUP(I3, 'Job Code Table'!D:E, 2, FALSE), "") | G3: =VLOOKUP(I3, '[1]Job Mapping'!$B:$N, 13, FALSE) -> Assistant Actuary | H3: =_xlfn.CONCAT(E3, "-", G3) -> M2-Assistant Actuary | I3: AR-AR-M2-2 | J3: Supervising Actuary | K3: 401 | L3: ClearSolutionsHR: Life/Health Actuarial Salary Survey 04/01/2024 | M3: Life & Health/all/ | N3: USD | O3: 161.7 | P3: 175.9 | Q3: 190.2 | T3: 191.3 | U3: 211.7 | V3: 235.4 | W3: =IFERROR(VLOOKUP(I3, Summary!K:L, 2, FALSE), "") | X3: =IF(W3="","",W3/P3) | Y3: =IFERROR(ROUND(VLOOKUP(I3, Summary!K:L, 2, FALSE)/VLOOKUP(I3, Summary!N:O, 2, FALSE), 1), "") | Z3: =IFERROR(VLOOKUP(I3, Summary!Q:R, 2, FALSE), 0) -> 0
A4: =I4 -> AR-AR-M2-2 | B4: Actuarial | C4: Actuarial | D4: 45715 | E4: M2 | F4: =IFERROR(VLOOKUP(I4, 'Job Code Table'!D:E, 2, FALSE), "") | G4: =VLOOKUP(I4, '[1]Job Mapping'!$B:$N, 13, FALSE) -> Assistant Actuary | H4: =_xlfn.CONCAT(E4, "-", G4) -> M2-Assistant Actuary | I4: AR-AR-M2-2 | J4: Actuary | K4: 5024 | L4: Corporate Comp Strategies: Life Survey Group 03/01/2024 | M4: All// | N4: USD | O4: 151.8 | P4: 165.1 | Q4: 181.4 | T4: 175.3 | U4: 195.7 | V4: 221.3 | W4: =IFERROR(VLOOKUP(I4, Summary!K:L, 2, FALSE), "") | X4: =IF(W4="","",W4/P4) | Y4: =IFERROR(ROUND(VLOOKUP(I4, Summary!K:L, 2, FALSE)/VLOOKUP(I4, Summary!N:O, 2, FALSE), 1), "") | Z4: =IFERROR(VLOOKUP(I4, Summary!Q:R, 2, FALSE), 0) -> 0
A5: =I5 -> AR-AR-M2-2 | B5: Actuarial | C5: Actuarial | D5: 45715 | E5: M2 | F5: =IFERROR(VLOOKUP(I5, 'Job Code Table'!D:E, 2, FALSE), "") | G5: =VLOOKUP(I5, '[1]Job Mapping'!$B:$N, 13, FALSE) -> Assistant Actuary | H5: =_xlfn.CONCAT(E5, "-", G5) -> M2-Assistant Actuary | I5: AR-AR-M2-2 | J5: Associate Actuary | K5: 2103 | L5: Life Office Management Assoc: Non-Executive Compensation Survey 04/01/2024 | M5: All Companies/All Companies/ | N5: USD | O5: 147 | P5: 159.3 | Q5: 176.7 | T5: 167 | U5: 187.4 | V5: 209.2 | W5: =IFERROR(VLOOKUP(I5, Summary!K:L, 2, FALSE), "") | X5: =IF(W5="","",W5/P5) | Y5: =IFERROR(ROUND(VLOOKUP(I5, Summary!K:L, 2, FALSE)/VLOOKUP(I5, Summary!N:O, 2, FALSE), 1), "") | Z5: =IFERROR(VLOOKUP(I5, Summary!Q:R, 2, FALSE), 0) -> 0
A6: =I6 -> AR-AR-M2-2 | B6: Actuarial | C6: Actuarial | D6: 45715 | E6: M2 | F6: =IFERROR(VLOOKUP(I6, 'Job Code Table'!D:E, 2, FALSE), "") | G6: =VLOOKUP(I6, '[1]Job Mapping'!$B:$N, 13, FALSE) -> Assistant Actuary | H6: =_xlfn.CONCAT(E6, "-", G6) -> M2-Assistant Actuary | I6: AR-AR-M2-2 | J6: Actuarial - Life|Actuarial - Life Generalist/Multidiscipline|Manager (Supervisory/Management)-M2-All Incumbent Global Grade | K6: FAD000-M2 | L6: Towers Watson: Financial Services MMPS 04/01/2024 | M6: Total Sample// | N6: USD | O6: 139.6 | P6: 162.1 | Q6: 176 | T6: 162.8 | U6: 186.1 | V6: 209.2 | W6: =IFERROR(VLOOKUP(I6, Summary!K:L, 2, FALSE), "") | X6: =IF(W6="","",W6/P6) | Y6: =IFERROR(ROUND(VLOOKUP(I6, Summary!K:L, 2, FALSE)/VLOOKUP(I6, Summary!N:O, 2, FALSE), 1), "") | Z6: =IFERROR(VLOOKUP(I6, Summary!Q:R, 2, FALSE), 0) -> 0
A7: =I7 -> AR-AR-M2-1 | B7: Actuarial | C7: Actuarial | D7: 45715 | E7: M2 | F7: =IFERROR(VLOOKUP(I7, 'Job Code Table'!D:E, 2, FALSE), "") | G7: =VLOOKUP(I7, '[1]Job Mapping'!$B:$N, 13, FALSE) -> Associate Actuary | H7: =_xlfn.CONCAT(E7, "-", G7) -> M2-Associate Actuary | I7: AR-AR-M2-1 | J7: Supervising Actuary | K7: 401 | L7: ClearSolutionsHR: Life/Health Actuarial Salary Survey 04/01/2024 | M7: Life & Health/all/ | N7: USD | O7: 161.7 | P7: 175.9 | Q7: 190.2 | T7: 191.3 | U7: 211.7 | V7: 235.4 | W7: =IFERROR(VLOOKUP(I7, Summary!K:L, 2, FALSE), "") | X7: =IF(W7="","",W7/P7) | Y7: =IFERROR(ROUND(VLOOKUP(I7, Summary!K:L, 2, FALSE)/VLOOKUP(I7, Summary!N:O, 2, FALSE), 1), "") | Z7: =IFERROR(VLOOKUP(I7, Summary!Q:R, 2, FALSE), 0) -> 0
A8: =I8 -> AR-AR-M2-1 | B8: Actuarial | C8: Actuarial | D8: 45715 | E8: M2 | F8: =IFERROR(VLOOKUP(I8, 'Job Code Table'!D:E, 2, FALSE), "") | G8: =VLOOKUP(I8, '[1]Job Mapping'!$B:$N, 13, FALSE) -> Associate Actuary | H8: =_xlfn.CONCAT(E8, "-", G8) -> M2-Associate Actuary | I8: AR-AR-M2-1 | J8: Actuary | K8: 5024 | L8: Corporate Comp Strategies: Life Survey Group 03/01/2024 | M8: All// | N8: USD | O8: 151.8 | P8: 165.1 | Q8: 181.4 | T8: 175.3 | U8: 195.7 | V8: 221.3 | W8: =IFERROR(VLOOKUP(I8, Summary!K:L, 2, FALSE), "") | X8: =IF(W8="","",W8/P8) | Y8: =IFERROR(ROUND(VLOOKUP(I8, Summary!K:L, 2, FALSE)/VLOOKUP(I8, Summary!N:O, 2, FALSE), 1), "") | Z8: =IFERROR(VLOOKUP(I8, Summary!Q:R, 2, FALSE), 0) -> 0
A9: =I9 -> AR-AR-M2-1 | B9: Actuarial | C9: Actuarial | D9: 45715 | E9: M2 | F9: =IFERROR(VLOOKUP(I9, 'Job Code Table'!D:E, 2, FALSE), "") | G9: =VLOOKUP(I9, '[1]Job Mapping'!$B:$N, 13, FALSE) -> Associate Actuary | H9: =_xlfn.CONCAT(E9, "-", G9) -> M2-Associate Actuary | I9: AR-AR-M2-1 | J9: Assistant Actuary | K9: 2104 | L9: Life Office Management Assoc: Non-Executive Compensation Survey 04/01/2024 | M9: All Companies/All Companies/ | N9: USD | O9: 141.7 | P9: 155.3 | Q9: 166.5 | T9: 158.3 | U9: 172.5 | V9: 187.2 | W9: =IFERROR(VLOOKUP(I9, Summary!K:L, 2, FALSE), "") | X9: =IF(W9="","",W9/P9) | Y9: =IFERROR(ROUND(VLOOKUP(I9, Summary!K:L, 2, FALSE)/VLOOKUP(I9, Summary!N:O, 2, FALSE), 1), "") | Z9: =IFERROR(VLOOKUP(I9, Summary!Q:R, 2, FALSE), 0) -> 0
A10: =I10 -> AR-AR-M2-1 | B10: Actuarial | C10: Actuarial | D10: 45715 | E10: M2 | F10: =IFERROR(VLOOKUP(I10, 'Job Code Table'!D:E, 2, FALSE), "") | G10: =VLOOKUP(I10, '[1]Job Mapping'!$B:$N, 13, FALSE) -> Associate Actuary | H10: =_xlfn.CONCAT(E10, "-", G10) -> M2-Associate Actuary | I10: AR-AR-M2-1 | J10: Actuarial - Life|Actuarial - Life Generalist/Multidiscipline|Manager (Supervisory/Management)-M2-All Incumbent Global Grade | K10: FAD000-M2 | L10: Towers Watson: Financial Services MMPS 04/01/2024 | M10: Total Sample// | N10: USD | O10: 139.6 | P10: 162.1 | Q10: 176 | T10: 162.8 | U10: 186.1 | V10: 209.2 | W10: =IFERROR(VLOOKUP(I10, Summary!K:L, 2, FALSE), "") | X10: =IF(W10="","",W10/P10) | Y10: =IFERROR(ROUND(VLOOKUP(I10, Summary!K:L, 2, FALSE)/VLOOKUP(I10, Summary!N:O, 2, FALSE), 1), "") | Z10: =IFERROR(VLOOKUP(I10, Summary!Q:R, 2, FALSE), 0) -> 0
A11: =I11 -> AR-AR-M3-1 | B11: Actuarial | C11: Actuarial | D11: 45715 | E11: M3 | G11: =VLOOKUP(I11, '[1]Job Mapping'!$B:$N, 13, FALSE) -> Actuary | H11: =_xlfn.CONCAT(E11, "-", G11) -> M3-Actuary | I11: AR-AR-M3-1 | J11: Managing Actuary - Consolidated | K11: 300 | L11: ClearSolutionsHR: Life/Health Actuarial Salary Survey 04/01/2024 | M11: Life & Health/all/ | N11: USD | O11: 184.9 | P11: 206.5 | Q11: 229.1 | T11: 217.2 | U11: 256.5 | V11: 296.6 | W11: =IFERROR(VLOOKUP(I11, Summary!K:L, 2, FALSE), "") | X11: =IF(W11="","",W11/P11) | Y11: =IFERROR(ROUND(VLOOKUP(I11, Summary!K:L, 2, FALSE)/VLOOKUP(I11, Summary!N:O, 2, FALSE), 1), "") | Z11: =IFERROR(VLOOKUP(I11, Summary!Q:R, 2, FALSE), 0) -> 0
A12: =I12 -> AR-AR-M3-1 | B12: Actuarial | C12: Actuarial | D12: 45715 | E12: M3 | G12: =VLOOKUP(I12, '[1]Job Mapping'!$B:$N, 13, FALSE) -> Actuary | H12: =_xlfn.CONCAT(E12, "-", G12) -> M3-Actuary | I12: AR-AR-M3-1 | J12: Actuary | K12: 5024 | L12: Corporate Comp Strategies: Life Survey Group 03/01/2024 | M12: All// | N12: USD | O12: 167 | P12: 181.6 | Q12: 199.5 | T12: 192.8 | U12: 215.3 | V12: 243.4 | W12: =IFERROR(VLOOKUP(I12, Summary!K:L, 2, FALSE), "") | X12: =IF(W12="","",W12/P12) | Y12: =IFERROR(ROUND(VLOOKUP(I12, Summary!K:L, 2, FALSE)/VLOOKUP(I12, Summary!N:O, 2, FALSE), 1), "") | Z12: =IFERROR(VLOOKUP(I12, Summary!Q:R, 2, FALSE), 0) -> 0
A13: =I13 -> AR-AR-M3-1 | B13: Actuarial | C13: Actuarial | D13: 45715 | E13: M3 | G13: =VLOOKUP(I13, '[1]Job Mapping'!$B:$N, 13, FALSE) -> Actuary | H13: =_xlfn.CONCAT(E13, "-", G13) -> M3-Actuary | I13: AR-AR-M3-1 | J13: Associate Actuary | K13: 2103 | L13: Life Office Management Assoc: Non-Executive Compensation Survey 04/01/2024 | M13: All Companies/All Companies/ | N13: USD | O13: 147 | P13: 159.3 | Q13: 176.7 | T13: 167 | U13: 187.4 | V13: 209.2 | W13: =IFERROR(VLOOKUP(I13, Summary!K:L, 2, FALSE), "") | X13: =IF(W13="","",W13/P13) | Y13: =IFERROR(ROUND(VLOOKUP(I13, Summary!K:L, 2, FALSE)/VLOOKUP(I13, Summary!N:O, 2, FALSE), 1), "") | Z13: =IFERROR(VLOOKUP(I13, Summary!Q:R, 2, FALSE), 0) -> 0
A14: =I14 -> AR-AR-M3-1 | B14: Actuarial | C14: Actuarial | D14: 45715 | E14: M3 | G14: =VLOOKUP(I14, '[1]Job Mapping'!$B:$N, 13, FALSE) -> Actuary | H14: =_xlfn.CONCAT(E14, "-", G14) -> M3-Actuary | I14: AR-AR-M3-1 | J14: Actuarial - Life|Actuarial - Life Generalist/Multidiscipline|Senior Manager (Supervisory/Management)-M3-All Incumbent Global Grade | K14: FAD000-M3 | L14: Towers Watson: Financial Services MMPS 04/01/2024 | M14: Total Sample// | N14: USD | O14: 168.9 | P14: 184.3 | Q14: 204 | T14: 205.8 | U14: 225.4 | V14: 255.8 | W14: =IFERROR(VLOOKUP(I14, Summary!K:L, 2, FALSE), "") | X14: =IF(W14="","",W14/P14) | Y14: =IFERROR(ROUND(VLOOKUP(I14, Summary!K:L, 2, FALSE)/VLOOKUP(I14, Summary!N:O, 2, FALSE), 1), "") | Z14: =IFERROR(VLOOKUP(I14, Summary!Q:R, 2, FALSE), 0) -> 0
A15: =I15 -> AR-AR-M3-2 | B15: Actuarial | C15: Actuarial | D15: 45715 | E15: M3 | G15: =VLOOKUP(I15, '[1]Job Mapping'!$B:$N, 13, FALSE) -> Senior Actuary | H15: =_xlfn.CONCAT(E15, "-", G15) -> M3-Senior Actuary | I15: AR-AR-M3-2 | J15: Managing Actuary - Consolidated | K15: 300 | L15: ClearSolutionsHR: Life/Health Actuarial Salary Survey 04/01/2024 | M15: Life & Health/all/ | N15: USD | O15: 184.9 | P15: 206.5 | Q15: 229.1 | T15: 217.2 | U15: 256.5 | V15: 296.6 | W15: =IFERROR(VLOOKUP(I15, Summary!K:L, 2, FALSE), "") | X15: =IF(W15="","",W15/P15) | Y15: =IFERROR(ROUND(VLOOKUP(I15, Summary!K:L, 2, FALSE)/VLOOKUP(I15, Summary!N:O, 2, FALSE), 1), "") | Z15: =IFERROR(VLOOKUP(I15, Summary!Q:R, 2, FALSE), 0) -> 0
A16: =I16 -> AR-AR-M3-2 | B16: Actuarial | C16: Actuarial | D16: 45715 | E16: M3 | G16: =VLOOKUP(I16, '[1]Job Mapping'!$B:$N, 13, FALSE) -> Senior Actuary | H16: =_xlfn.CONCAT(E16, "-", G16) -> M3-Senior Actuary | I16: AR-AR-M3-2 | J16: Senior Actuary | K16: 5022 | L16: Corporate Comp Strategies: Life Survey Group 03/01/2024 | M16: All// | N16: USD | O16: 175.2 | P16: 187.6 | Q16: 208.7 | T16: 213.1 | U16: 231.5 | V16: 265 | W16: =IFERROR(VLOOKUP(I16, Summary!K:L, 2, FALSE), "") | X16: =IF(W16="","",W16/P16) | Y16: =IFERROR(ROUND(VLOOKUP(I16, Summary!K:L, 2, FALSE)/VLOOKUP(I16, Summary!N:O, 2, FALSE), 1), "") | Z16: =IFERROR(VLOOKUP(I16, Summary!Q:R, 2, FALSE), 0) -> 0
A17: =I17 -> AR-AR-M3-2 | B17: Actuarial | C17: Actuarial | D17: 45715 | E17: M3 | G17: =VLOOKUP(I17, '[1]Job Mapping'!$B:$N, 13, FALSE) -> Senior Actuary | H17: =_xlfn.CONCAT(E17, "-", G17) -> M3-Senior Actuary | I17: AR-AR-M3-2 | J17: Actuary | K17: 2102 | L17: Life Office Management Assoc: Non-Executive Compensation Survey 04/01/2024 | M17: All Companies/All Companies/ | N17: USD | O17: 187.7 | P17: 201.4 | Q17: 221.3 | T17: 225.4 | U17: 246.8 | V17: 274 | W17: =IFERROR(VLOOKUP(I17, Summary!K:L, 2, FALSE), "") | X17: =IF(W17="","",W17/P17) | Y17: =IFERROR(ROUND(VLOOKUP(I17, Summary!K:L, 2, FALSE)/VLOOKUP(I17, Summary!N:O, 2, FALSE), 1), "") | Z17: =IFERROR(VLOOKUP(I17, Summary!Q:R, 2, FALSE), 0) -> 0
A18: =I18 -> AR-AR-M3-2 | B18: Actuarial | C18: Actuarial | D18: 45715 | E18: M3 | G18: =VLOOKUP(I18, '[1]Job Mapping'!$B:$N, 13, FALSE) -> Senior Actuary | H18: =_xlfn.CONCAT(E18, "-", G18) -> M3-Senior Actuary | I18: AR-AR-M3-2 | J18: Actuarial - Life|Actuarial - Life Generalist/Multidiscipline|Senior Manager (Supervisory/Management)-M3-All Incumbent Global Grade | K18: FAD000-M3 | L18: Towers Watson: Financial Services MMPS 04/01/2024 | M18: Total Sample// | N18: USD | O18: 168.9 | P18: 184.3 | Q18: 204 | T18: 205.8 | U18: 225.4 | V18: 255.8 | W18: =IFERROR(VLOOKUP(I18, Summary!K:L, 2, FALSE), "") | X18: =IF(W18="","",W18/P18) | Y18: =IFERROR(ROUND(VLOOKUP(I18, Summary!K:L, 2, FALSE)/VLOOKUP(I18, Summary!N:O, 2, FALSE), 1), "") | Z18: =IFERROR(VLOOKUP(I18, Summary!Q:R, 2, FALSE), 0) -> 0
A19: =I19 -> 100811 | B19: Actuarial | C19: Actuarial | D19: 45715 | E19: M4 | G19: =VLOOKUP(I19, '[1]Job Mapping'!$B:$N, 13, FALSE) -> Senior Director Actuary | H19: =_xlfn.CONCAT(E19, "-", G19) -> M4-Senior Director Actuary | I19: 100811 | J19: Managing Actuary - Consolidated | K19: 300 | L19: ClearSolutionsHR: Life/Health Actuarial Salary Survey 04/01/2024 | M19: Life & Health/all/ | N19: USD | O19: 184.9 | P19: 206.5 | Q19: 229.1 | T19: 217.2 | U19: 256.5 | V19: 296.6 | W19: =IFERROR(VLOOKUP(I19, Summary!K:L, 2, FALSE), "") -> 226.9 | X19: =IF(W19="","",W19/P19) -> 1.0987893 | Y19: =IFERROR(ROUND(VLOOKUP(I19, Summary!K:L, 2, FALSE)/VLOOKUP(I19, Summary!N:O, 2, FALSE), 1), "") -> 1.1 | Z19: =IFERROR(VLOOKUP(I19, Summary!Q:R, 2, FALSE), 0) -> 4
A20: =I20 -> 100811 | B20: Actuarial | C20: Actuarial | D20: 45715 | E20: M4 | G20: =VLOOKUP(I20, '[1]Job Mapping'!$B:$N, 13, FALSE) -> Senior Director Actuary | H20: =_xlfn.CONCAT(E20, "-", G20) -> M4-Senior Director Actuary | I20: 100811 | J20: Managing Actuary | K20: 5010 | L20: Corporate Comp Strategies: Life Survey Group 03/01/2024 | M20: All// | N20: USD | O20: 185 | P20: 205.5 | Q20: 228.5 | T20: 219.4 | U20: 262.8 | V20: 302.6 | W20: =IFERROR(VLOOKUP(I20, Summary!K:L, 2, FALSE), "") -> 226.9 | X20: =IF(W20="","",W20/P20) -> 1.1041363 | Y20: =IFERROR(ROUND(VLOOKUP(I20, Summary!K:L, 2, FALSE)/VLOOKUP(I20, Summary!N:O, 2, FALSE), 1), "") -> 1.1 | Z20: =IFERROR(VLOOKUP(I20, Summary!Q:R, 2, FALSE), 0) -> 4
A21: =I21 -> 100811 | B21: Actuarial | C21: Actuarial | D21: 45715 | E21: M4 | G21: =VLOOKUP(I21, '[1]Job Mapping'!$B:$N, 13, FALSE) -> Senior Director Actuary | H21: =_xlfn.CONCAT(E21, "-", G21) -> M4-Senior Director Actuary | I21: 100811 | J21: Managing Actuary | K21: 2101 | L21: Life Office Management Assoc: Non-Executive Compensation Survey 04/01/2024 | M21: All Companies/All Companies/ | N21: USD | O21: 196.9 | P21: 213.2 | Q21: 239.1 | T21: 230.5 | U21: 265.2 | V21: 303.2 | W21: =IFERROR(VLOOKUP(I21, Summary!K:L, 2, FALSE), "") -> 226.9 | X21: =IF(W21="","",W21/P21) -> 1.0642589 | Y21: =IFERROR(ROUND(VLOOKUP(I21, Summary!K:L, 2, FALSE)/VLOOKUP(I21, Summary!N:O, 2, FALSE), 1), "") -> 1.1 | Z21: =IFERROR(VLOOKUP(I21, Summary!Q:R, 2, FALSE), 0) -> 4
A22: =I22 -> 100811 | B22: Actuarial | C22: Actuarial | D22: 45715 | E22: M4 | G22: =VLOOKUP(I22, '[1]Job Mapping'!$B:$N, 13, FALSE) -> Senior Director Actuary | H22: =_xlfn.CONCAT(E22, "-", G22) -> M4-Senior Director Actuary | I22: 100811 | J22: Actuarial - Life|Actuarial - Life Generalist/Multidiscipline|Group Manager (Supervisory/Management)-M4-All Incumbent Global Grade | K22: FAD000-M4 | L22: Towers Watson: Financial Services MMPS 04/01/2024 | M22: Total Sample// | N22: USD | O22: 215.1 | P22: 232.8 | Q22: 249.3 | T22: 269.5 | U22: 306 | V22: 343.7 | W22: =IFERROR(VLOOKUP(I22, Summary!K:L, 2, FALSE), "") -> 226.9 | X22: =IF(W22="","",W22/P22) -> 0.97465636 | Y22: =IFERROR(ROUND(VLOOKUP(I22, Summary!K:L, 2, FALSE)/VLOOKUP(I22, Summary!N:O, 2, FALSE), 1), "") -> 1.1 | Z22: =IFERROR(VLOOKUP(I22, Summary!Q:R, 2, FALSE), 0) -> 4
A23: =I23 -> 100024 | B23: Actuarial | C23: Actuarial | D23: 45715 | E23: P1 | F23: =IFERROR(VLOOKUP(I23, 'Job Code Table'!D:E, 2, FALSE), "") -> Actuarial Analyst | G23: =VLOOKUP(I23, '[1]Job Mapping'!$B:$N, 13, FALSE) -> Actuarial Analyst | H23: =_xlfn.CONCAT(E23, "-", G23) -> P1-Actuarial Analyst | I23: 100024 | J23: Level I - Entry Actuarial Candidate | K23: 505 | L23: ClearSolutionsHR: Life/Health Actuarial Salary Survey 04/01/2024 | M23: Life & Health/all/ | N23: USD | O23: 78.1 | P23: 83.1 | Q23: 88.5 | T23: 81 | U23: 86.3 | V23: 93.1 | W23: =IFERROR(VLOOKUP(I23, Summary!K:L, 2, FALSE), "") -> 91.613333 | X23: =IF(W23="","",W23/P23) -> 1.1024469 | Y23: =IFERROR(ROUND(VLOOKUP(I23, Summary!K:L, 2, FALSE)/VLOOKUP(I23, Summary!N:O, 2, FALSE), 1), "") -> 1 | Z23: =IFERROR(VLOOKUP(I23, Summary!Q:R, 2, FALSE), 0) -> 15 | AA23: 1-3 exams
A24: =I24 -> 100024 | B24: Actuarial | C24: Actuarial | D24: 45715 | E24: P1 | F24: =IFERROR(VLOOKUP(I24, 'Job Code Table'!D:E, 2, FALSE), "") -> Actuarial Analyst | G24: =VLOOKUP(I24, '[1]Job Mapping'!$B:$N, 13, FALSE) -> Actuarial Analyst | H24: =_xlfn.CONCAT(E24, "-", G24) -> P1-Actuarial Analyst | I24: 100024 | J24: Actuarial Analyst | K24: 5034 | L24: Corporate Comp Strategies: Life Survey Group 03/01/2024 | M24: All// | N24: USD | O24: 82.5 | P24: 90.4 | Q24: 102 | T24: 85.8 | U24: 95.4 | V24: 108.7 | W24: =IFERROR(VLOOKUP(I24, Summary!K:L, 2, FALSE), "") -> 91.613333 | X24: =IF(W24="","",W24/P24) -> 1.0134218 | Y24: =IFERROR(ROUND(VLOOKUP(I24, Summary!K:L, 2, FALSE)/VLOOKUP(I24, Summary!N:O, 2, FALSE), 1), "") -> 1 | Z24: =IFERROR(VLOOKUP(I24, Summary!Q:R, 2, FALSE), 0) -> 15 | AA24: 1-3 exams
A25: =I25 -> 100024 | B25: Actuarial | C25: Actuarial | D25: 45715 | E25: P1 | F25: =IFERROR(VLOOKUP(I25, 'Job Code Table'!D:E, 2, FALSE), "") -> Actuarial Analyst | G25: =VLOOKUP(I25, '[1]Job Mapping'!$B:$N, 13, FALSE) -> Actuarial Analyst | H25: =_xlfn.CONCAT(E25, "-", G25) -> P1-Actuarial Analyst | I25: 100024 | J25: Actuarial Analyst | K25: 2106 | L25: Life Office Management Assoc: Non-Executive Compensation Survey 04/01/2024 | M25: All Companies/All Companies/ | N25: USD | O25: 89.4 | P25: 98.1 | Q25: 105.6 | T25: 95.1 | U25: 103.8 | V25: 112.8 | W25: =IFERROR(VLOOKUP(I25, Summary!K:L, 2, FALSE), "") -> 91.613333 | X25: =IF(W25="","",W25/P25) -> 0.933877 | Y25: =IFERROR(ROUND(VLOOKUP(I25, Summary!K:L, 2, FALSE)/VLOOKUP(I25, Summary!N:O, 2, FALSE), 1), "") -> 1 | Z25: =IFERROR(VLOOKUP(I25, Summary!Q:R, 2, FALSE), 0) -> 15 | AA25: 1-3 exams
A26: =I26 -> 100024 | B26: Actuarial | C26: Actuarial | D26: 45715 | E26: P1 | F26: =IFERROR(VLOOKUP(I26, 'Job Code Table'!D:E, 2, FALSE), "") -> Actuarial Analyst | G26: =VLOOKUP(I26, '[1]Job Mapping'!$B:$N, 13, FALSE) -> Actuarial Analyst | H26: =_xlfn.CONCAT(E26, "-", G26) -> P1-Actuarial Analyst | I26: 100024 | J26: Actuarial - Life|Actuarial - Life Generalist/Multidiscipline|Entry (Professional)-P1-All Incumbent Global Grade | K26: FAD000-P1 | L26: Towers Watson: Financial Services MMPS 04/01/2024 | M26: Total Sample// | N26: USD | O26: 76.3 | P26: 81.8 | Q26: 88.2 | T26: 80.7 | U26: 87.8 | V26: 94.7 | W26: =IFERROR(VLOOKUP(I26, Summary!K:L, 2, FALSE), "") -> 91.613333 | X26: =IF(W26="","",W26/P26) -> 1.1199674 | Y26: =IFERROR(ROUND(VLOOKUP(I26, Summary!K:L, 2, FALSE)/VLOOKUP(I26, Summary!N:O, 2, FALSE), 1), "") -> 1 | Z26: =IFERROR(VLOOKUP(I26, Summary!Q:R, 2, FALSE), 0) -> 15 | AA26: 1-3 exams
A27: =I27 -> 100702 | B27: Actuarial | C27: Actuarial | D27: 45715 | E27: P2 | F27: =IFERROR(VLOOKUP(I27, 'Job Code Table'!D:E, 2, FALSE), "") -> Principal Actuarial Analyst | G27: =VLOOKUP(I27, '[1]Job Mapping'!$B:$N, 13, FALSE) -> Principal Actuarial Analyst | H27: =_xlfn.CONCAT(E27, "-", G27) -> P2-Principal Actuarial Analyst | I27: 100702 | J27: Level III - Senior Actuarial Assistant | K27: 503 | L27: ClearSolutionsHR: Life/Health Actuarial Salary Survey 04/01/2024 | M27: Life & Health/all/ | N27: USD | O27: 113 | P27: 123 | Q27: 133.3 | T27: 122.4 | U27: 134.4 | V27: 146.4 | W27: =IFERROR(VLOOKUP(I27, Summary!K:L, 2, FALSE), "") -> 123.31875 | X27: =IF(W27="","",W27/P27) -> 1.0025915 | Y27: =IFERROR(ROUND(VLOOKUP(I27, Summary!K:L, 2, FALSE)/VLOOKUP(I27, Summary!N:O, 2, FALSE), 1), "") -> 1 | Z27: =IFERROR(VLOOKUP(I27, Summary!Q:R, 2, FALSE), 0) -> 16 | AA27: 5-6 exams/ASA
A28: =I28 -> 100702 | B28: Actuarial | C28: Actuarial | D28: 45715 | E28: P2 | F28: =IFERROR(VLOOKUP(I28, 'Job Code Table'!D:E, 2, FALSE), "") -> Principal Actuarial Analyst | G28: =VLOOKUP(I28, '[1]Job Mapping'!$B:$N, 13, FALSE) -> Principal Actuarial Analyst | H28: =_xlfn.CONCAT(E28, "-", G28) -> P2-Principal Actuarial Analyst | I28: 100702 | J28: Actuarial Associate | K28: 5026 | L28: Corporate Comp Strategies: Life Survey Group 03/01/2024 | M28: All// | N28: USD | O28: 121.1 | P28: 133.7 | Q28: 147.9 | T28: 134.5 | U28: 151.6 | V28: 170.7 | W28: =IFERROR(VLOOKUP(I28, Summary!K:L, 2, FALSE), "") -> 123.31875 | X28: =IF(W28="","",W28/P28) -> 0.92235415 | Y28: =IFERROR(ROUND(VLOOKUP(I28, Summary!K:L, 2, FALSE)/VLOOKUP(I28, Summary!N:O, 2, FALSE), 1), "") -> 1 | Z28: =IFERROR(VLOOKUP(I28, Summary!Q:R, 2, FALSE), 0) -> 16 | AA28: 5-6 exams/ASA
A29: =I29 -> 100702 | B29: Actuarial | C29: Actuarial | D29: 45715 | E29: P2 | F29: =IFERROR(VLOOKUP(I29, 'Job Code Table'!D:E, 2, FALSE), "") -> Principal Actuarial Analyst | G29: =VLOOKUP(I29, '[1]Job Mapping'!$B:$N, 13, FALSE) -> Principal Actuarial Analyst | H29: =_xlfn.CONCAT(E29, "-", G29) -> P2-Principal Actuarial Analyst | I29: 100702 | J29: Actuarial Assistant | K29: 2105 | L29: Life Office Management Assoc: Non-Executive Compensation Survey 04/01/2024 | M29: All Companies/All Companies/ | N29: USD | O29: 112.9 | P29: 123 | Q29: 131.2 | T29: 120.6 | U29: 132.2 | V29: 142.6 | W29: =IFERROR(VLOOKUP(I29, Summary!K:L, 2, FALSE), "") -> 123.31875 | X29: =IF(W29="","",W29/P29) -> 1.0025915 | Y29: =IFERROR(ROUND(VLOOKUP(I29, Summary!K:L, 2, FALSE)/VLOOKUP(I29, Summary!N:O, 2, FALSE), 1), "") -> 1 | Z29: =IFERROR(VLOOKUP(I29, Summary!Q:R, 2, FALSE), 0) -> 16 | AA29: 5-6 exams/ASA
A30: =I30 -> 100702 | B30: Actuarial | C30: Actuarial | D30: 45715 | E30: P2 | F30: =IFERROR(VLOOKUP(I30, 'Job Code Table'!D:E, 2, FALSE), "") -> Principal Actuarial Analyst | G30: =VLOOKUP(I30, '[1]Job Mapping'!$B:$N, 13, FALSE) -> Principal Actuarial Analyst | H30: =_xlfn.CONCAT(E30, "-", G30) -> P2-Principal Actuarial Analyst | I30: 100702 | J30: Actuarial - Life|Actuarial - Life Generalist/Multidiscipline|Intermediate (Professional)-P2-All Incumbent Global Grade | K30: FAD000-P2 | L30: Towers Watson: Financial Services MMPS 04/01/2024 | M30: Total Sample// | N30: USD | O30: 89.4 | P30: 97.4 | Q30: 109.8 | T30: 97.2 | U30: 108.1 | V30: 121.8 | W30: =IFERROR(VLOOKUP(I30, Summary!K:L, 2, FALSE), "") -> 123.31875 | X30: =IF(W30="","",W30/P30) -> 1.2661063 | Y30: =IFERROR(ROUND(VLOOKUP(I30, Summary!K:L, 2, FALSE)/VLOOKUP(I30, Summary!N:O, 2, FALSE), 1), "") -> 1 | Z30: =IFERROR(VLOOKUP(I30, Summary!Q:R, 2, FALSE), 0) -> 16 | AA30: 5-6 exams/ASA
A31: =I31 -> 100807 | B31: Actuarial | C31: Actuarial | D31: 45715 | E31: P2 | F31: =IFERROR(VLOOKUP(I31, 'Job Code Table'!D:E, 2, FALSE), "") -> Senior Actuarial Analyst | G31: =VLOOKUP(I31, '[1]Job Mapping'!$B:$N, 13, FALSE) -> Senior Actuarial Analyst | H31: =_xlfn.CONCAT(E31, "-", G31) -> P2-Senior Actuarial Analyst | I31: 100807 | J31: Level II - Actuarial Assistant | K31: 504 | L31: ClearSolutionsHR: Life/Health Actuarial Salary Survey 04/01/2024 | M31: Life & Health/all/ | N31: USD | O31: 93.5 | P31: 100.2 | Q31: 107.1 | T31: 99.9 | U31: 107.3 | V31: 114.8 | W31: =IFERROR(VLOOKUP(I31, Summary!K:L, 2, FALSE), "") -> 104.95357 | X31: =IF(W31="","",W31/P31) -> 1.0474408 | Y31: =IFERROR(ROUND(VLOOKUP(I31, Summary!K:L, 2, FALSE)/VLOOKUP(I31, Summary!N:O, 2, FALSE), 1), "") -> 1 | Z31: =IFERROR(VLOOKUP(I31, Summary!Q:R, 2, FALSE), 0) -> 28 | AA31: 3-5 exams
A32: =I32 -> 100807 | B32: Actuarial | C32: Actuarial | D32: 45715 | E32: P2 | F32: =IFERROR(VLOOKUP(I32, 'Job Code Table'!D:E, 2, FALSE), "") -> Senior Actuarial Analyst | G32: =VLOOKUP(I32, '[1]Job Mapping'!$B:$N, 13, FALSE) -> Senior Actuarial Analyst | H32: =_xlfn.CONCAT(E32, "-", G32) -> P2-Senior Actuarial Analyst | I32: 100807 | J32: Senior Actuarial Analyst | K32: 5032 | L32: Corporate Comp Strategies: Life Survey Group 03/01/2024 | M32: All// | N32: USD | O32: 97.8 | P32: 107.4 | Q32: 123.4 | T32: 105.5 | U32: 117.6 | V32: 135.1 | W32: =IFERROR(VLOOKUP(I32, Summary!K:L, 2, FALSE), "") -> 104.95357 | X32: =IF(W32="","",W32/P32) -> 0.97722134 | Y32: =IFERROR(ROUND(VLOOKUP(I32, Summary!K:L, 2, FALSE)/VLOOKUP(I32, Summary!N:O, 2, FALSE), 1), "") -> 1 | Z32: =IFERROR(VLOOKUP(I32, Summary!Q:R, 2, FALSE), 0) -> 28 | AA32: 3-5 exams
A33: =I33 -> 100807 | B33: Actuarial | C33: Actuarial | D33: 45715 | E33: P2 | F33: =IFERROR(VLOOKUP(I33, 'Job Code Table'!D:E, 2, FALSE), "") -> Senior Actuarial Analyst | G33: =VLOOKUP(I33, '[1]Job Mapping'!$B:$N, 13, FALSE) -> Senior Actuarial Analyst | H33: =_xlfn.CONCAT(E33, "-", G33) -> P2-Senior Actuarial Analyst | I33: 100807 | J33: Actuarial Assistant | K33: 2105 | L33: Life Office Management Assoc: Non-Executive Compensation Survey 04/01/2024 | M33: All Companies/All Companies/ | N33: USD | O33: 101.6 | P33: 110.7 | Q33: 118.1 | T33: 108.5 | U33: 119 | V33: 128.3 | W33: =IFERROR(VLOOKUP(I33, Summary!K:L, 2, FALSE), "") -> 104.95357 | X33: =IF(W33="","",W33/P33) -> 0.94809008 | Y33: =IFERROR(ROUND(VLOOKUP(I33, Summary!K:L, 2, FALSE)/VLOOKUP(I33, Summary!N:O, 2, FALSE), 1), "") -> 1 | Z33: =IFERROR(VLOOKUP(I33, Summary!Q:R, 2, FALSE), 0) -> 28 | AA33: 3-5 exams
A34: =I34 -> 100807 | B34: Actuarial | C34: Actuarial | D34: 45715 | E34: P2 | F34: =IFERROR(VLOOKUP(I34, 'Job Code Table'!D:E, 2, FALSE), "") -> Senior Actuarial Analyst | G34: =VLOOKUP(I34, '[1]Job Mapping'!$B:$N, 13, FALSE) -> Senior Actuarial Analyst | H34: =_xlfn.CONCAT(E34, "-", G34) -> P2-Senior Actuarial Analyst | I34: 100807 | J34: Actuarial - Life|Actuarial - Life Generalist/Multidiscipline|Intermediate (Professional)-P2-All Incumbent Global Grade | K34: FAD000-P2 | L34: Towers Watson: Financial Services MMPS 04/01/2024 | M34: Total Sample// | N34: USD | O34: 89.4 | P34: 97.4 | Q34: 109.8 | T34: 97.2 | U34: 108.1 | V34: 121.8 | W34: =IFERROR(VLOOKUP(I34, Summary!K:L, 2, FALSE), "") -> 104.95357 | X34: =IF(W34="","",W34/P34) -> 1.0775521 | Y34: =IFERROR(ROUND(VLOOKUP(I34, Summary!K:L, 2, FALSE)/VLOOKUP(I34, Summary!N:O, 2, FALSE), 1), "") -> 1 | Z34: =IFERROR(VLOOKUP(I34, Summary!Q:R, 2, FALSE), 0) -> 28 | AA34: 3-5 exams
... A45: =I45 -> 100025 | B45: Actuarial | C45: Actuarial | D45: 45715 | E45: P5 | F45: =IFERROR(VLOOKUP(I45, 'Job Code Table'!D:E, 2, FALSE), "") -> Actuary | G45: =VLOOKUP(I45, '[1]Job Mapping'!$B:$N, 13, FALSE) -> Actuary | H45: =_xlfn.CONCAT(E45, "-", G45) -> P5-Actuary | I45: 100025 | J45: Actuarial - Life|Actuarial - Life Generalist/Multidiscipline|Expert (Professional)-P5-All Incumbent Global Grade | K45: FAD000-P5 | L45: Towers Watson: Financial Services MMPS 04/01/2024 | M45: Total Sample// | N45: USD | O45: 141.4 | P45: 184.1 | Q45: 200.2 | T45: 165.8 | U45: 226.6 | V45: 251.2 | W45: =IFERROR(VLOOKUP(I45, Summary!K:L, 2, FALSE), "") -> 185.225 | X45: =IF(W45="","",W45/P45) -> 1.0061108 | Y45: =IFERROR(ROUND(VLOOKUP(I45, Summary!K:L, 2, FALSE)/VLOOKUP(I45, Summary!N:O, 2, FALSE), 1), "") -> 1.1 | Z45: =IFERROR(VLOOKUP(I45, Summary!Q:R, 2, FALSE), 0) -> 8 | AA45: FSA, 6-10 years experience
A46: =I46 -> 100808 | B46: Actuarial | C46: Actuarial | D46: 45715 | E46: P5 | F46: =IFERROR(VLOOKUP(I46, 'Job Code Table'!D:E, 2, FALSE), "") -> Senior Actuary | G46: =VLOOKUP(I46, '[1]Job Mapping'!$B:$N, 13, FALSE) -> Senior Actuary | H46: =_xlfn.CONCAT(E46, "-", G46) -> P5-Senior Actuary | I46: 100808 | J46: Senior Actuary | K46: 5022 | L46: Corporate Comp Strategies: Life Survey Group 03/01/2024 | M46: All// | N46: USD | O46: 175.2 | P46: 187.6 | Q46: 208.7 | T46: 213.1 | U46: 231.5 | V46: 265 | W46: =IFERROR(VLOOKUP(I46, Summary!K:L, 2, FALSE), "") -> 210 | X46: =IF(W46="","",W46/P46) -> 1.119403 | Y46: =IFERROR(ROUND(VLOOKUP(I46, Summary!K:L, 2, FALSE)/VLOOKUP(I46, Summary!N:O, 2, FALSE), 1), "") -> 1.1 | Z46: =IFERROR(VLOOKUP(I46, Summary!Q:R, 2, FALSE), 0) -> 1
A47: =I47 -> 100808 | B47: Actuarial | C47: Actuarial | D47: 45715 | E47: P5 | F47: =IFERROR(VLOOKUP(I47, 'Job Code Table'!D:E, 2, FALSE), "") -> Senior Actuary | G47: =VLOOKUP(I47, '[1]Job Mapping'!$B:$N, 13, FALSE) -> Senior Actuary | H47: =_xlfn.CONCAT(E47, "-", G47) -> P5-Senior Actuary | I47: 100808 | J47: Actuary | K47: 2102 | L47: Life Office Management Assoc: Non-Executive Compensation Survey 04/01/2024 | M47: All Companies/All Companies/ | N47: USD | O47: 187.7 | P47: 201.4 | Q47: 221.3 | T47: 225.4 | U47: 246.8 | V47: 274 | W47: =IFERROR(VLOOKUP(I47, Summary!K:L, 2, FALSE), "") -> 210 | X47: =IF(W47="","",W47/P47) -> 1.0427011 | Y47: =IFERROR(ROUND(VLOOKUP(I47, Summary!K:L, 2, FALSE)/VLOOKUP(I47, Summary!N:O, 2, FALSE), 1), "") -> 1.1 | Z47: =IFERROR(VLOOKUP(I47, Summary!Q:R, 2, FALSE), 0) -> 1
A48: =I48 -> 100808 | B48: Actuarial | C48: Actuarial | D48: 45715 | E48: P5 | F48: =IFERROR(VLOOKUP(I48, 'Job Code Table'!D:E, 2, FALSE), "") -> Senior Actuary | G48: =VLOOKUP(I48, '[1]Job Mapping'!$B:$N, 13, FALSE) -> Senior Actuary | H48: =_xlfn.CONCAT(E48, "-", G48) -> P5-Senior Actuary | I48: 100808 | J48: Actuarial - Life|Actuarial - Life Generalist/Multidiscipline|Expert (Professional)-P5-All Incumbent Global Grade | K48: FAD000-P5 | L48: Towers Watson: Financial Services MMPS 04/01/2024 | M48: Total Sample// | N48: USD | O48: 141.4 | P48: 184.1 | Q48: 200.2 | T48: 165.8 | U48: 226.6 | V48: 251.2 | W48: =IFERROR(VLOOKUP(I48, Summary!K:L, 2, FALSE), "") -> 210 | X48: =IF(W48="","",W48/P48) -> 1.1406844 | Y48: =IFERROR(ROUND(VLOOKUP(I48, Summary!K:L, 2, FALSE)/VLOOKUP(I48, Summary!N:O, 2, FALSE), 1), "") -> 1.1 | Z48: =IFERROR(VLOOKUP(I48, Summary!Q:R, 2, FALSE), 0) -> 1
A49: =I49 -> 100137 | B49: Audit | C49: Audit | D49: 45670 | E49: M3 | F49: =IFERROR(VLOOKUP(I49, 'Job Code Table'!D:E, 2, FALSE), "") -> Audit Director | G49: =VLOOKUP(I49, '[1]Job Mapping'!$B:$N, 13, FALSE) -> Director Audit | H49: =_xlfn.CONCAT(E49, "-", G49) -> M3-Director Audit | I49: 100137 | J49: Internal Audit - Senior Manager (M4) | K49: LCA.05.000.M40 | L49: Mercer: MBD - Information Technology Report 03/01/2021 | M49: All Data// | N49: USD | O49: 150.4 | P49: 175.5 | Q49: 207.3 | T49: 150.6 | U49: 197.6 | V49: 240 | W49: =IFERROR(VLOOKUP(I49, Summary!K:L, 2, FALSE), "") -> 157.6 | X49: =IF(W49="","",W49/P49) -> 0.8980057 | Y49: =IFERROR(ROUND(VLOOKUP(I49, Summary!K:L, 2, FALSE)/VLOOKUP(I49, Summary!N:O, 2, FALSE), 1), "") -> 0.8 | Z49: =IFERROR(VLOOKUP(I49, Summary!Q:R, 2, FALSE), 0) -> 3
A50: =I50 -> 100137 | B50: Audit | C50: Audit | D50: 45670 | E50: M3 | F50: =IFERROR(VLOOKUP(I50, 'Job Code Table'!D:E, 2, FALSE), "") -> Audit Director | G50: =VLOOKUP(I50, '[1]Job Mapping'!$B:$N, 13, FALSE) -> Director Audit | H50: =_xlfn.CONCAT(E50, "-", G50) -> M3-Director Audit | I50: 100137 | J50: Audit Director | K50: 2485 | L50: Peer - Global Network | M50: Exchange Job: Audit Director; Exchange: Global Network; Countries: USA; | N50: USD | O50: 165.6 | P50: 188.3 | Q50: 214.3 | T50: 193.1 | U50: 224.5 | V50: 259.1 | W50: =IFERROR(VLOOKUP(I50, Summary!K:L, 2, FALSE), "") -> 157.6 | X50: =IF(W50="","",W50/P50) -> 0.83696229 | Y50: =IFERROR(ROUND(VLOOKUP(I50, Summary!K:L, 2, FALSE)/VLOOKUP(I50, Summary!N:O, 2, FALSE), 1), "") -> 0.8 | Z50: =IFERROR(VLOOKUP(I50, Summary!Q:R, 2, FALSE), 0) -> 3
A51: =I51 -> 100137 | B51: Audit | C51: Audit | D51: 45670 | E51: M3 | F51: =IFERROR(VLOOKUP(I51, 'Job Code Table'!D:E, 2, FALSE), "") -> Audit Director | G51: =VLOOKUP(I51, '[1]Job Mapping'!$B:$N, 13, FALSE) -> Director Audit | H51: =_xlfn.CONCAT(E51, "-", G51) -> M3-Director Audit | I51: 100137 | J51: Audit - Multi-Focus - Director (M5) | K51: FI.IAMF.M5 | L51: Radford: Global Compensation Database 04/15/2022 | M51: United States// | N51: USD | O51: 174.8 | P51: 193.1 | Q51: 220.3 | T51: 185.4 | U51: 222.1 | V51: 261.3 | W51: =IFERROR(VLOOKUP(I51, Summary!K:L, 2, FALSE), "") -> 157.6 | X51: =IF(W51="","",W51/P51) -> 0.81615743 | Y51: =IFERROR(ROUND(VLOOKUP(I51, Summary!K:L, 2, FALSE)/VLOOKUP(I51, Summary!N:O, 2, FALSE), 1), "") -> 0.8 | Z51: =IFERROR(VLOOKUP(I51, Summary!Q:R, 2, FALSE), 0) -> 3
A52: =I52 -> 100137 | B52: Audit | C52: Audit | D52: 45670 | E52: M3 | F52: =IFERROR(VLOOKUP(I52, 'Job Code Table'!D:E, 2, FALSE), "") -> Audit Director | G52: =VLOOKUP(I52, '[1]Job Mapping'!$B:$N, 13, FALSE) -> Director Audit | H52: =_xlfn.CONCAT(E52, "-", G52) -> M3-Director Audit | I52: 100137 | J52: Audit and Financial/Business Controls|Audit and Financial/Business Controls Generalist/Multidiscipline|Senior Manager (Supervisory/Management)-M3-All Incumbent Global Grade | K52: AFU000-M3 | L52: Towers Watson: Financial Services MMPS 04/01/2024 | M52: Total Sample// | N52: USD | O52: 169.6 | P52: 190.9 | Q52: 222.3 | T52: 193 | U52: 220.4 | V52: 250.4 | W52: =IFERROR(VLOOKUP(I52, Summary!K:L, 2, FALSE), "") -> 157.6 | X52: =IF(W52="","",W52/P52) -> 0.82556312 | Y52: =IFERROR(ROUND(VLOOKUP(I52, Summary!K:L, 2, FALSE)/VLOOKUP(I52, Summary!N:O, 2, FALSE), 1), "") -> 0.8 | Z52: =IFERROR(VLOOKUP(I52, Summary!Q:R, 2, FALSE), 0) -> 3
A53: =I53 -> 100141 | B53: Audit | C53: Audit | D53: 45670 | E53: M4 | F53: =IFERROR(VLOOKUP(I53, 'Job Code Table'!D:E, 2, FALSE), "") -> Audit Senior Director | G53: =VLOOKUP(I53, '[1]Job Mapping'!$B:$N, 13, FALSE) -> Audit Senior Director | H53: =_xlfn.CONCAT(E53, "-", G53) -> M4-Audit Senior Director | I53: 100141 | J53: Audit Director Senior | K53: 11611 | L53: Peer - Global Network | M53: Exchange Job: Audit Director Senior; Exchange: Global Network; Countries: USA; | N53: USD | O53: 197.9 | P53: 223.2 | Q53: 260.2 | T53: 219 | U53: 244.5 | V53: 301.7 | W53: =IFERROR(VLOOKUP(I53, Summary!K:L, 2, FALSE), "") | X53: =IF(W53="","",W53/P53) | Y53: =IFERROR(ROUND(VLOOKUP(I53, Summary!K:L, 2, FALSE)/VLOOKUP(I53, Summary!N:O, 2, FALSE), 1), "") | Z53: =IFERROR(VLOOKUP(I53, Summary!Q:R, 2, FALSE), 0) -> 0
A54: =I54 -> 100141 | B54: Audit | C54: Audit | D54: 45670 | E54: M4 | F54: =IFERROR(VLOOKUP(I54, 'Job Code Table'!D:E, 2, FALSE), "") -> Audit Senior Director | G54: =VLOOKUP(I54, '[1]Job Mapping'!$B:$N, 13, FALSE) -> Audit Senior Director | H54: =_xlfn.CONCAT(E54, "-", G54) -> M4-Audit Senior Director | I54: 100141 | J54: Audit - Multi-Focus - Senior Director (M6) | K54: FI.IAMF.M6 | L54: Radford: Global Compensation Database 04/15/2022 | M54: United States// | N54: USD | O54: 207.4 | P54: 236 | Q54: 268.9 | T54: 234.4 | U54: 279.1 | V54: 339 | W54: =IFERROR(VLOOKUP(I54, Summary!K:L, 2, FALSE), "") | X54: =IF(W54="","",W54/P54) | Y54: =IFERROR(ROUND(VLOOKUP(I54, Summary!K:L, 2, FALSE)/VLOOKUP(I54, Summary!N:O, 2, FALSE), 1), "") | Z54: =IFERROR(VLOOKUP(I54, Summary!Q:R, 2, FALSE), 0) -> 0
A55: =I55 -> 100141 | B55: Audit | C55: Audit | D55: 45670 | E55: M4 | F55: =IFERROR(VLOOKUP(I55, 'Job Code Table'!D:E, 2, FALSE), "") -> Audit Senior Director | G55: =VLOOKUP(I55, '[1]Job Mapping'!$B:$N, 13, FALSE) -> Audit Senior Director | H55: =_xlfn.CONCAT(E55, "-", G55) -> M4-Audit Senior Director | I55: 100141 | J55: Audit and Financial/Business Controls|Audit and Financial/Business Controls Generalist/Multidiscipline|Group Manager (Supervisory/Management)-M4-All Incumbent Global Grade | K55: AFU000-M4 | L55: Towers Watson: Financial Services MMPS 04/01/2024 | M55: Total Sample// | N55: USD | O55: 195.2 | P55: 221.5 | Q55: 247.3 | T55: 236.9 | U55: 274.5 | V55: 310 | W55: =IFERROR(VLOOKUP(I55, Summary!K:L, 2, FALSE), "") | X55: =IF(W55="","",W55/P55) | Y55: =IFERROR(ROUND(VLOOKUP(I55, Summary!K:L, 2, FALSE)/VLOOKUP(I55, Summary!N:O, 2, FALSE), 1), "") | Z55: =IFERROR(VLOOKUP(I55, Summary!Q:R, 2, FALSE), 0) -> 0
A56: =I56 -> 100135 | B56: Audit | C56: Audit | D56: 45670 | E56: P1 | F56: =IFERROR(VLOOKUP(I56, 'Job Code Table'!D:E, 2, FALSE), "") -> Audit Analyst Associate | G56: =VLOOKUP(I56, '[1]Job Mapping'!$B:$N, 13, FALSE) -> Audit Analyst Associate | H56: =_xlfn.CONCAT(E56, "-", G56) -> P1-Audit Analyst Associate | I56: 100135 | J56: Internal Audit - Entry Professional (P1) | K56: LCA.05.000.P10 | L56: Mercer: MBD - Finance, Accounting, and Legal Report 03/01/2021 | M56: All Data// | N56: USD | O56: 57.3 | P56: 65.4 | Q56: 74.3 | T56: 58.6 | U56: 66.4 | V56: 76.2 | W56: =IFERROR(VLOOKUP(I56, Summary!K:L, 2, FALSE), "") | X56: =IF(W56="","",W56/P56) | Y56: =IFERROR(ROUND(VLOOKUP(I56, Summary!K:L, 2, FALSE)/VLOOKUP(I56, Summary!N:O, 2, FALSE), 1), "") | Z56: =IFERROR(VLOOKUP(I56, Summary!Q:R, 2, FALSE), 0) -> 0
A57: =I57 -> 100135 | B57: Audit | C57: Audit | D57: 45670 | E57: P1 | F57: =IFERROR(VLOOKUP(I57, 'Job Code Table'!D:E, 2, FALSE), "") -> Audit Analyst Associate | G57: =VLOOKUP(I57, '[1]Job Mapping'!$B:$N, 13, FALSE) -> Audit Analyst Associate | H57: =_xlfn.CONCAT(E57, "-", G57) -> P1-Audit Analyst Associate | I57: 100135 | J57: Auditor (Internal) I | K57: 2499 | L57: Peer - Global Network | M57: Exchange Job: Auditor (Internal) I; Exchange: Global Network; Countries: USA; | N57: USD | O57: 58.2 | P57: 67.8 | Q57: 76.2 | T57: 58.2 | U57: 67.8 | V57: 76.2 | W57: =IFERROR(VLOOKUP(I57, Summary!K:L, 2, FALSE), "") | X57: =IF(W57="","",W57/P57) | Y57: =IFERROR(ROUND(VLOOKUP(I57, Summary!K:L, 2, FALSE)/VLOOKUP(I57, Summary!N:O, 2, FALSE), 1), "") | Z57: =IFERROR(VLOOKUP(I57, Summary!Q:R, 2, FALSE), 0) -> 0
... A64: =I64 -> 100136 | B64: Audit | C64: Audit | D64: 45670 | E64: P3 | F64: =IFERROR(VLOOKUP(I64, 'Job Code Table'!D:E, 2, FALSE), "") -> Audit Analyst Senior | G64: =VLOOKUP(I64, '[1]Job Mapping'!$B:$N, 13, FALSE) -> Audit Analyst Senior | H64: =_xlfn.CONCAT(E64, "-", G64) -> P3-Audit Analyst Senior | I64: 100136 | J64: Internal Audit - Senior Professional (P3) | K64: LCA.05.000.P30 | L64: Mercer: MBD - Finance, Accounting, and Legal Report 03/01/2021 | M64: All Data// | N64: USD | O64: 88.1 | P64: 99.5 | Q64: 111.9 | T64: 90.8 | U64: 102.9 | V64: 118 | W64: =IFERROR(VLOOKUP(I64, Summary!K:L, 2, FALSE), "") -> 84.45 | X64: =IF(W64="","",W64/P64) -> 0.84874372 | Y64: =IFERROR(ROUND(VLOOKUP(I64, Summary!K:L, 2, FALSE)/VLOOKUP(I64, Summary!N:O, 2, FALSE), 1), "") -> 0.8 | Z64: =IFERROR(VLOOKUP(I64, Summary!Q:R, 2, FALSE), 0) -> 2
A65: =I65 -> 100136 | B65: Audit | C65: Audit | D65: 45670 | E65: P3 | F65: =IFERROR(VLOOKUP(I65, 'Job Code Table'!D:E, 2, FALSE), "") -> Audit Analyst Senior | G65: =VLOOKUP(I65, '[1]Job Mapping'!$B:$N, 13, FALSE) -> Audit Analyst Senior | H65: =_xlfn.CONCAT(E65, "-", G65) -> P3-Audit Analyst Senior | I65: 100136 | J65: Auditor (Internal) III | K65: 2491 | L65: Peer - Global Network | M65: Exchange Job: Auditor (Internal) III; Exchange: Global Network; Countries: USA; | N65: USD | O65: 67 | P65: 86.7 | Q65: 103.7 | T65: 80.7 | U65: 88.6 | V65: 106.5 | W65: =IFERROR(VLOOKUP(I65, Summary!K:L, 2, FALSE), "") -> 84.45 | X65: =IF(W65="","",W65/P65) -> 0.97404844 | Y65: =IFERROR(ROUND(VLOOKUP(I65, Summary!K:L, 2, FALSE)/VLOOKUP(I65, Summary!N:O, 2, FALSE), 1), "") -> 0.8 | Z65: =IFERROR(VLOOKUP(I65, Summary!Q:R, 2, FALSE), 0) -> 2 | AA65: Examine match; on par when organization weighted
A66: =I66 -> 100136 | B66: Audit | C66: Audit | D66: 45670 | E66: P3 | F66: =IFERROR(VLOOKUP(I66, 'Job Code Table'!D:E, 2, FALSE), "") -> Audit Analyst Senior | G66: =VLOOKUP(I66, '[1]Job Mapping'!$B:$N, 13, FALSE) -> Audit Analyst Senior | H66: =_xlfn.CONCAT(E66, "-", G66) -> P3-Audit Analyst Senior | I66: 100136 | J66: Audit - Multi-Focus - Career (P3) | K66: FI.IAMF.P3 | L66: Radford: Global Compensation Database 04/15/2022 | M66: United States// | N66: USD | O66: 92.1 | P66: 103.1 | Q66: 120.5 | T66: 95.9 | U66: 108.4 | V66: 129.2 | W66: =IFERROR(VLOOKUP(I66, Summary!K:L, 2, FALSE), "") -> 84.45 | X66: =IF(W66="","",W66/P66) -> 0.81910766 | Y66: =IFERROR(ROUND(VLOOKUP(I66, Summary!K:L, 2, FALSE)/VLOOKUP(I66, Summary!N:O, 2, FALSE), 1), "") -> 0.8 | Z66: =IFERROR(VLOOKUP(I66, Summary!Q:R, 2, FALSE), 0) -> 2
A67: =I67 -> 100136 | B67: Audit | C67: Audit | D67: 45670 | E67: P3 | F67: =IFERROR(VLOOKUP(I67, 'Job Code Table'!D:E, 2, FALSE), "") -> Audit Analyst Senior | G67: =VLOOKUP(I67, '[1]Job Mapping'!$B:$N, 13, FALSE) -> Audit Analyst Senior | H67: =_xlfn.CONCAT(E67, "-", G67) -> P3-Audit Analyst Senior | I67: 100136 | J67: Audit and Financial/Business Controls|Audit and Financial/Business Controls Generalist/Multidiscipline|Career (Professional)-P3-All Incumbent Global Grade | K67: AFU000-P3 | L67: Towers Watson: Financial Services MMPS 04/01/2024 | M67: Total Sample// | N67: USD | O67: 102.2 | P67: 115.7 | Q67: 136.4 | T67: 108.6 | U67: 124.8 | V67: 146.6 | W67: =IFERROR(VLOOKUP(I67, Summary!K:L, 2, FALSE), "") -> 84.45 | X67: =IF(W67="","",W67/P67) -> 0.72990493 | Y67: =IFERROR(ROUND(VLOOKUP(I67, Summary!K:L, 2, FALSE)/VLOOKUP(I67, Summary!N:O, 2, FALSE), 1), "") -> 0.8 | Z67: =IFERROR(VLOOKUP(I67, Summary!Q:R, 2, FALSE), 0) -> 2 | AA67: High, but confirmed job responsibilities
A68: =I68 -> 100140 | B68: Audit | C68: Audit | D68: 45670 | E68: P4 | F68: =IFERROR(VLOOKUP(I68, 'Job Code Table'!D:E, 2, FALSE), "") -> Audit Program Manager | G68: =VLOOKUP(I68, '[1]Job Mapping'!$B:$N, 13, FALSE) -> Audit Analyst Principal | H68: =_xlfn.CONCAT(E68, "-", G68) -> P4-Audit Analyst Principal | I68: 100140 | J68: Audit Principal | K68: 100138 | L68: Allianz Life Insurance Company Of North America Jobs | M68: Group:Insurance/Employees:All/Location:All | N68: USD | O68: 115.4 | P68: 130.5 | Q68: 152.5 | T68: 125 | U68: 141.7 | V68: 165.6 | W68: =IFERROR(VLOOKUP(I68, Summary!K:L, 2, FALSE), "") -> 140.93333 | X68: =IF(W68="","",W68/P68) -> 1.0799489 | Y68: =IFERROR(ROUND(VLOOKUP(I68, Summary!K:L, 2, FALSE)/VLOOKUP(I68, Summary!N:O, 2, FALSE), 1), "") -> 1.1 | Z68: =IFERROR(VLOOKUP(I68, Summary!Q:R, 2, FALSE), 0) -> 3 | AA68: Slot against principal
A69: =I69 -> 100138 | B69: Audit | C69: Audit | D69: 45670 | E69: P4 | F69: =IFERROR(VLOOKUP(I69, 'Job Code Table'!D:E, 2, FALSE), "") -> Audit Principal | G69: =VLOOKUP(I69, '[1]Job Mapping'!$B:$N, 13, FALSE) -> Audit Analyst Principal | H69: =_xlfn.CONCAT(E69, "-", G69) -> P4-Audit Analyst Principal | I69: 100138 | J69: Internal Audit - Specialist Professional (P4) | K69: LCA.05.000.P40 | L69: Mercer: MBD - Finance, Accounting, and Legal Report 03/01/2021 | M69: All Data// | N69: USD | O69: 107.4 | P69: 121.6 | Q69: 137.6 | T69: 113 | U69: 129.9 | V69: 147.6 | W69: =IFERROR(VLOOKUP(I69, Summary!K:L, 2, FALSE), "") -> 106.8375 | X69: =IF(W69="","",W69/P69) -> 0.87859786 | Y69: =IFERROR(ROUND(VLOOKUP(I69, Summary!K:L, 2, FALSE)/VLOOKUP(I69, Summary!N:O, 2, FALSE), 1), "") -> 0.8 | Z69: =IFERROR(VLOOKUP(I69, Summary!Q:R, 2, FALSE), 0) -> 8
A70: =I70 -> 100138 | B70: Audit | C70: Audit | D70: 45670 | E70: P4 | F70: =IFERROR(VLOOKUP(I70, 'Job Code Table'!D:E, 2, FALSE), "") -> Audit Principal | G70: =VLOOKUP(I70, '[1]Job Mapping'!$B:$N, 13, FALSE) -> Audit Analyst Principal | H70: =_xlfn.CONCAT(E70, "-", G70) -> P4-Audit Analyst Principal | I70: 100138 | J70: Auditor (Internal) IV | K70: 2502 | L70: Peer - Global Network | M70: Exchange Job: Auditor (Internal) IV; Exchange: Global Network; Countries: USA; | N70: USD | O70: 106.1 | P70: 119.4 | Q70: 133.6 | T70: 121.8 | U70: 134.2 | V70: 157.3 | W70: =IFERROR(VLOOKUP(I70, Summary!K:L, 2, FALSE), "") -> 106.8375 | X70: =IF(W70="","",W70/P70) -> 0.89478643 | Y70: =IFERROR(ROUND(VLOOKUP(I70, Summary!K:L, 2, FALSE)/VLOOKUP(I70, Summary!N:O, 2, FALSE), 1), "") -> 0.8 | Z70: =IFERROR(VLOOKUP(I70, Summary!Q:R, 2, FALSE), 0) -> 8
A71: =I71 -> 100138 | B71: Audit | C71: Audit | D71: 45670 | E71: P4 | F71: =IFERROR(VLOOKUP(I71, 'Job Code Table'!D:E, 2, FALSE), "") -> Audit Principal | G71: =VLOOKUP(I71, '[1]Job Mapping'!$B:$N, 13, FALSE) -> Audit Analyst Principal | H71: =_xlfn.CONCAT(E71, "-", G71) -> P4-Audit Analyst Principal | I71: 100138 | J71: Audit - Multi-Focus - Advanced (P4) | K71: FI.IAMF.P4 | L71: Radford: Global Compensation Database 04/15/2022 | M71: United States// | N71: USD | O71: 107.9 | P71: 123.9 | Q71: 139.1 | T71: 115 | U71: 131.8 | V71: 149.4 | W71: =IFERROR(VLOOKUP(I71, Summary!K:L, 2, FALSE), "") -> 106.8375 | X71: =IF(W71="","",W71/P71) -> 0.86228814 | Y71: =IFERROR(ROUND(VLOOKUP(I71, Summary!K:L, 2, FALSE)/VLOOKUP(I71, Summary!N:O, 2, FALSE), 1), "") -> 0.8 | Z71: =IFERROR(VLOOKUP(I71, Summary!Q:R, 2, FALSE), 0) -> 8
A72: =I72 -> 100138 | B72: Audit | C72: Audit | D72: 45670 | E72: P4 | F72: =IFERROR(VLOOKUP(I72, 'Job Code Table'!D:E, 2, FALSE), "") -> Audit Principal | G72: =VLOOKUP(I72, '[1]Job Mapping'!$B:$N, 13, FALSE) -> Audit Analyst Principal | H72: =_xlfn.CONCAT(E72, "-", G72) -> P4-Audit Analyst Principal | I72: 100138 | J72: Audit and Financial/Business Controls|Audit and Financial/Business Controls Generalist/Multidiscipline|Specialist (Professional)-P4-All Incumbent Global Grade | K72: AFU000-P4 | L72: Towers Watson: Financial Services MMPS 04/01/2024 | M72: Total Sample// | N72: USD | O72: 125.6 | P72: 143.6 | Q72: 174.7 | T72: 137.1 | U72: 158.8 | V72: 187.9 | W72: =IFERROR(VLOOKUP(I72, Summary!K:L, 2, FALSE), "") -> 106.8375 | X72: =IF(W72="","",W72/P72) -> 0.74399373 | Y72: =IFERROR(ROUND(VLOOKUP(I72, Summary!K:L, 2, FALSE)/VLOOKUP(I72, Summary!N:O, 2, FALSE), 1), "") -> 0.8 | Z72: =IFERROR(VLOOKUP(I72, Summary!Q:R, 2, FALSE), 0) -> 8 | AA72: High, but confirmed job responsibilities
A73: =I73 -> 101637 | B73: Data Analytics | C73: Data Engineering | D73: 45684 | E73: M2 | F73: =IFERROR(VLOOKUP(I73, 'Job Code Table'!D:E, 2, FALSE), "") -> Manager Data Engineering | G73: =VLOOKUP(I73, '[2]Job Mapping'!$B:$N, 13,FALSE) -> Senior Manager Data Engineering | H73: =_xlfn.CONCAT(E73, "-", G73) -> M2-Senior Manager Data Engineering | I73: 101637 | J73: Internal Data Engineering & Warehousing - Manager (M3) | K73: DAW.03.000.M30 | L73: Mercer: MBD - Information Technology Report 03/01/2021 | M73: All Data// | N73: USD | O73: 147.1 | P73: 161.6 | Q73: 172.8 | T73: 151.4 | U73: 168.7 | V73: 192.2 | W73: =IFERROR(VLOOKUP(I73, Summary!K:L, 2, FALSE), "") -> 150 | X73: =IF(W73="","",W73/P73) -> 0.92821782 | Y73: =IFERROR(ROUND(VLOOKUP(I73, Summary!K:L, 2, FALSE)/VLOOKUP(I73, Summary!N:O, 2, FALSE), 1), "") -> 0.9 | Z73: =IFERROR(VLOOKUP(I73, Summary!Q:R, 2, FALSE), 0) -> 1
A74: =I74 -> 101637 | B74: Data Analytics | C74: Data Engineering | D74: 45684 | E74: M2 | F74: =IFERROR(VLOOKUP(I74, 'Job Code Table'!D:E, 2, FALSE), "") -> Manager Data Engineering | G74: =VLOOKUP(I74, '[2]Job Mapping'!$B:$N, 13,FALSE) -> Senior Manager Data Engineering | H74: =_xlfn.CONCAT(E74, "-", G74) -> M2-Senior Manager Data Engineering | I74: 101637 | J74: Data Engineer Manager | K74: 1005 | L74: Peer - Global Network | M74: Exchange Job: Data Engineer Manager; Exchange: Global Network; Countries: USA; | N74: USD | O74: 155.1 | P74: 168.9 | Q74: 183.2 | T74: 163.5 | U74: 175.8 | V74: 209 | W74: =IFERROR(VLOOKUP(I74, Summary!K:L, 2, FALSE), "") -> 150 | X74: =IF(W74="","",W74/P74) -> 0.88809947 | Y74: =IFERROR(ROUND(VLOOKUP(I74, Summary!K:L, 2, FALSE)/VLOOKUP(I74, Summary!N:O, 2, FALSE), 1), "") -> 0.9 | Z74: =IFERROR(VLOOKUP(I74, Summary!Q:R, 2, FALSE), 0) -> 1 | AA74: Confirm responsibilities
A75: =I75 -> 101637 | B75: Data Analytics | C75: Data Engineering | D75: 45684 | E75: M2 | F75: =IFERROR(VLOOKUP(I75, 'Job Code Table'!D:E, 2, FALSE), "") -> Manager Data Engineering | G75: =VLOOKUP(I75, '[2]Job Mapping'!$B:$N, 13,FALSE) -> Senior Manager Data Engineering | H75: =_xlfn.CONCAT(E75, "-", G75) -> M2-Senior Manager Data Engineering | I75: 101637 | J75: Data Management - Data Engineer - Manager (M3) | K75: TE.DMDE.M3 | L75: Radford: Global Compensation Database 04/15/2022 | M75: United States// | N75: USD | O75: 139.8 | P75: 159.1 | Q75: 190 | T75: 147.7 | U75: 170.1 | V75: 197.6 | W75: =IFERROR(VLOOKUP(I75, Summary!K:L, 2, FALSE), "") -> 150 | X75: =IF(W75="","",W75/P75) -> 0.94280327 | Y75: =IFERROR(ROUND(VLOOKUP(I75, Summary!K:L, 2, FALSE)/VLOOKUP(I75, Summary!N:O, 2, FALSE), 1), "") -> 0.9 | Z75: =IFERROR(VLOOKUP(I75, Summary!Q:R, 2, FALSE), 0) -> 1
A76: =I76 -> 101637 | B76: Data Analytics | C76: Data Engineering | D76: 45684 | E76: M2 | F76: =IFERROR(VLOOKUP(I76, 'Job Code Table'!D:E, 2, FALSE), "") -> Manager Data Engineering | G76: =VLOOKUP(I76, '[2]Job Mapping'!$B:$N, 13,FALSE) -> Senior Manager Data Engineering | H76: =_xlfn.CONCAT(E76, "-", G76) -> M2-Senior Manager Data Engineering | I76: 101637 | J76: Data Science and Business Intelligence|Data Engineering|Manager (Supervisory/Management)-M2-All Incumbent Global Grade | K76: AEM060-M2 | L76: Towers Watson: Financial Services MMPS 04/01/2024 | M76: Total Sample// | N76: USD | O76: 156.2 | P76: 166 | Q76: 178.3 | T76: 180.6 | U76: 193.7 | V76: 215.8 | W76: =IFERROR(VLOOKUP(I76, Summary!K:L, 2, FALSE), "") -> 150 | X76: =IF(W76="","",W76/P76) -> 0.90361446 | Y76: =IFERROR(ROUND(VLOOKUP(I76, Summary!K:L, 2, FALSE)/VLOOKUP(I76, Summary!N:O, 2, FALSE), 1), "") -> 0.9 | Z76: =IFERROR(VLOOKUP(I76, Summary!Q:R, 2, FALSE), 0) -> 1
A77: =I77 -> DA-DE-M4 | B77: Data Analytics | C77: Data Engineering | D77: 45684 | E77: M4 | F77: =IFERROR(VLOOKUP(I77, 'Job Code Table'!D:E, 2, FALSE), "") | G77: =VLOOKUP(I77, '[2]Job Mapping'!$B:$N, 13,FALSE) -> Senior Director Data Engineering | H77: =_xlfn.CONCAT(E77, "-", G77) -> M4-Senior Director Data Engineering | I77: DA-DE-M4 | J77: Data Management - Data Engineer - Senior Director (M6) | K77: TE.DMDE.M6 | L77: Radford: Global Compensation Database 04/15/2022 | M77: United States// | N77: USD | O77: 215.1 | P77: 251.1 | Q77: 293.9 | T77: 258.1 | U77: 276.7 | V77: 323.9 | W77: =IFERROR(VLOOKUP(I77, Summary!K:L, 2, FALSE), "") | X77: =IF(W77="","",W77/P77) | Y77: =IFERROR(ROUND(VLOOKUP(I77, Summary!K:L, 2, FALSE)/VLOOKUP(I77, Summary!N:O, 2, FALSE), 1), "") | Z77: =IFERROR(VLOOKUP(I77, Summary!Q:R, 2, FALSE), 0) -> 0
A78: =I78 -> DA-DE-M4 | B78: Data Analytics | C78: Data Engineering | D78: 45684 | E78: M4 | F78: =IFERROR(VLOOKUP(I78, 'Job Code Table'!D:E, 2, FALSE), "") | G78: =VLOOKUP(I78, '[2]Job Mapping'!$B:$N, 13,FALSE) -> Senior Director Data Engineering | H78: =_xlfn.CONCAT(E78, "-", G78) -> M4-Senior Director Data Engineering | I78: DA-DE-M4 | J78: Data Science and Business Intelligence|Data Engineering|Group Manager (Supervisory/Management)-M4-All Incumbent Global Grade | K78: AEM060-M4 | L78: Towers Watson: Financial Services MMPS 04/01/2024 | M78: Total Sample// | N78: USD | O78: 216.8 | P78: 227.8 | Q78: 248.3 | T78: 267.2 | U78: 292.1 | V78: 325.2 | W78: =IFERROR(VLOOKUP(I78, Summary!K:L, 2, FALSE), "") | X78: =IF(W78="","",W78/P78) | Y78: =IFERROR(ROUND(VLOOKUP(I78, Summary!K:L, 2, FALSE)/VLOOKUP(I78, Summary!N:O, 2, FALSE), 1), "") | Z78: =IFERROR(VLOOKUP(I78, Summary!Q:R, 2, FALSE), 0) -> 0
A79: =I79 -> 101629 | B79: Data Analytics | C79: Data Engineering | D79: 45684 | E79: P1 | F79: =IFERROR(VLOOKUP(I79, 'Job Code Table'!D:E, 2, FALSE), "") -> Analytics Engineer Associate | G79: =VLOOKUP(I79, '[2]Job Mapping'!$B:$N, 13,FALSE) -> Data Engineer Associate | H79: =_xlfn.CONCAT(E79, "-", G79) -> P1-Data Engineer Associate | I79: 101629 | J79: Internal Data Engineering & Warehousing - Entry Professional (P1) | K79: DAW.03.000.P10 | L79: Mercer: MBD - Information Technology Report 03/01/2021 | M79: All Data// | N79: USD | O79: 61.3 | P79: 73.5 | Q79: 88.1 | T79: 61.8 | U79: 74.6 | V79: 89.9 | W79: =IFERROR(VLOOKUP(I79, Summary!K:L, 2, FALSE), "") | X79: =IF(W79="","",W79/P79) | Y79: =IFERROR(ROUND(VLOOKUP(I79, Summary!K:L, 2, FALSE)/VLOOKUP(I79, Summary!N:O, 2, FALSE), 1), "") | Z79: =IFERROR(VLOOKUP(I79, Summary!Q:R, 2, FALSE), 0) -> 0
A80: =I80 -> 101629 | B80: Data Analytics | C80: Data Engineering | D80: 45684 | E80: P1 | F80: =IFERROR(VLOOKUP(I80, 'Job Code Table'!D:E, 2, FALSE), "") -> Analytics Engineer Associate | G80: =VLOOKUP(I80, '[2]Job Mapping'!$B:$N, 13,FALSE) -> Data Engineer Associate | H80: =_xlfn.CONCAT(E80, "-", G80) -> P1-Data Engineer Associate | I80: 101629 | J80: Data Management - Data Engineer - Entry (P1) | K80: TE.DMDE.P1 | L80: Radford: Global Compensation Database 04/15/2022 | M80: United States// | N80: USD | O80: 71.3 | P80: 81.4 | Q80: 98.7 | T80: 71.4 | U80: 83.2 | V80: 100.2 | W80: =IFERROR(VLOOKUP(I80, Summary!K:L, 2, FALSE), "") | X80: =IF(W80="","",W80/P80) | Y80: =IFERROR(ROUND(VLOOKUP(I80, Summary!K:L, 2, FALSE)/VLOOKUP(I80, Summary!N:O, 2, FALSE), 1), "") | Z80: =IFERROR(VLOOKUP(I80, Summary!Q:R, 2, FALSE), 0) -> 0
A81: =I81 -> 101629 | B81: Data Analytics | C81: Data Engineering | D81: 45684 | E81: P1 | F81: =IFERROR(VLOOKUP(I81, 'Job Code Table'!D:E, 2, FALSE), "") -> Analytics Engineer Associate | G81: =VLOOKUP(I81, '[2]Job Mapping'!$B:$N, 13,FALSE) -> Data Engineer Associate | H81: =_xlfn.CONCAT(E81, "-", G81) -> P1-Data Engineer Associate | I81: 101629 | J81: Data Science and Business Intelligence|Data Engineering|Entry (Professional)-P1-All Incumbent Global Grade | K81: AEM060-P1 | L81: Towers Watson: Financial Services MMPS 04/01/2024 | M81: Total Sample// | N81: USD | O81: 78.2 | P81: 86.5 | Q81: 107.2 | T81: 84.6 | U81: 94 | V81: 115.8 | W81: =IFERROR(VLOOKUP(I81, Summary!K:L, 2, FALSE), "") | X81: =IF(W81="","",W81/P81) | Y81: =IFERROR(ROUND(VLOOKUP(I81, Summary!K:L, 2, FALSE)/VLOOKUP(I81, Summary!N:O, 2, FALSE), 1), "") | Z81: =IFERROR(VLOOKUP(I81, Summary!Q:R, 2, FALSE), 0) -> 0
A82: =I82 -> 101442 | B82: Data Analytics | C82: Data Engineering | D82: 45684 | E82: P2 | F82: =IFERROR(VLOOKUP(I82, 'Job Code Table'!D:E, 2, FALSE), "") -> Data Engineer | G82: =VLOOKUP(I82, '[2]Job Mapping'!$B:$N, 13,FALSE) -> Data Engineer | H82: =_xlfn.CONCAT(E82, "-", G82) -> P2-Data Engineer | I82: 101442 | J82: Internal Data Engineering & Warehousing - Experienced Professional (P2) | K82: DAW.03.000.P20 | L82: Mercer: MBD - Information Technology Report 03/01/2021 | M82: All Data// | N82: USD | O82: 89.1 | P82: 99 | Q82: 113 | T82: 90.4 | U82: 101.6 | V82: 115 | W82: =IFERROR(VLOOKUP(I82, Summary!K:L, 2, FALSE), "") | X82: =IF(W82="","",W82/P82) | Y82: =IFERROR(ROUND(VLOOKUP(I82, Summary!K:L, 2, FALSE)/VLOOKUP(I82, Summary!N:O, 2, FALSE), 1), "") | Z82: =IFERROR(VLOOKUP(I82, Summary!Q:R, 2, FALSE), 0) -> 0
A83: =I83 -> 101442 | B83: Data Analytics | C83: Data Engineering | D83: 45684 | E83: P2 | F83: =IFERROR(VLOOKUP(I83, 'Job Code Table'!D:E, 2, FALSE), "") -> Data Engineer | G83: =VLOOKUP(I83, '[2]Job Mapping'!$B:$N, 13,FALSE) -> Data Engineer | H83: =_xlfn.CONCAT(E83, "-", G83) -> P2-Data Engineer | I83: 101442 | J83: Data Engineer II | K83: 1008 | L83: Peer - Global Network | M83: Exchange Job: Data Engineer II; Exchange: Global Network; Countries: USA; | N83: USD | O83: 99.1 | P83: 116.1 | Q83: 137.4 | T83: 112.2 | U83: 134.5 | V83: 152.6 | W83: =IFERROR(VLOOKUP(I83, Summary!K:L, 2, FALSE), "") | X83: =IF(W83="","",W83/P83) | Y83: =IFERROR(ROUND(VLOOKUP(I83, Summary!K:L, 2, FALSE)/VLOOKUP(I83, Summary!N:O, 2, FALSE), 1), "") | Z83: =IFERROR(VLOOKUP(I83, Summary!Q:R, 2, FALSE), 0) -> 0
A84: =I84 -> 101442 | B84: Data Analytics | C84: Data Engineering | D84: 45684 | E84: P2 | F84: =IFERROR(VLOOKUP(I84, 'Job Code Table'!D:E, 2, FALSE), "") -> Data Engineer | G84: =VLOOKUP(I84, '[2]Job Mapping'!$B:$N, 13,FALSE) -> Data Engineer | H84: =_xlfn.CONCAT(E84, "-", G84) -> P2-Data Engineer | I84: 101442 | J84: Data Management - Data Engineer - Developing (P2) | K84: TE.DMDE.P2 | L84: Radford: Global Compensation Database 04/15/2022 | M84: United States// | N84: USD | O84: 100.7 | P84: 119.7 | Q84: 137.2 | T84: 104.3 | U84: 124.3 | V84: 138.3 | W84: =IFERROR(VLOOKUP(I84, Summary!K:L, 2, FALSE), "") | X84: =IF(W84="","",W84/P84) | Y84: =IFERROR(ROUND(VLOOKUP(I84, Summary!K:L, 2, FALSE)/VLOOKUP(I84, Summary!N:O, 2, FALSE), 1), "") | Z84: =IFERROR(VLOOKUP(I84, Summary!Q:R, 2, FALSE), 0) -> 0
A85: =I85 -> 101442 | B85: Data Analytics | C85: Data Engineering | D85: 45684 | E85: P2 | F85: =IFERROR(VLOOKUP(I85, 'Job Code Table'!D:E, 2, FALSE), "") -> Data Engineer | G85: =VLOOKUP(I85, '[2]Job Mapping'!$B:$N, 13,FALSE) -> Data Engineer | H85: =_xlfn.CONCAT(E85, "-", G85) -> P2-Data Engineer | I85: 101442 | J85: Data Science and Business Intelligence|Data Engineering|Intermediate (Professional)-P2-All Incumbent Global Grade | K85: AEM060-P2 | L85: Towers Watson: Financial Services MMPS 04/01/2024 | M85: Total Sample// | N85: USD | O85: 100.1 | P85: 114.4 | Q85: 129.3 | T85: 109.3 | U85: 125.4 | V85: 142.9 | W85: =IFERROR(VLOOKUP(I85, Summary!K:L, 2, FALSE), "") | X85: =IF(W85="","",W85/P85) | Y85: =IFERROR(ROUND(VLOOKUP(I85, Summary!K:L, 2, FALSE)/VLOOKUP(I85, Summary!N:O, 2, FALSE), 1), "") | Z85: =IFERROR(VLOOKUP(I85, Summary!Q:R, 2, FALSE), 0) -> 0
A86: =I86 -> 101611 | B86: Data Analytics | C86: Data Engineering | D86: 45684 | E86: P3 | F86: =IFERROR(VLOOKUP(I86, 'Job Code Table'!D:E, 2, FALSE), "") -> Analytics Engineer Senior | G86: =VLOOKUP(I86, '[2]Job Mapping'!$B:$N, 13,FALSE) -> Data Engineer Senior | H86: =_xlfn.CONCAT(E86, "-", G86) -> P3-Data Engineer Senior | I86: 101611 | J86: Internal Data Engineering & Warehousing - Senior Professional (P3) | K86: DAW.03.000.P30 | L86: Mercer: MBD - Information Technology Report 03/01/2021 | M86: All Data// | N86: USD | O86: 105.8 | P86: 120 | Q86: 135.6 | T86: 107.9 | U86: 123.4 | V86: 141.3 | W86: =IFERROR(VLOOKUP(I86, Summary!K:L, 2, FALSE), "") | X86: =IF(W86="","",W86/P86) | Y86: =IFERROR(ROUND(VLOOKUP(I86, Summary!K:L, 2, FALSE)/VLOOKUP(I86, Summary!N:O, 2, FALSE), 1), "") | Z86: =IFERROR(VLOOKUP(I86, Summary!Q:R, 2, FALSE), 0) -> 0
... A90: =I90 -> 101631 | B90: Data Analytics | C90: Data Engineering | D90: 45684 | E90: P4 | F90: =IFERROR(VLOOKUP(I90, 'Job Code Table'!D:E, 2, FALSE), "") -> Analytics Engineer Principal | G90: =VLOOKUP(I90, '[2]Job Mapping'!$B:$N, 13,FALSE) -> Data Engineer Principal | H90: =_xlfn.CONCAT(E90, "-", G90) -> P4-Data Engineer Principal | I90: 101631 | J90: Internal Data Engineering & Warehousing - Specialist Professional (P4) | K90: DAW.03.000.P40 | L90: Mercer: MBD - Information Technology Report 03/01/2021 | M90: All Data// | N90: USD | O90: 132 | P90: 147.9 | Q90: 163.3 | T90: 137.3 | U90: 154.4 | V90: 172.4 | W90: =IFERROR(VLOOKUP(I90, Summary!K:L, 2, FALSE), "") | X90: =IF(W90="","",W90/P90) | Y90: =IFERROR(ROUND(VLOOKUP(I90, Summary!K:L, 2, FALSE)/VLOOKUP(I90, Summary!N:O, 2, FALSE), 1), "") | Z90: =IFERROR(VLOOKUP(I90, Summary!Q:R, 2, FALSE), 0) -> 0
A91: =I91 -> 101631 | B91: Data Analytics | C91: Data Engineering | D91: 45684 | E91: P4 | F91: =IFERROR(VLOOKUP(I91, 'Job Code Table'!D:E, 2, FALSE), "") -> Analytics Engineer Principal | G91: =VLOOKUP(I91, '[2]Job Mapping'!$B:$N, 13,FALSE) -> Data Engineer Principal | H91: =_xlfn.CONCAT(E91, "-", G91) -> P4-Data Engineer Principal | I91: 101631 | J91: Data Engineer IV | K91: 13066 | L91: Peer - Global Network | M91: Exchange Job: Data Engineer IV; Exchange: Global Network; Countries: USA; | N91: USD | O91: 147 | P91: 161 | Q91: 171.7 | W91: =IFERROR(VLOOKUP(I91, Summary!K:L, 2, FALSE), "") | X91: =IF(W91="","",W91/P91) | Y91: =IFERROR(ROUND(VLOOKUP(I91, Summary!K:L, 2, FALSE)/VLOOKUP(I91, Summary!N:O, 2, FALSE), 1), "") | Z91: =IFERROR(VLOOKUP(I91, Summary!Q:R, 2, FALSE), 0) -> 0
A92: =I92 -> 101631 | B92: Data Analytics | C92: Data Engineering | D92: 45684 | E92: P4 | F92: =IFERROR(VLOOKUP(I92, 'Job Code Table'!D:E, 2, FALSE), "") -> Analytics Engineer Principal | G92: =VLOOKUP(I92, '[2]Job Mapping'!$B:$N, 13,FALSE) -> Data Engineer Principal | H92: =_xlfn.CONCAT(E92, "-", G92) -> P4-Data Engineer Principal | I92: 101631 | J92: Data Management - Data Engineer - Advanced (P4) | K92: TE.DMDE.P4 | L92: Radford: Global Compensation Database 04/15/2022 | M92: United States// | N92: USD | O92: 146.7 | P92: 169 | Q92: 199 | T92: 152.9 | U92: 176.1 | V92: 213.3 | W92: =IFERROR(VLOOKUP(I92, Summary!K:L, 2, FALSE), "") | X92: =IF(W92="","",W92/P92) | Y92: =IFERROR(ROUND(VLOOKUP(I92, Summary!K:L, 2, FALSE)/VLOOKUP(I92, Summary!N:O, 2, FALSE), 1), "") | Z92: =IFERROR(VLOOKUP(I92, Summary!Q:R, 2, FALSE), 0) -> 0
A93: =I93 -> 101631 | B93: Data Analytics | C93: Data Engineering | D93: 45684 | E93: P4 | F93: =IFERROR(VLOOKUP(I93, 'Job Code Table'!D:E, 2, FALSE), "") -> Analytics Engineer Principal | G93: =VLOOKUP(I93, '[2]Job Mapping'!$B:$N, 13,FALSE) -> Data Engineer Principal | H93: =_xlfn.CONCAT(E93, "-", G93) -> P4-Data Engineer Principal | I93: 101631 | J93: Data Science and Business Intelligence|Data Engineering|Specialist (Professional)-P4-All Incumbent Global Grade | K93: AEM060-P4 | L93: Towers Watson: Financial Services MMPS 04/01/2024 | M93: Total Sample// | N93: USD | O93: 146.2 | P93: 156 | Q93: 169.5 | T93: 164.7 | U93: 179.5 | V93: 198.3 | W93: =IFERROR(VLOOKUP(I93, Summary!K:L, 2, FALSE), "") | X93: =IF(W93="","",W93/P93) | Y93: =IFERROR(ROUND(VLOOKUP(I93, Summary!K:L, 2, FALSE)/VLOOKUP(I93, Summary!N:O, 2, FALSE), 1), "") | Z93: =IFERROR(VLOOKUP(I93, Summary!Q:R, 2, FALSE), 0) -> 0
A94: =I94 -> 101342 | B94: Data Analytics | C94: Data Reporting & Analysis | D94: 45684 | E94: M2 | F94: =IFERROR(VLOOKUP(I94, 'Job Code Table'!D:E, 2, FALSE), "") -> Manager Data & Analytics | G94: =VLOOKUP(I94, '[2]Job Mapping'!$B:$N, 13,FALSE) -> Senior Manager Data Reporting & Analysis | H94: =_xlfn.CONCAT(E94, "-", G94) -> M2-Senior Manager Data Reporting & Analysis | I94: 101342 | J94: Manager, Data Analysis | K94: 2730 | L94: Life Office Management Assoc: Non-Executive Compensation Survey 04/01/2024 | M94: Region/Midwest/ | N94: USD | O94: 123.9 | P94: 147.6 | Q94: 160.3 | T94: 148.5 | U94: 161.8 | V94: 184.1 | W94: =IFERROR(VLOOKUP(I94, Summary!K:L, 2, FALSE), "") -> 142.5 | X94: =IF(W94="","",W94/P94) -> 0.96544715 | Y94: =IFERROR(ROUND(VLOOKUP(I94, Summary!K:L, 2, FALSE)/VLOOKUP(I94, Summary!N:O, 2, FALSE), 1), "") -> 1 | Z94: =IFERROR(VLOOKUP(I94, Summary!Q:R, 2, FALSE), 0) -> 2
A95: =I95 -> 101342 | B95: Data Analytics | C95: Data Reporting & Analysis | D95: 45684 | E95: M2 | F95: =IFERROR(VLOOKUP(I95, 'Job Code Table'!D:E, 2, FALSE), "") -> Manager Data & Analytics | G95: =VLOOKUP(I95, '[2]Job Mapping'!$B:$N, 13,FALSE) -> Senior Manager Data Reporting & Analysis | H95: =_xlfn.CONCAT(E95, "-", G95) -> M2-Senior Manager Data Reporting & Analysis | I95: 101342 | J95: Business Intelligence (BI) Data Analysis - Manager (M3) | K95: DAW.02.055.M30 | L95: Mercer: MBD - Finance, Accounting, and Legal Report 03/01/2021 | M95: All Data// | N95: USD | O95: 128.5 | P95: 145.4 | Q95: 160 | T95: 136.3 | U95: 157.3 | V95: 178 | W95: =IFERROR(VLOOKUP(I95, Summary!K:L, 2, FALSE), "") -> 142.5 | X95: =IF(W95="","",W95/P95) -> 0.98005502 | Y95: =IFERROR(ROUND(VLOOKUP(I95, Summary!K:L, 2, FALSE)/VLOOKUP(I95, Summary!N:O, 2, FALSE), 1), "") -> 1 | Z95: =IFERROR(VLOOKUP(I95, Summary!Q:R, 2, FALSE), 0) -> 2
A96: =I96 -> 101342 | B96: Data Analytics | C96: Data Reporting & Analysis | D96: 45684 | E96: M2 | F96: =IFERROR(VLOOKUP(I96, 'Job Code Table'!D:E, 2, FALSE), "") -> Manager Data & Analytics | G96: =VLOOKUP(I96, '[2]Job Mapping'!$B:$N, 13,FALSE) -> Senior Manager Data Reporting & Analysis | H96: =_xlfn.CONCAT(E96, "-", G96) -> M2-Senior Manager Data Reporting & Analysis | I96: 101342 | J96: Corporate & Business Services - Data Analytics - All Focuses Roll-Up - Manager (M3) | K96: CB.DA00.M3 | L96: Radford: Global Compensation Database 04/15/2022 | M96: United States// | N96: USD | O96: 130.7 | P96: 150.4 | Q96: 174.3 | T96: 137.2 | U96: 162.6 | V96: 187.6 | W96: =IFERROR(VLOOKUP(I96, Summary!K:L, 2, FALSE), "") -> 142.5 | X96: =IF(W96="","",W96/P96) -> 0.9474734 | Y96: =IFERROR(ROUND(VLOOKUP(I96, Summary!K:L, 2, FALSE)/VLOOKUP(I96, Summary!N:O, 2, FALSE), 1), "") -> 1 | Z96: =IFERROR(VLOOKUP(I96, Summary!Q:R, 2, FALSE), 0) -> 2
A97: =I97 -> 101342 | B97: Data Analytics | C97: Data Reporting & Analysis | D97: 45684 | E97: M2 | F97: =IFERROR(VLOOKUP(I97, 'Job Code Table'!D:E, 2, FALSE), "") -> Manager Data & Analytics | G97: =VLOOKUP(I97, '[2]Job Mapping'!$B:$N, 13,FALSE) -> Senior Manager Data Reporting & Analysis | H97: =_xlfn.CONCAT(E97, "-", G97) -> M2-Senior Manager Data Reporting & Analysis | I97: 101342 | J97: Data Science and Business Intelligence|Business Data Analysis|Manager (Supervisory/Management)-M2-All Incumbent Global Grade | K97: AEM020-M2 | L97: Towers Watson: Financial Services MMPS 04/01/2024 | M97: Total Sample// | N97: USD | O97: 130.8 | P97: 145.3 | Q97: 165.5 | T97: 144.3 | U97: 164.6 | V97: 186.1 | W97: =IFERROR(VLOOKUP(I97, Summary!K:L, 2, FALSE), "") -> 142.5 | X97: =IF(W97="","",W97/P97) -> 0.98072953 | Y97: =IFERROR(ROUND(VLOOKUP(I97, Summary!K:L, 2, FALSE)/VLOOKUP(I97, Summary!N:O, 2, FALSE), 1), "") -> 1 | Z97: =IFERROR(VLOOKUP(I97, Summary!Q:R, 2, FALSE), 0) -> 2
A98: =I98 -> 100665 | B98: Data Analytics | C98: Data Reporting & Analysis | D98: 45684 | E98: M3 | F98: =IFERROR(VLOOKUP(I98, 'Job Code Table'!D:E, 2, FALSE), "") -> Director Data & Analytics | G98: =VLOOKUP(I98, '[2]Job Mapping'!$B:$N, 13,FALSE) -> Director Data Reporting & Analysis | H98: =_xlfn.CONCAT(E98, "-", G98) -> M3-Director Data Reporting & Analysis | I98: 100665 | J98: Business Intelligence (BI) Data Analysis - Senior Manager II (M5) | K98: DAW.02.055.M50 | L98: Mercer: MBD - Information Technology Report 03/01/2021 | M98: All Data// | N98: USD | O98: 192.1 | P98: 223.1 | Q98: 245 | T98: 213.1 | U98: 251.8 | V98: 299.6 | W98: =IFERROR(VLOOKUP(I98, Summary!K:L, 2, FALSE), "") -> 165.8 | X98: =IF(W98="","",W98/P98) -> 0.7431645 | Y98: =IFERROR(ROUND(VLOOKUP(I98, Summary!K:L, 2, FALSE)/VLOOKUP(I98, Summary!N:O, 2, FALSE), 1), "") -> 0.8 | Z98: =IFERROR(VLOOKUP(I98, Summary!Q:R, 2, FALSE), 0) -> 3
A99: =I99 -> 100665 | B99: Data Analytics | C99: Data Reporting & Analysis | D99: 45684 | E99: M3 | F99: =IFERROR(VLOOKUP(I99, 'Job Code Table'!D:E, 2, FALSE), "") -> Director Data & Analytics | G99: =VLOOKUP(I99, '[2]Job Mapping'!$B:$N, 13,FALSE) -> Director Data Reporting & Analysis | H99: =_xlfn.CONCAT(E99, "-", G99) -> M3-Director Data Reporting & Analysis | I99: 100665 | J99: Business Data Analysis Director | K99: 10721 | L99: Peer - Global Network | M99: United States | N99: USD | O99: 158.2 | P99: 187.2 | Q99: 210.8 | T99: 193.4 | U99: 220.9 | V99: 253.1 | W99: =IFERROR(VLOOKUP(I99, Summary!K:L, 2, FALSE), "") -> 165.8 | X99: =IF(W99="","",W99/P99) -> 0.88568376 | Y99: =IFERROR(ROUND(VLOOKUP(I99, Summary!K:L, 2, FALSE)/VLOOKUP(I99, Summary!N:O, 2, FALSE), 1), "") -> 0.8 | Z99: =IFERROR(VLOOKUP(I99, Summary!Q:R, 2, FALSE), 0) -> 3
A100: =I100 -> 100665 | B100: Data Analytics | C100: Data Reporting & Analysis | D100: 45684 | E100: M3 | F100: =IFERROR(VLOOKUP(I100, 'Job Code Table'!D:E, 2, FALSE), "") -> Director Data & Analytics | G100: =VLOOKUP(I100, '[2]Job Mapping'!$B:$N, 13,FALSE) -> Director Data Reporting & Analysis | H100: =_xlfn.CONCAT(E100, "-", G100) -> M3-Director Data Reporting & Analysis | I100: 100665 | J100: Corporate & Business Services - Data Analytics - All Focuses Roll-Up - Director (M5) | K100: CB.DA00.M5 | L100: Radford: Global Compensation Database 04/15/2022 | M100: United States// | N100: USD | O100: 192.1 | P100: 218.1 | Q100: 246.9 | T100: 209 | U100: 253.6 | V100: 298.5 | W100: =IFERROR(VLOOKUP(I100, Summary!K:L, 2, FALSE), "") -> 165.8 | X100: =IF(W100="","",W100/P100) -> 0.76020174 | Y100: =IFERROR(ROUND(VLOOKUP(I100, Summary!K:L, 2, FALSE)/VLOOKUP(I100, Summary!N:O, 2, FALSE), 1), "") -> 0.8 | Z100: =IFERROR(VLOOKUP(I100, Summary!Q:R, 2, FALSE), 0) -> 3
A101: =I101 -> 100665 | B101: Data Analytics | C101: Data Reporting & Analysis | D101: 45684 | E101: M3 | F101: =IFERROR(VLOOKUP(I101, 'Job Code Table'!D:E, 2, FALSE), "") -> Director Data & Analytics | G101: =VLOOKUP(I101, '[2]Job Mapping'!$B:$N, 13,FALSE) -> Director Data Reporting & Analysis | H101: =_xlfn.CONCAT(E101, "-", G101) -> M3-Director Data Reporting & Analysis | I101: 100665 | J101: Data Science and Business Intelligence|Business Data Analysis|Senior Manager (Supervisory/Management)-M3-All Incumbent Global Grade | K101: AEM020-M3 | L101: Towers Watson: Financial Services MMPS 04/01/2024 | M101: Total Sample// | N101: USD | O101: 141.3 | P101: 169.9 | Q101: 191.6 | T101: 162.3 | U101: 195.9 | V101: 227.5 | W101: =IFERROR(VLOOKUP(I101, Summary!K:L, 2, FALSE), "") -> 165.8 | X101: =IF(W101="","",W101/P101) -> 0.97586816 | Y101: =IFERROR(ROUND(VLOOKUP(I101, Summary!K:L, 2, FALSE)/VLOOKUP(I101, Summary!N:O, 2, FALSE), 1), "") -> 0.8 | Z101: =IFERROR(VLOOKUP(I101, Summary!Q:R, 2, FALSE), 0) -> 3
A102: =I102 -> 101643 | B102: Data Analytics | C102: Data Reporting & Analysis | D102: 45684 | E102: M4 | F102: =IFERROR(VLOOKUP(I102, 'Job Code Table'!D:E, 2, FALSE), "") -> Senior Director Data & Analytics | G102: =VLOOKUP(I102, '[2]Job Mapping'!$B:$N, 13,FALSE) -> Senior Director Data Reporting & Analysis | H102: =_xlfn.CONCAT(E102, "-", G102) -> M4-Senior Director Data Reporting & Analysis | I102: 101643 | J102: Business Data Analysis Director Senior | K102: 12122 | L102: Peer - Global Network | M102: Exchange Job: Business Data Analysis Director Senior; Exchange: Global Network; Countries: USA; | N102: USD | O102: 198.4 | P102: 223.9 | Q102: 244.3 | T102: 216.5 | U102: 261 | V102: 275.8 | W102: =IFERROR(VLOOKUP(I102, Summary!K:L, 2, FALSE), "") -> 193.35 | X102: =IF(W102="","",W102/P102) -> 0.86355516 | Y102: =IFERROR(ROUND(VLOOKUP(I102, Summary!K:L, 2, FALSE)/VLOOKUP(I102, Summary!N:O, 2, FALSE), 1), "") -> 0.8 | Z102: =IFERROR(VLOOKUP(I102, Summary!Q:R, 2, FALSE), 0) -> 2
A103: =I103 -> 101643 | B103: Data Analytics | C103: Data Reporting & Analysis | D103: 45684 | E103: M4 | F103: =IFERROR(VLOOKUP(I103, 'Job Code Table'!D:E, 2, FALSE), "") -> Senior Director Data & Analytics | G103: =VLOOKUP(I103, '[2]Job Mapping'!$B:$N, 13,FALSE) -> Senior Director Data Reporting & Analysis | H103: =_xlfn.CONCAT(E103, "-", G103) -> M4-Senior Director Data Reporting & Analysis | I103: 101643 | J103: Corporate & Business Services - Data Analytics - All Focuses Roll-Up - Senior Director (M6) | K103: CB.DA00.M6 | L103: Radford: Global Compensation Database 04/15/2022 | M103: United States// | N103: USD | O103: 229.3 | P103: 260.6 | Q103: 289.1 | T103: 263.4 | U103: 317.2 | V103: 373.9 | W103: =IFERROR(VLOOKUP(I103, Summary!K:L, 2, FALSE), "") -> 193.35 | X103: =IF(W103="","",W103/P103) -> 0.74194167 | Y103: =IFERROR(ROUND(VLOOKUP(I103, Summary!K:L, 2, FALSE)/VLOOKUP(I103, Summary!N:O, 2, FALSE), 1), "") -> 0.8 | Z103: =IFERROR(VLOOKUP(I103, Summary!Q:R, 2, FALSE), 0) -> 2
... A149: =I149 -> 100299 | B149: Data Analytics | C149: Data Science | D149: 45685 | E149: P4 | F149: =IFERROR(VLOOKUP(I149, 'Job Code Table'!D:E, 2, FALSE), "") -> Data Scientist Principal | G149: =VLOOKUP(I149, '[2]Job Mapping'!$B:$N, 13,FALSE) -> Data Science Analyst Principal | H149: =_xlfn.CONCAT(E149, "-", G149) -> P4-Data Science Analyst Principal | I149: 100299 | J149: Data Science and Business Intelligence|Data Science and Business Intelligence Generalist/Multidiscipline|Specialist (Professional)-P4-All Incumbent Global Grade | K149: AEM000-P4 | L149: Towers Watson: Financial Services MMPS 04/01/2024 | M149: Total Sample// | N149: USD | O149: 133.9 | P149: 150.4 | Q149: 170.3 | T149: 147.1 | U149: 172.9 | V149: 196.4 | W149: =IFERROR(VLOOKUP(I149, Summary!K:L, 2, FALSE), "") | X149: =IF(W149="","",W149/P149) | Y149: =IFERROR(ROUND(VLOOKUP(I149, Summary!K:L, 2, FALSE)/VLOOKUP(I149, Summary!N:O, 2, FALSE), 1), "") | Z149: =IFERROR(VLOOKUP(I149, Summary!Q:R, 2, FALSE), 0) -> 0
A150: =I150 -> 100795 | B150: Data Analytics | C150: Sales Enablement | D150: 45685 | E150: M2 | F150: =IFERROR(VLOOKUP(I150, 'Job Code Table'!D:E, 2, FALSE), "") -> Sales Enablement Manager | G150: =VLOOKUP(I150, '[2]Job Mapping'!$B:$N, 13,FALSE) -> Senior Manager Sales Enablement | H150: =_xlfn.CONCAT(E150, "-", G150) -> M2-Senior Manager Sales Enablement | I150: 100795 | J150: Sales Enablement - Manager (M3) | K150: SMP.11.011.M30 | L150: Mercer: MBD - Sales, Marketing, & Communications 03/01/2021 | M150: All Data// | N150: USD | O150: 125.8 | P150: 138.7 | Q150: 172.1 | T150: 156.4 | U150: 186.5 | V150: 267.2 | W150: =IFERROR(VLOOKUP(I150, Summary!K:L, 2, FALSE), "") | X150: =IF(W150="","",W150/P150) | Y150: =IFERROR(ROUND(VLOOKUP(I150, Summary!K:L, 2, FALSE)/VLOOKUP(I150, Summary!N:O, 2, FALSE), 1), "")
A151: =I151 -> 100795 | B151: Data Analytics | C151: Sales Enablement | D151: 45685 | E151: M2 | F151: =IFERROR(VLOOKUP(I151, 'Job Code Table'!D:E, 2, FALSE), "") -> Sales Enablement Manager | G151: =VLOOKUP(I151, '[2]Job Mapping'!$B:$N, 13,FALSE) -> Senior Manager Sales Enablement | H151: =_xlfn.CONCAT(E151, "-", G151) -> M2-Senior Manager Sales Enablement | I151: 100795 | J151: Operations / Sales Support - Sales Enablement - Manager (M3) | K151: SA.OPSE.M3 | L151: Radford: Global Compensation Database 04/15/2022 | M151: United States// | N151: USD | O151: 120.7 | P151: 142.7 | Q151: 169 | T151: 132.7 | U151: 170.7 | V151: 225.3 | W151: =IFERROR(VLOOKUP(I151, Summary!K:L, 2, FALSE), "") | X151: =IF(W151="","",W151/P151) | Y151: =IFERROR(ROUND(VLOOKUP(I151, Summary!K:L, 2, FALSE)/VLOOKUP(I151, Summary!N:O, 2, FALSE), 1), "") | Z151: =IFERROR(VLOOKUP(I151, Summary!Q:R, 2, FALSE), 0) -> 0
A152: =I152 -> 101291 | B152: Data Analytics | C152: Sales Enablement | D152: 45685 | E152: M3 | F152: =IFERROR(VLOOKUP(I152, 'Job Code Table'!D:E, 2, FALSE), "") -> Sales Enablement Director | G152: =VLOOKUP(I152, '[2]Job Mapping'!$B:$N, 13,FALSE) -> Director Sales Enablement | H152: =_xlfn.CONCAT(E152, "-", G152) -> M3-Director Sales Enablement | I152: 101291 | J152: Sales Enablement - Senior Manager (M4) | K152: SMP.11.011.M40 | L152: Mercer: MBD - Sales, Marketing, & Communications 03/01/2021 | M152: All Data// | N152: USD | O152: 139.8 | P152: 171.2 | Q152: 200 | T152: 139.8 | U152: 196.8 | V152: 264.4 | W152: =IFERROR(VLOOKUP(I152, Summary!K:L, 2, FALSE), "") -> 182.1 | X152: =IF(W152="","",W152/P152) -> 1.0636682 | Y152: =IFERROR(ROUND(VLOOKUP(I152, Summary!K:L, 2, FALSE)/VLOOKUP(I152, Summary!N:O, 2, FALSE), 1), "") -> 1
A153: =I153 -> 101291 | B153: Data Analytics | C153: Sales Enablement | D153: 45685 | E153: M3 | F153: =IFERROR(VLOOKUP(I153, 'Job Code Table'!D:E, 2, FALSE), "") -> Sales Enablement Director | G153: =VLOOKUP(I153, '[2]Job Mapping'!$B:$N, 13,FALSE) -> Director Sales Enablement | H153: =_xlfn.CONCAT(E153, "-", G153) -> M3-Director Sales Enablement | I153: 101291 | J153: Operations / Sales Support - Sales Enablement - Director (M5) | K153: SA.OPSE.M5 | L153: Radford: Global Compensation Database 04/15/2022 | M153: United States// | N153: USD | O153: 170.6 | P153: 192 | Q153: 215 | T153: 198.7 | U153: 225.4 | V153: 269 | W153: =IFERROR(VLOOKUP(I153, Summary!K:L, 2, FALSE), "") -> 182.1 | X153: =IF(W153="","",W153/P153) -> 0.9484375 | Y153: =IFERROR(ROUND(VLOOKUP(I153, Summary!K:L, 2, FALSE)/VLOOKUP(I153, Summary!N:O, 2, FALSE), 1), "") -> 1 | Z153: =IFERROR(VLOOKUP(I153, Summary!Q:R, 2, FALSE), 0) -> 1
A154: =I154 -> 100798 | B154: Data Analytics | C154: Sales Enablement | D154: 45685 | E154: M4 | F154: =IFERROR(VLOOKUP(I154, 'Job Code Table'!D:E, 2, FALSE), "") -> Sales Enablement Senior Director | G154: =VLOOKUP(I154, '[2]Job Mapping'!$B:$N, 13,FALSE) -> Senior Director Sales Enablement | H154: =_xlfn.CONCAT(E154, "-", G154) -> M4-Senior Director Sales Enablement | I154: 100798 | J154: Operations / Sales Support - Sales Enablement - Senior Director (M6) | K154: SA.OPSE.M6 | L154: Radford: Global Compensation Database 04/15/2022 | M154: United States// | N154: USD | O154: 210.7 | P154: 230.5 | Q154: 266.9 | T154: 236.7 | U154: 271.1 | V154: 313.2 | W154: =IFERROR(VLOOKUP(I154, Summary!K:L, 2, FALSE), "") -> 125.1 | X154: =IF(W154="","",W154/P154) -> 0.54273319 | Y154: =IFERROR(ROUND(VLOOKUP(I154, Summary!K:L, 2, FALSE)/VLOOKUP(I154, Summary!N:O, 2, FALSE), 1), "") -> 0.5 | Z154: =IFERROR(VLOOKUP(I154, Summary!Q:R, 2, FALSE), 0) -> 1
A155: =I155 -> 100794 | B155: Data Analytics | C155: Sales Enablement | D155: 45685 | E155: P2 | F155: =IFERROR(VLOOKUP(I155, 'Job Code Table'!D:E, 2, FALSE), "") -> Sales Enablement Analyst | G155: =VLOOKUP(I155, '[2]Job Mapping'!$B:$N, 13,FALSE) -> Sales Enablement Consultant | H155: =_xlfn.CONCAT(E155, "-", G155) -> P2-Sales Enablement Consultant | I155: 100794 | J155: Sales Enablement - Experienced Professional (P2) | K155: SMP.11.011.P20 | L155: Mercer: MBD - Sales, Marketing, & Communications 03/01/2021 | M155: All Data// | N155: USD | P155: 72.7 | U155: 76.6 | W155: =IFERROR(VLOOKUP(I155, Summary!K:L, 2, FALSE), "") -> 84.4 | X155: =IF(W155="","",W155/P155) -> 1.1609354 | Y155: =IFERROR(ROUND(VLOOKUP(I155, Summary!K:L, 2, FALSE)/VLOOKUP(I155, Summary!N:O, 2, FALSE), 1), "") -> 1.1
A156: =I156 -> 100794 | B156: Data Analytics | C156: Sales Enablement | D156: 45685 | E156: P2 | F156: =IFERROR(VLOOKUP(I156, 'Job Code Table'!D:E, 2, FALSE), "") -> Sales Enablement Analyst | G156: =VLOOKUP(I156, '[2]Job Mapping'!$B:$N, 13,FALSE) -> Sales Enablement Consultant | H156: =_xlfn.CONCAT(E156, "-", G156) -> P2-Sales Enablement Consultant | I156: 100794 | J156: Operations / Sales Support - Sales Enablement - Developing (P2) | K156: SA.OPSE.P2 | L156: Radford: Global Compensation Database 04/15/2022 | M156: United States// | N156: USD | O156: 71.6 | P156: 84.2 | Q156: 90 | T156: 78.8 | U156: 87.6 | V156: 97.5 | W156: =IFERROR(VLOOKUP(I156, Summary!K:L, 2, FALSE), "") -> 84.4 | X156: =IF(W156="","",W156/P156) -> 1.0023753 | Y156: =IFERROR(ROUND(VLOOKUP(I156, Summary!K:L, 2, FALSE)/VLOOKUP(I156, Summary!N:O, 2, FALSE), 1), "") -> 1.1 | Z156: =IFERROR(VLOOKUP(I156, Summary!Q:R, 2, FALSE), 0) -> 5
A157: =I157 -> 100797 | B157: Data Analytics | C157: Sales Enablement | D157: 45685 | E157: P3 | F157: =IFERROR(VLOOKUP(I157, 'Job Code Table'!D:E, 2, FALSE), "") -> Sales Enablement Principal | G157: =VLOOKUP(I157, '[2]Job Mapping'!$B:$N, 13,FALSE) -> Sales Enablement Consultant Senior | H157: =_xlfn.CONCAT(E157, "-", G157) -> P3-Sales Enablement Consultant Senior | I157: 100797 | J157: Analytics Consultant Senior | K157: 101561 | O157: 96.8 | P157: 109.8 | W157: =IFERROR(VLOOKUP(I157, Summary!K:L, 2, FALSE), "") | X157: =IF(W157="","",W157/P157) | Y157: =IFERROR(ROUND(VLOOKUP(I157, Summary!K:L, 2, FALSE)/VLOOKUP(I157, Summary!N:O, 2, FALSE), 1), "") | Z157: =IFERROR(VLOOKUP(I157, Summary!Q:R, 2, FALSE), 0) -> 0
A158: =I158 -> DA-SE-P4 | B158: Data Analytics | C158: Sales Enablement | D158: 45685 | E158: P4 | F158: =IFERROR(VLOOKUP(I158, 'Job Code Table'!D:E, 2, FALSE), "") | G158: =VLOOKUP(I158, '[2]Job Mapping'!$B:$N, 13,FALSE) -> Sales Enablement Consultant Principal | H158: =_xlfn.CONCAT(E158, "-", G158) -> P4-Sales Enablement Consultant Principal | I158: DA-SE-P4 | J158: Sales Enablement - Specialist Professional (P4) | K158: SMP.11.011.P40 | L158: Mercer: MBD - Sales, Marketing, & Communications 03/01/2021 | M158: All Data// | N158: USD | O158: 103.3 | P158: 122.2 | Q158: 147.6 | T158: 109 | U158: 133.2 | V158: 173 | W158: =IFERROR(VLOOKUP(I158, Summary!K:L, 2, FALSE), "") | X158: =IF(W158="","",W158/P158) | Y158: =IFERROR(ROUND(VLOOKUP(I158, Summary!K:L, 2, FALSE)/VLOOKUP(I158, Summary!N:O, 2, FALSE), 1), "")
A159: =I159 -> DA-SE-P4 | B159: Data Analytics | C159: Sales Enablement | D159: 45685 | E159: P4 | F159: =IFERROR(VLOOKUP(I159, 'Job Code Table'!D:E, 2, FALSE), "") | G159: =VLOOKUP(I159, '[2]Job Mapping'!$B:$N, 13,FALSE) -> Sales Enablement Consultant Principal | H159: =_xlfn.CONCAT(E159, "-", G159) -> P4-Sales Enablement Consultant Principal | I159: DA-SE-P4 | J159: Operations / Sales Support - Sales Enablement - Advanced (P4) | K159: SA.OPSE.P4 | L159: Radford: Global Compensation Database 04/15/2022 | M159: United States// | N159: USD | O159: 123.1 | P159: 142.7 | Q159: 164.6 | T159: 127.8 | U159: 154.6 | V159: 180.8 | W159: =IFERROR(VLOOKUP(I159, Summary!K:L, 2, FALSE), "") | X159: =IF(W159="","",W159/P159) | Y159: =IFERROR(ROUND(VLOOKUP(I159, Summary!K:L, 2, FALSE)/VLOOKUP(I159, Summary!N:O, 2, FALSE), 1), "") | Z159: =IFERROR(VLOOKUP(I159, Summary!Q:R, 2, FALSE), 0) -> 0
A160: =I160 -> DA-SE-P5 | B160: Data Analytics | C160: Sales Enablement | D160: 45685 | E160: P5 | F160: =IFERROR(VLOOKUP(I160, 'Job Code Table'!D:E, 2, FALSE), "") | G160: =VLOOKUP(I160, '[2]Job Mapping'!$B:$N, 13,FALSE) -> Sales Enablement Director | H160: =_xlfn.CONCAT(E160, "-", G160) -> P5-Sales Enablement Director | I160: DA-SE-P5 | J160: Sales Enablement - Expert Professional (P5) | K160: SMP.11.011.P50 | L160: Mercer: MBD - Sales, Marketing, & Communications 03/01/2021 | M160: All Data// | N160: USD | O160: 142.8 | P160: 169.8 | W160: =IFERROR(VLOOKUP(I160, Summary!K:L, 2, FALSE), "") | X160: =IF(W160="","",W160/P160) | Y160: =IFERROR(ROUND(VLOOKUP(I160, Summary!K:L, 2, FALSE)/VLOOKUP(I160, Summary!N:O, 2, FALSE), 1), "") | Z160: =IFERROR(VLOOKUP(I160, Summary!Q:R, 2, FALSE), 0) -> 0
A161: =I161 -> DA-SE-P5 | B161: Data Analytics | C161: Sales Enablement | D161: 45685 | E161: P5 | F161: =IFERROR(VLOOKUP(I161, 'Job Code Table'!D:E, 2, FALSE), "") | G161: =VLOOKUP(I161, '[2]Job Mapping'!$B:$N, 13,FALSE) -> Sales Enablement Director | H161: =_xlfn.CONCAT(E161, "-", G161) -> P5-Sales Enablement Director | I161: DA-SE-P5 | J161: Operations / Sales Support - Sales Enablement - Expert (P5) | K161: SA.OPSE.P5 | L161: Radford: Global Compensation Database 04/15/2022 | M161: United States// | N161: USD | O161: 142.8 | P161: 169.8 | Q161: 192.1 | T161: 101.8 | U161: 173.6 | V161: 207.3 | W161: =IFERROR(VLOOKUP(I161, Summary!K:L, 2, FALSE), "") | X161: =IF(W161="","",W161/P161) | Y161: =IFERROR(ROUND(VLOOKUP(I161, Summary!K:L, 2, FALSE)/VLOOKUP(I161, Summary!N:O, 2, FALSE), 1), "") | Z161: =IFERROR(VLOOKUP(I161, Summary!Q:R, 2, FALSE), 0) -> 0
A162: =I162 -> 100394 | B162: Finance | C162: Accounting | D162: 45671 | E162: M2 | F162: =IFERROR(VLOOKUP(I162, 'Job Code Table'!D:E, 2, FALSE), "") -> Financial Manager II | G162: =VLOOKUP(I162, '[1]Job Mapping'!$B:$N, 13, FALSE) -> Senior Manager Accounting | H162: =_xlfn.CONCAT(E162, "-", G162) -> M2-Senior Manager Accounting | I162: 100394 | J162: Accounting - Manager (M3) | K162: FIN.06.000.M30 | L162: Mercer: MBD - Finance, Accounting, and Legal Report 03/01/2021 | M162: All Data// | N162: USD | O162: 116.4 | P162: 133.2 | Q162: 151.3 | T162: 121.8 | U162: 141.4 | V162: 166.1 | W162: =IFERROR(VLOOKUP(I162, Summary!K:L, 2, FALSE), "") -> 146.275 | X162: =IF(W162="","",W162/P162) -> 1.0981607 | Y162: =IFERROR(ROUND(VLOOKUP(I162, Summary!K:L, 2, FALSE)/VLOOKUP(I162, Summary!N:O, 2, FALSE), 1), "") -> 1.2 | Z162: =IFERROR(VLOOKUP(I162, Summary!Q:R, 2, FALSE), 0) -> 4
A163: =I163 -> 100394 | B163: Finance | C163: Accounting | D163: 45671 | E163: M2 | F163: =IFERROR(VLOOKUP(I163, 'Job Code Table'!D:E, 2, FALSE), "") -> Financial Manager II | G163: =VLOOKUP(I163, '[1]Job Mapping'!$B:$N, 13, FALSE) -> Senior Manager Accounting | H163: =_xlfn.CONCAT(E163, "-", G163) -> M2-Senior Manager Accounting | I163: 100394 | J163: Accounting Manager | K163: 2464 | L163: Peer - Global Network | M163: Exchange Job: Accounting Manager; Exchange: Global Network; Countries: USA; | N163: USD | O163: 99.5 | P163: 117 | Q163: 136.2 | T163: 114 | U163: 135.8 | V163: 163.4 | W163: =IFERROR(VLOOKUP(I163, Summary!K:L, 2, FALSE), "") -> 146.275 | X163: =IF(W163="","",W163/P163) -> 1.2502137 | Y163: =IFERROR(ROUND(VLOOKUP(I163, Summary!K:L, 2, FALSE)/VLOOKUP(I163, Summary!N:O, 2, FALSE), 1), "") -> 1.2 | Z163: =IFERROR(VLOOKUP(I163, Summary!Q:R, 2, FALSE), 0) -> 4
A164: =I164 -> 100394 | B164: Finance | C164: Accounting | D164: 45671 | E164: M2 | F164: =IFERROR(VLOOKUP(I164, 'Job Code Table'!D:E, 2, FALSE), "") -> Financial Manager II | G164: =VLOOKUP(I164, '[1]Job Mapping'!$B:$N, 13, FALSE) -> Senior Manager Accounting | H164: =_xlfn.CONCAT(E164, "-", G164) -> M2-Senior Manager Accounting | I164: 100394 | J164: Accounting - Multi-Focus - Manager (M3) | K164: FI.ACMF.M3 | L164: Radford: Global Compensation Database 04/15/2022 | M164: United States// | N164: USD | O164: 112.3 | P164: 128.4 | Q164: 145.2 | T164: 118.5 | U164: 137.1 | V164: 159.2 | W164: =IFERROR(VLOOKUP(I164, Summary!K:L, 2, FALSE), "") -> 146.275 | X164: =IF(W164="","",W164/P164) -> 1.1392134 | Y164: =IFERROR(ROUND(VLOOKUP(I164, Summary!K:L, 2, FALSE)/VLOOKUP(I164, Summary!N:O, 2, FALSE), 1), "") -> 1.2 | Z164: =IFERROR(VLOOKUP(I164, Summary!Q:R, 2, FALSE), 0) -> 4
...

Sheet Employees
A1: Job Title | B1: Job Code | C1: Pay Market | D1: Name | E1: Employee ID | F1: MRP | G1: Job Base Rate | H1: Employee Annual Rate | I1: MRP | J1: TCC Amt | K1: % | L1: Source | M1: Comment | N1: Job Family | O1: Job Level | P1: WTW Benchmark | Q1: Chart
A2: Actuarial Analyst | B2: 100024 | C2: National | D2: Chloe Argue | E2: 10133710 | F2: National | G2: 88.4 | H2: 85 | I2: 96.2 | J2: 93.3 | K2: 85 | L2: 91.1 | N2: =VLOOKUP(B2,'New Matches'!A:B,2,FALSE) -> Actuarial | O2: =VLOOKUP(B2, 'New Matches'!A:I, 5, FALSE) -> P1 | P2: =IFERROR(VLOOKUP(O2, Summary!T:U, 2, FALSE), "") -> 0.13 | Q2: =IFERROR(VLOOKUP(Employees!O2, Summary!T:V, 3, FALSE), "") -> Professional
A3: Actuarial Analyst | B3: 100024 | C3: National | D3: Daniel Bell | E3: 10135617 | F3: National | G3: 88.4 | H3: 90 | I3: 101.8 | J3: 93.3 | K3: 90 | L3: 96.5 | N3: =VLOOKUP(B3,'New Matches'!A:B,2,FALSE) -> Actuarial | O3: =VLOOKUP(B3, 'New Matches'!A:I, 5, FALSE) -> P1 | P3: =IFERROR(VLOOKUP(O3, Summary!T:U, 2, FALSE), "") -> 0.13 | Q3: =IFERROR(VLOOKUP(Employees!O3, Summary!T:V, 3, FALSE), "") -> Professional
A4: Actuarial Analyst | B4: 100024 | C4: National | D4: Peter Brady | E4: 10133478 | F4: National | G4: 88.4 | H4: 89.5 | I4: 101.2 | J4: 93.3 | K4: 89.5 | L4: 95.9 | N4: =VLOOKUP(B4,'New Matches'!A:B,2,FALSE) -> Actuarial | O4: =VLOOKUP(B4, 'New Matches'!A:I, 5, FALSE) -> P1 | P4: =IFERROR(VLOOKUP(O4, Summary!T:U, 2, FALSE), "") -> 0.13 | Q4: =IFERROR(VLOOKUP(Employees!O4, Summary!T:V, 3, FALSE), "") -> Professional
A5: Actuarial Analyst | B5: 100024 | C5: National | D5: Zander Felde | E5: 10131626 | F5: National | G5: 88.4 | H5: 95 | I5: 107.5 | J5: 93.3 | K5: 95 | L5: 101.8 | N5: =VLOOKUP(B5,'New Matches'!A:B,2,FALSE) -> Actuarial | O5: =VLOOKUP(B5, 'New Matches'!A:I, 5, FALSE) -> P1 | P5: =IFERROR(VLOOKUP(O5, Summary!T:U, 2, FALSE), "") -> 0.13 | Q5: =IFERROR(VLOOKUP(Employees!O5, Summary!T:V, 3, FALSE), "") -> Professional
A6: Actuarial Analyst | B6: 100024 | C6: National | D6: Kevin Fernandez | E6: 10135195 | F6: National | G6: 88.4 | H6: 81.5 | I6: 92.2 | J6: 93.3 | K6: 81.5 | L6: 87.4 | N6: =VLOOKUP(B6,'New Matches'!A:B,2,FALSE) -> Actuarial | O6: =VLOOKUP(B6, 'New Matches'!A:I, 5, FALSE) -> P1 | P6: =IFERROR(VLOOKUP(O6, Summary!T:U, 2, FALSE), "") -> 0.13 | Q6: =IFERROR(VLOOKUP(Employees!O6, Summary!T:V, 3, FALSE), "") -> Professional
A7: Actuarial Analyst | B7: 100024 | C7: National | D7: Andrew Johnson | E7: 10133706 | F7: National | G7: 88.4 | H7: 91.5 | I7: 103.5 | J7: 93.3 | K7: 91.5 | L7: 98.1 | N7: =VLOOKUP(B7,'New Matches'!A:B,2,FALSE) -> Actuarial | O7: =VLOOKUP(B7, 'New Matches'!A:I, 5, FALSE) -> P1 | P7: =IFERROR(VLOOKUP(O7, Summary!T:U, 2, FALSE), "") -> 0.13 | Q7: =IFERROR(VLOOKUP(Employees!O7, Summary!T:V, 3, FALSE), "") -> Professional
A8: Actuarial Analyst | B8: 100024 | C8: National | D8: Nick Kirchner | E8: 10135213 | F8: National | G8: 88.4 | H8: 100 | I8: 113.1 | J8: 93.3 | K8: 100 | L8: 107.2 | N8: =VLOOKUP(B8,'New Matches'!A:B,2,FALSE) -> Actuarial | O8: =VLOOKUP(B8, 'New Matches'!A:I, 5, FALSE) -> P1 | P8: =IFERROR(VLOOKUP(O8, Summary!T:U, 2, FALSE), "") -> 0.13 | Q8: =IFERROR(VLOOKUP(Employees!O8, Summary!T:V, 3, FALSE), "") -> Professional
A9: Actuarial Analyst | B9: 100024 | C9: National | D9: Aron Ma | E9: 10135027 | F9: National | G9: 88.4 | H9: 92.5 | I9: 104.6 | J9: 93.3 | K9: 92.5 | L9: 99.1 | N9: =VLOOKUP(B9,'New Matches'!A:B,2,FALSE) -> Actuarial | O9: =VLOOKUP(B9, 'New Matches'!A:I, 5, FALSE) -> P1 | P9: =IFERROR(VLOOKUP(O9, Summary!T:U, 2, FALSE), "") -> 0.13 | Q9: =IFERROR(VLOOKUP(Employees!O9, Summary!T:V, 3, FALSE), "") -> Professional
A10: Actuarial Analyst | B10: 100024 | C10: National | D10: Katelyn Mamrick | E10: 10133719 | F10: National | G10: 88.4 | H10: 100.5 | I10: 113.7 | J10: 93.3 | K10: 100.5 | L10: 107.7 | N10: =VLOOKUP(B10,'New Matches'!A:B,2,FALSE) -> Actuarial | O10: =VLOOKUP(B10, 'New Matches'!A:I, 5, FALSE) -> P1 | P10: =IFERROR(VLOOKUP(O10, Summary!T:U, 2, FALSE), "") -> 0.13 | Q10: =IFERROR(VLOOKUP(Employees!O10, Summary!T:V, 3, FALSE), "") -> Professional
A11: Actuarial Analyst | B11: 100024 | C11: National | D11: Heidi Marg | E11: 10133713 | F11: National | G11: 88.4 | H11: 94.5 | I11: 106.9 | J11: 93.3 | K11: 94.5 | L11: 101.3 | N11: =VLOOKUP(B11,'New Matches'!A:B,2,FALSE) -> Actuarial | O11: =VLOOKUP(B11, 'New Matches'!A:I, 5, FALSE) -> P1 | P11: =IFERROR(VLOOKUP(O11, Summary!T:U, 2, FALSE), "") -> 0.13 | Q11: =IFERROR(VLOOKUP(Employees!O11, Summary!T:V, 3, FALSE), "") -> Professional
A12: Actuarial Analyst | B12: 100024 | C12: National | D12: Hannah Moses | E12: 10135747 | F12: National | G12: 88.4 | H12: 82.5 | I12: 93.3 | J12: 93.3 | K12: 82.5 | L12: 88.4 | N12: =VLOOKUP(B12,'New Matches'!A:B,2,FALSE) -> Actuarial | O12: =VLOOKUP(B12, 'New Matches'!A:I, 5, FALSE) -> P1 | P12: =IFERROR(VLOOKUP(O12, Summary!T:U, 2, FALSE), "") -> 0.13 | Q12: =IFERROR(VLOOKUP(Employees!O12, Summary!T:V, 3, FALSE), "") -> Professional
A13: Actuarial Analyst | B13: 100024 | C13: National | D13: Jordy Pauly | E13: 10135054 | F13: National | G13: 88.4 | H13: 90.5 | I13: 102.4 | J13: 93.3 | K13: 90.5 | L13: 97 | N13: =VLOOKUP(B13,'New Matches'!A:B,2,FALSE) -> Actuarial | O13: =VLOOKUP(B13, 'New Matches'!A:I, 5, FALSE) -> P1 | P13: =IFERROR(VLOOKUP(O13, Summary!T:U, 2, FALSE), "") -> 0.13 | Q13: =IFERROR(VLOOKUP(Employees!O13, Summary!T:V, 3, FALSE), "") -> Professional
... A96: Audit Director | B96: 100137 | C96: National | D96: David Johnson | E96: 10132089 | F96: National | G96: 187 | H96: 163.8 | I96: 87.6 | J96: 216.2 | K96: 163.8 | L96: 75.8 | N96: =VLOOKUP(B96,'New Matches'!A:B,2,FALSE) -> Audit | O96: =VLOOKUP(B96, 'New Matches'!A:I, 5, FALSE) -> M3 | P96: =IFERROR(VLOOKUP(O96, Summary!T:U, 2, FALSE), "") -> 0.31 | Q96: =IFERROR(VLOOKUP(Employees!O96, Summary!T:V, 3, FALSE), "") -> Management
A97: Audit Director | B97: 100137 | C97: National | D97: Lynn Johnson | E97: 10100256 | F97: National | G97: 187 | H97: 140 | I97: 74.9 | J97: 216.2 | K97: 140 | L97: 64.8 | M97: Evaluate if employee is leveled correctly based on market data | N97: =VLOOKUP(B97,'New Matches'!A:B,2,FALSE) -> Audit | O97: =VLOOKUP(B97, 'New Matches'!A:I, 5, FALSE) -> M3 | P97: =IFERROR(VLOOKUP(O97, Summary!T:U, 2, FALSE), "") -> 0.31 | Q97: =IFERROR(VLOOKUP(Employees!O97, Summary!T:V, 3, FALSE), "") -> Management
A98: Audit Analyst Senior | B98: 100136 | C98: National | D98: Mallory Meidl | E98: 10131271 | F98: National | G98: 101.3 | H98: 99.3 | I98: 98 | J98: 106.2 | K98: 99.3 | L98: 93.5 | N98: =VLOOKUP(B98,'New Matches'!A:B,2,FALSE) -> Audit | O98: =VLOOKUP(B98, 'New Matches'!A:I, 5, FALSE) -> P3 | P98: =IFERROR(VLOOKUP(O98, Summary!T:U, 2, FALSE), "") -> 0.33 | Q98: =IFERROR(VLOOKUP(Employees!O98, Summary!T:V, 3, FALSE), "") -> Professional
A99: Audit Analyst Senior | B99: 100136 | C99: National | D99: Tasha Scovill | E99: 10102174 | F99: National | G99: 101.3 | H99: 69.6 | I99: 68.7 | J99: 106.2 | K99: 69.6 | L99: 65.5 | M99: Evaluate if employee is leveled correctly based on market data | N99: =VLOOKUP(B99,'New Matches'!A:B,2,FALSE) -> Audit | O99: =VLOOKUP(B99, 'New Matches'!A:I, 5, FALSE) -> P3 | P99: =IFERROR(VLOOKUP(O99, Summary!T:U, 2, FALSE), "") -> 0.33 | Q99: =IFERROR(VLOOKUP(Employees!O99, Summary!T:V, 3, FALSE), "") -> Professional
A100: Audit Principal | B100: 100138 | C100: National | D100: Claire Chhettri | E100: 10135959 | F100: National | G100: 127.1 | H100: 118 | I100: 92.8 | J100: 138.7 | K100: 118 | L100: 85.1 | N100: =VLOOKUP(B100,'New Matches'!A:B,2,FALSE) -> Audit | O100: =VLOOKUP(B100, 'New Matches'!A:I, 5, FALSE) -> P4 | P100: =IFERROR(VLOOKUP(O100, Summary!T:U, 2, FALSE), "") -> 0.21 | Q100: =IFERROR(VLOOKUP(Employees!O100, Summary!T:V, 3, FALSE), "") -> Professional
A101: Audit Principal | B101: 100138 | C101: National | D101: Brett Goda | E101: 10136111 | F101: National | G101: 127.1 | H101: 105 | I101: 82.6 | J101: 138.7 | K101: 105 | L101: 75.7 | N101: =VLOOKUP(B101,'New Matches'!A:B,2,FALSE) -> Audit | O101: =VLOOKUP(B101, 'New Matches'!A:I, 5, FALSE) -> P4 | P101: =IFERROR(VLOOKUP(O101, Summary!T:U, 2, FALSE), "") -> 0.21 | Q101: =IFERROR(VLOOKUP(Employees!O101, Summary!T:V, 3, FALSE), "") -> Professional
A102: Audit Principal | B102: 100138 | C102: National | D102: Daniel Ludowese | E102: 10132219 | F102: National | G102: 127.1 | H102: 119 | I102: 93.6 | J102: 138.7 | K102: 119 | L102: 85.8 | N102: =VLOOKUP(B102,'New Matches'!A:B,2,FALSE) -> Audit | O102: =VLOOKUP(B102, 'New Matches'!A:I, 5, FALSE) -> P4 | P102: =IFERROR(VLOOKUP(O102, Summary!T:U, 2, FALSE), "") -> 0.21 | Q102: =IFERROR(VLOOKUP(Employees!O102, Summary!T:V, 3, FALSE), "") -> Professional
A103: Audit Principal | B103: 100138 | C103: National | D103: Lisa Manders | E103: 10101452 | F103: National | G103: 127.1 | H103: 89.3 | I103: 70.3 | J103: 138.7 | K103: 89.3 | L103: 64.4 | M103: Evaluate if employee is leveled correctly based on market data | N103: =VLOOKUP(B103,'New Matches'!A:B,2,FALSE) -> Audit | O103: =VLOOKUP(B103, 'New Matches'!A:I, 5, FALSE) -> P4 | P103: =IFERROR(VLOOKUP(O103, Summary!T:U, 2, FALSE), "") -> 0.21 | Q103: =IFERROR(VLOOKUP(Employees!O103, Summary!T:V, 3, FALSE), "") -> Professional
A104: Audit Principal | B104: 100138 | C104: National | D104: Emma Onyancha | E104: 10134558 | F104: National | G104: 127.1 | H104: 110 | I104: 86.5 | J104: 138.7 | K104: 110 | L104: 79.3 | N104: =VLOOKUP(B104,'New Matches'!A:B,2,FALSE) -> Audit | O104: =VLOOKUP(B104, 'New Matches'!A:I, 5, FALSE) -> P4 | P104: =IFERROR(VLOOKUP(O104, Summary!T:U, 2, FALSE), "") -> 0.21 | Q104: =IFERROR(VLOOKUP(Employees!O104, Summary!T:V, 3, FALSE), "") -> Professional
A105: Audit Principal | B105: 100138 | C105: National | D105: Katelynn Robinson | E105: 10101304 | F105: National | G105: 127.1 | H105: 97.6 | I105: 76.8 | J105: 138.7 | K105: 97.6 | L105: 70.4 | N105: =VLOOKUP(B105,'New Matches'!A:B,2,FALSE) -> Audit | O105: =VLOOKUP(B105, 'New Matches'!A:I, 5, FALSE) -> P4 | P105: =IFERROR(VLOOKUP(O105, Summary!T:U, 2, FALSE), "") -> 0.21 | Q105: =IFERROR(VLOOKUP(Employees!O105, Summary!T:V, 3, FALSE), "") -> Professional
A106: Audit Principal | B106: 100138 | C106: National | D106: Sarah Schwarzkopf | E106: 10134891 | F106: National | G106: 127.1 | H106: 98 | I106: 77.1 | J106: 138.7 | K106: 98 | L106: 70.7 | N106: =VLOOKUP(B106,'New Matches'!A:B,2,FALSE) -> Audit | O106: =VLOOKUP(B106, 'New Matches'!A:I, 5, FALSE) -> P4 | P106: =IFERROR(VLOOKUP(O106, Summary!T:U, 2, FALSE), "") -> 0.21 | Q106: =IFERROR(VLOOKUP(Employees!O106, Summary!T:V, 3, FALSE), "") -> Professional
A107: Audit Principal | B107: 100138 | C107: National | D107: Colette Tupy | E107: 10132290 | F107: National | G107: 127.1 | H107: 117.8 | I107: 92.7 | J107: 138.7 | K107: 117.8 | L107: 84.9 | N107: =VLOOKUP(B107,'New Matches'!A:B,2,FALSE) -> Audit | O107: =VLOOKUP(B107, 'New Matches'!A:I, 5, FALSE) -> P4 | P107: =IFERROR(VLOOKUP(O107, Summary!T:U, 2, FALSE), "") -> 0.21 | Q107: =IFERROR(VLOOKUP(Employees!O107, Summary!T:V, 3, FALSE), "") -> Professional
A108: Audit Program Manager | B108: 100140 | C108: National | D108: Lisa Clemens | E108: 10100266 | F108: National | G108: 130.5 | H108: 130.7 | I108: 100.2 | J108: 141.7 | K108: 130.7 | L108: 92.2 | N108: =VLOOKUP(B108,'New Matches'!A:B,2,FALSE) -> Audit | O108: =VLOOKUP(B108, 'New Matches'!A:I, 5, FALSE) -> P4 | P108: =IFERROR(VLOOKUP(O108, Summary!T:U, 2, FALSE), "") -> 0.21 | Q108: =IFERROR(VLOOKUP(Employees!O108, Summary!T:V, 3, FALSE), "") -> Professional
A109: Audit Program Manager | B109: 100140 | C109: National | D109: Mathias Int-Veen | E109: 15001913 | F109: National | G109: 130.5 | H109: 147.1 | I109: 112.7 | J109: 141.7 | K109: 147.1 | L109: 103.8 | N109: =VLOOKUP(B109,'New Matches'!A:B,2,FALSE) -> Audit | O109: =VLOOKUP(B109, 'New Matches'!A:I, 5, FALSE) -> P4 | P109: =IFERROR(VLOOKUP(O109, Summary!T:U, 2, FALSE), "") -> 0.21 | Q109: =IFERROR(VLOOKUP(Employees!O109, Summary!T:V, 3, FALSE), "") -> Professional
A110: Audit Program Manager | B110: 100140 | C110: National | D110: Michael Ritchie | E110: 10136009 | F110: National | G110: 130.5 | H110: 145 | I110: 111.1 | J110: 141.7 | K110: 145 | L110: 102.3 | N110: =VLOOKUP(B110,'New Matches'!A:B,2,FALSE) -> Audit | O110: =VLOOKUP(B110, 'New Matches'!A:I, 5, FALSE) -> P4 | P110: =IFERROR(VLOOKUP(O110, Summary!T:U, 2, FALSE), "") -> 0.21 | Q110: =IFERROR(VLOOKUP(Employees!O110, Summary!T:V, 3, FALSE), "") -> Professional
A111: Manager Data & Analytics | B111: 101342 | C111: National | D111: Arin Arpinar | E111: 10134236 | F111: National | G111: 145 | H111: 130 | I111: 89.7 | J111: 159.6 | K111: 130 | L111: 81.5 | N111: =VLOOKUP(B111,'New Matches'!A:B,2,FALSE) -> Data Analytics | O111: =VLOOKUP(B111, 'New Matches'!A:I, 5, FALSE) -> M2 | P111: =IFERROR(VLOOKUP(O111, Summary!T:U, 2, FALSE), "") -> 0.38 | Q111: =IFERROR(VLOOKUP(Employees!O111, Summary!T:V, 3, FALSE), "") -> Management
A112: Manager Data & Analytics | B112: 101342 | C112: National | D112: Lisa Tomasko | E112: 10100350 | F112: National | G112: 145 | H112: 155 | I112: 106.9 | J112: 159.6 | K112: 155 | L112: 97.1 | N112: =VLOOKUP(B112,'New Matches'!A:B,2,FALSE) -> Data Analytics | O112: =VLOOKUP(B112, 'New Matches'!A:I, 5, FALSE) -> M2 | P112: =IFERROR(VLOOKUP(O112, Summary!T:U, 2, FALSE), "") -> 0.38 | Q112: =IFERROR(VLOOKUP(Employees!O112, Summary!T:V, 3, FALSE), "") -> Management
A113: Manager Data Engineering | B113: 101637 | C113: National | D113: Oscar Kalipe | E113: 10134328 | F113: National | G113: 163.9 | H113: 150 | I113: 91.5 | J113: 177.1 | K113: 150 | L113: 84.7 | N113: =VLOOKUP(B113,'New Matches'!A:B,2,FALSE) -> Data Analytics | O113: =VLOOKUP(B113, 'New Matches'!A:I, 5, FALSE) -> M2 | P113: =IFERROR(VLOOKUP(O113, Summary!T:U, 2, FALSE), "") -> 0.38 | Q113: =IFERROR(VLOOKUP(Employees!O113, Summary!T:V, 3, FALSE), "") -> Management
A114: Data Science Director | B114: 100349 | C114: National | D114: Monica King | E114: 10130224 | F114: National | G114: 216.1 | H114: 195.8 | I114: 90.6 | J114: 255.3 | K114: 195.8 | L114: 76.7 | N114: =VLOOKUP(B114,'New Matches'!A:B,2,FALSE) -> Data Analytics | O114: =VLOOKUP(B114, 'New Matches'!A:I, 5, FALSE) -> M3 | P114: =IFERROR(VLOOKUP(O114, Summary!T:U, 2, FALSE), "") -> 0.31 | Q114: =IFERROR(VLOOKUP(Employees!O114, Summary!T:V, 3, FALSE), "") -> Management
A115: Director Data & Analytics | B115: 100665 | C115: National | D115: Kristine Arneson | E115: 10134798 | F115: National | G115: 199.6 | H115: 165 | I115: 82.7 | J115: 230.6 | K115: 165 | L115: 71.6 | N115: =VLOOKUP(B115,'New Matches'!A:B,2,FALSE) -> Data Analytics | O115: =VLOOKUP(B115, 'New Matches'!A:I, 5, FALSE) -> M3 | P115: =IFERROR(VLOOKUP(O115, Summary!T:U, 2, FALSE), "") -> 0.31 | Q115: =IFERROR(VLOOKUP(Employees!O115, Summary!T:V, 3, FALSE), "") -> Management
... A117: Director Data & Analytics | B117: 100665 | C117: National | D117: Andrew Morem | E117: 10101225 | F117: National | G117: 199.6 | H117: 155.6 | I117: 78 | J117: 230.6 | K117: 155.6 | L117: 67.5 | N117: =VLOOKUP(B117,'New Matches'!A:B,2,FALSE) -> Data Analytics | O117: =VLOOKUP(B117, 'New Matches'!A:I, 5, FALSE) -> M3 | P117: =IFERROR(VLOOKUP(O117, Summary!T:U, 2, FALSE), "") -> 0.31 | Q117: =IFERROR(VLOOKUP(Employees!O117, Summary!T:V, 3, FALSE), "") -> Management
A118: Senior Director Data & Analytics | B118: 101643 | C118: National | D118: Natalie Johnson | E118: 10100840 | F118: National | G118: 229.1 | H118: 170 | I118: 74.2 | J118: 276.1 | K118: 170 | L118: 61.6 | M118: Evaluate if employee is leveled correctly based on market data | N118: =VLOOKUP(B118,'New Matches'!A:B,2,FALSE) -> Data Analytics | O118: =VLOOKUP(B118, 'New Matches'!A:I, 5, FALSE) -> M4 | P118: =IFERROR(VLOOKUP(O118, Summary!T:U, 2, FALSE), "") -> 0.18 | Q118: =IFERROR(VLOOKUP(Employees!O118, Summary!T:V, 3, FALSE), "") -> Management
A119: Senior Director Data & Analytics | B119: 101643 | C119: National | D119: Tyler Mittelstadt | E119: 10131505 | F119: National | G119: 229.1 | H119: 216.7 | I119: 94.6 | J119: 276.1 | K119: 216.7 | L119: 78.5 | N119: =VLOOKUP(B119,'New Matches'!A:B,2,FALSE) -> Data Analytics | O119: =VLOOKUP(B119, 'New Matches'!A:I, 5, FALSE) -> M4 | P119: =IFERROR(VLOOKUP(O119, Summary!T:U, 2, FALSE), "") -> 0.18 | Q119: =IFERROR(VLOOKUP(Employees!O119, Summary!T:V, 3, FALSE), "") -> Management
A120: Analytics Consultant | B120: 101566 | C120: National | D120: Phil Johnson | E120: 10131662 | F120: National | G120: 86.2 | H120: 67 | I120: 77.7 | J120: 89.4 | K120: 67 | L120: 74.9 | N120: =VLOOKUP(B120,'New Matches'!A:B,2,FALSE) -> Data Analytics | O120: =VLOOKUP(B120, 'New Matches'!A:I, 5, FALSE) -> P2 | P120: =IFERROR(VLOOKUP(O120, Summary!T:U, 2, FALSE), "") -> 0.25 | Q120: =IFERROR(VLOOKUP(Employees!O120, Summary!T:V, 3, FALSE), "") -> Professional
A121: Analytics Consultant | B121: 101566 | C121: National | D121: Adam Schulz | E121: 10134153 | F121: National | G121: 86.2 | H121: 77.3 | I121: 89.7 | J121: 89.4 | K121: 77.3 | L121: 86.5 | N121: =VLOOKUP(B121,'New Matches'!A:B,2,FALSE) -> Data Analytics | O121: =VLOOKUP(B121, 'New Matches'!A:I, 5, FALSE) -> P2 | P121: =IFERROR(VLOOKUP(O121, Summary!T:U, 2, FALSE), "") -> 0.25 | Q121: =IFERROR(VLOOKUP(Employees!O121, Summary!T:V, 3, FALSE), "") -> Professional
A122: Data Scientist | B122: 100298 | C122: National | D122: Marissa Munley | E122: 10130434 | F122: National | G122: 124.6 | H122: 97.6 | I122: 78.3 | J122: 130.3 | K122: 97.6 | L122: 74.9 | N122: =VLOOKUP(B122,'New Matches'!A:B,2,FALSE) -> Data Analytics | O122: =VLOOKUP(B122, 'New Matches'!A:I, 5, FALSE) -> P2 | P122: =IFERROR(VLOOKUP(O122, Summary!T:U, 2, FALSE), "") -> 0.25 | Q122: =IFERROR(VLOOKUP(Employees!O122, Summary!T:V, 3, FALSE), "") -> Professional
A123: Data Scientist | B123: 100298 | C123: National | D123: Linh Nguyen | E123: 10133728 | F123: National | G123: 124.6 | H123: 120 | I123: 96.3 | J123: 130.3 | K123: 120 | L123: 92.1 | N123: =VLOOKUP(B123,'New Matches'!A:B,2,FALSE) -> Data Analytics | O123: =VLOOKUP(B123, 'New Matches'!A:I, 5, FALSE) -> P2 | P123: =IFERROR(VLOOKUP(O123, Summary!T:U, 2, FALSE), "") -> 0.25 | Q123: =IFERROR(VLOOKUP(Employees!O123, Summary!T:V, 3, FALSE), "") -> Professional
A124: Data Scientist | B124: 100298 | C124: National | D124: Yuria Utsumi | E124: 10135194 | F124: National | G124: 124.6 | H124: 107 | I124: 85.9 | J124: 130.3 | K124: 107 | L124: 82.1 | N124: =VLOOKUP(B124,'New Matches'!A:B,2,FALSE) -> Data Analytics | O124: =VLOOKUP(B124, 'New Matches'!A:I, 5, FALSE) -> P2 | P124: =IFERROR(VLOOKUP(O124, Summary!T:U, 2, FALSE), "") -> 0.25 | Q124: =IFERROR(VLOOKUP(Employees!O124, Summary!T:V, 3, FALSE), "") -> Professional
A125: Analytics Consultant Senior | B125: 101567 | C125: National | D125: Arghavan Abtahi | E125: 10101933 | F125: National | G125: 107.9 | H125: 82 | I125: 76 | J125: 112.9 | K125: 82 | L125: 72.6 | N125: =VLOOKUP(B125,'New Matches'!A:B,2,FALSE) -> Data Analytics | O125: =VLOOKUP(B125, 'New Matches'!A:I, 5, FALSE) -> P3 | P125: =IFERROR(VLOOKUP(O125, Summary!T:U, 2, FALSE), "") -> 0.33 | Q125: =IFERROR(VLOOKUP(Employees!O125, Summary!T:V, 3, FALSE), "") -> Professional
A126: Analytics Consultant Senior | B126: 101567 | C126: National | D126: Veneta Bebrevska-Nedelcheva | E126: 10100798 | F126: National | G126: 107.9 | H126: 94.1 | I126: 87.2 | J126: 112.9 | K126: 94.1 | L126: 83.3 | N126: =VLOOKUP(B126,'New Matches'!A:B,2,FALSE) -> Data Analytics | O126: =VLOOKUP(B126, 'New Matches'!A:I, 5, FALSE) -> P3 | P126: =IFERROR(VLOOKUP(O126, Summary!T:U, 2, FALSE), "") -> 0.33 | Q126: =IFERROR(VLOOKUP(Employees!O126, Summary!T:V, 3, FALSE), "") -> Professional
A127: Analytics Consultant Senior | B127: 101567 | C127: National | D127: Chris Edwards | E127: 10133477 | F127: National | G127: 107.9 | H127: 109.2 | I127: 101.2 | J127: 112.9 | K127: 109.2 | L127: 96.7 | N127: =VLOOKUP(B127,'New Matches'!A:B,2,FALSE) -> Data Analytics | O127: =VLOOKUP(B127, 'New Matches'!A:I, 5, FALSE) -> P3 | P127: =IFERROR(VLOOKUP(O127, Summary!T:U, 2, FALSE), "") -> 0.33 | Q127: =IFERROR(VLOOKUP(Employees!O127, Summary!T:V, 3, FALSE), "") -> Professional
A128: Analytics Consultant Senior | B128: 101567 | C128: National | D128: SeQuoya Robinson | E128: 10131398 | F128: National | G128: 107.9 | H128: 92 | I128: 85.3 | J128: 112.9 | K128: 92 | L128: 81.5 | N128: =VLOOKUP(B128,'New Matches'!A:B,2,FALSE) -> Data Analytics | O128: =VLOOKUP(B128, 'New Matches'!A:I, 5, FALSE) -> P3 | P128: =IFERROR(VLOOKUP(O128, Summary!T:U, 2, FALSE), "") -> 0.33 | Q128: =IFERROR(VLOOKUP(Employees!O128, Summary!T:V, 3, FALSE), "") -> Professional
A129: Analytics Consultant Senior | B129: 101567 | C129: National | D129: Cole Schnichels | E129: 10134591 | F129: National | G129: 107.9 | H129: 88 | I129: 81.6 | J129: 112.9 | K129: 88 | L129: 77.9 | N129: =VLOOKUP(B129,'New Matches'!A:B,2,FALSE) -> Data Analytics | O129: =VLOOKUP(B129, 'New Matches'!A:I, 5, FALSE) -> P3 | P129: =IFERROR(VLOOKUP(O129, Summary!T:U, 2, FALSE), "") -> 0.33 | Q129: =IFERROR(VLOOKUP(Employees!O129, Summary!T:V, 3, FALSE), "") -> Professional
A130: Analytics Consultant Senior | B130: 101567 | C130: National | D130: Jonathan Shaheen | E130: 10133350 | F130: National | G130: 107.9 | H130: 95.7 | I130: 88.7 | J130: 112.9 | K130: 95.7 | L130: 84.8 | N130: =VLOOKUP(B130,'New Matches'!A:B,2,FALSE) -> Data Analytics | O130: =VLOOKUP(B130, 'New Matches'!A:I, 5, FALSE) -> P3 | P130: =IFERROR(VLOOKUP(O130, Summary!T:U, 2, FALSE), "") -> 0.33 | Q130: =IFERROR(VLOOKUP(Employees!O130, Summary!T:V, 3, FALSE), "") -> Professional
... A146: Data Science Manager | B146: 101936 | C146: National | D146: Sara Spring | E146: 10130772 | F146: National | G146: 175.5 | H146: 155 | I146: 88.3 | J146: 195 | K146: 155 | L146: 79.5 | N146: =VLOOKUP(B146,'New Matches'!A:B,2,FALSE) -> Data Analytics | O146: =VLOOKUP(B146, 'New Matches'!A:I, 5, FALSE) -> P4 | P146: =IFERROR(VLOOKUP(O146, Summary!T:U, 2, FALSE), "") -> 0.21 | Q146: =IFERROR(VLOOKUP(Employees!O146, Summary!T:V, 3, FALSE), "") -> Professional
A147: Web Analytics Manager | B147: 100933 | C147: National | D147: Nicholas Quandt | E147: 10132786 | F147: =F142 -> National | G147: =G142 -> 131.2 | H147: 130.7 | I147: =ROUND(H147/G142*100,1) -> 99.6 | J147: =J142 -> 142 | K147: 130.7 | L147: =ROUND(K147/J142*100,1) -> 92 | N147: =VLOOKUP(B147,'New Matches'!A:B,2,FALSE) -> Data Analytics | O147: =VLOOKUP(B147, 'New Matches'!A:I, 5, FALSE) -> P4 | P147: =IFERROR(VLOOKUP(O147, Summary!T:U, 2, FALSE), "") -> 0.21 | Q147: =IFERROR(VLOOKUP(Employees!O147, Summary!T:V, 3, FALSE), "") -> Professional
A148: Tax Manager | B148: 100005 | C148: National | D148: Sarah Blommel | E148: 10105146 | F148: National | G148: 115.1 | H148: 117 | I148: 101.7 | J148: 129.9 | K148: 117 | L148: 90.1 | N148: =VLOOKUP(B148,'New Matches'!A:B,2,FALSE) -> Finance | O148: =VLOOKUP(B148, 'New Matches'!A:I, 5, FALSE) -> M1 | P148: =IFERROR(VLOOKUP(O148, Summary!T:U, 2, FALSE), "") -> 0.13 | Q148: =IFERROR(VLOOKUP(Employees!O148, Summary!T:V, 3, FALSE), "") -> Management
A149: Tax Manager | B149: 100005 | C149: National | D149: Kelly Harrison | E149: 10105149 | F149: National | G149: 115.1 | H149: 156 | I149: 135.5 | J149: 129.9 | K149: 156 | L149: 120.1 | N149: =VLOOKUP(B149,'New Matches'!A:B,2,FALSE) -> Finance | O149: =VLOOKUP(B149, 'New Matches'!A:I, 5, FALSE) -> M1 | P149: =IFERROR(VLOOKUP(O149, Summary!T:U, 2, FALSE), "") -> 0.13 | Q149: =IFERROR(VLOOKUP(Employees!O149, Summary!T:V, 3, FALSE), "") -> Management
A150: Tax Manager | B150: 100005 | C150: National | D150: Sarah Hussong | E150: 15011081 | F150: National | G150: 115.1 | H150: 115 | I150: 99.9 | J150: 129.9 | K150: 115 | L150: 88.5 | N150: =VLOOKUP(B150,'New Matches'!A:B,2,FALSE) -> Finance | O150: =VLOOKUP(B150, 'New Matches'!A:I, 5, FALSE) -> M1 | P150: =IFERROR(VLOOKUP(O150, Summary!T:U, 2, FALSE), "") -> 0.13 | Q150: =IFERROR(VLOOKUP(Employees!O150, Summary!T:V, 3, FALSE), "") -> Management
A151: Tax Manager | B151: 100005 | C151: National | D151: Jamie Laird | E151: 10105153 | F151: National | G151: 115.1 | H151: 137.5 | I151: 119.5 | J151: 129.9 | K151: 137.5 | L151: 105.9 | M151: Evaluate if employee is leveled correctly based on market data | N151: =VLOOKUP(B151,'New Matches'!A:B,2,FALSE) -> Finance | O151: =VLOOKUP(B151, 'New Matches'!A:I, 5, FALSE) -> M1 | P151: =IFERROR(VLOOKUP(O151, Summary!T:U, 2, FALSE), "") -> 0.13 | Q151: =IFERROR(VLOOKUP(Employees!O151, Summary!T:V, 3, FALSE), "") -> Management
A152: Tax Manager | B152: 100005 | C152: National | D152: Perry Wells | E152: 15016684 | F152: National | G152: 115.1 | H152: 142.3 | I152: 123.6 | J152: 129.9 | K152: 142.3 | L152: 109.5 | M152: Evaluate if employee is leveled correctly based on market data | N152: =VLOOKUP(B152,'New Matches'!A:B,2,FALSE) -> Finance | O152: =VLOOKUP(B152, 'New Matches'!A:I, 5, FALSE) -> M1 | P152: =IFERROR(VLOOKUP(O152, Summary!T:U, 2, FALSE), "") -> 0.13 | Q152: =IFERROR(VLOOKUP(Employees!O152, Summary!T:V, 3, FALSE), "") -> Management
A153: Financial Manager II | B153: 100394 | C153: National | D153: Ryan Duffy | E153: 10101929 | F153: National | G153: 127.1 | H153: 144.1 | I153: 113.4 | J153: 140.1 | K153: 144.1 | L153: 102.9 | N153: =VLOOKUP(B153,'New Matches'!A:B,2,FALSE) -> Finance | O153: =VLOOKUP(B153, 'New Matches'!A:I, 5, FALSE) -> M2 | P153: =IFERROR(VLOOKUP(O153, Summary!T:U, 2, FALSE), "") -> 0.38 | Q153: =IFERROR(VLOOKUP(Employees!O153, Summary!T:V, 3, FALSE), "") -> Management
A154: Financial Manager II | B154: 100394 | C154: National | D154: Matt Nelson | E154: 10100809 | F154: National | G154: 127.1 | H154: 138.3 | I154: 108.8 | J154: 140.1 | K154: 138.3 | L154: 98.7 | N154: =VLOOKUP(B154,'New Matches'!A:B,2,FALSE) -> Finance | O154: =VLOOKUP(B154, 'New Matches'!A:I, 5, FALSE) -> M2 | P154: =IFERROR(VLOOKUP(O154, Summary!T:U, 2, FALSE), "") -> 0.38 | Q154: =IFERROR(VLOOKUP(Employees!O154, Summary!T:V, 3, FALSE), "") -> Management
A155: Financial Manager II | B155: 100394 | C155: National | D155: Pete Sanchez | E155: 10101132 | F155: National | G155: 127.1 | H155: 133.9 | I155: 105.4 | J155: 140.1 | K155: 133.9 | L155: 95.6 | N155: =VLOOKUP(B155,'New Matches'!A:B,2,FALSE) -> Finance | O155: =VLOOKUP(B155, 'New Matches'!A:I, 5, FALSE) -> M2 | P155: =IFERROR(VLOOKUP(O155, Summary!T:U, 2, FALSE), "") -> 0.38 | Q155: =IFERROR(VLOOKUP(Employees!O155, Summary!T:V, 3, FALSE), "") -> Management
A156: Financial Manager II | B156: 100394 | C156: National | D156: Josh Schaefgen | E156: 10100509 | F156: National | G156: 127.1 | H156: 168.8 | I156: 132.8 | J156: 140.1 | K156: 168.8 | L156: 120.5 | N156: =VLOOKUP(B156,'New Matches'!A:B,2,FALSE) -> Finance | O156: =VLOOKUP(B156, 'New Matches'!A:I, 5, FALSE) -> M2 | P156: =IFERROR(VLOOKUP(O156, Summary!T:U, 2, FALSE), "") -> 0.38 | Q156: =IFERROR(VLOOKUP(Employees!O156, Summary!T:V, 3, FALSE), "") -> Management
A157: Tax Senior Manager | B157: 100007 | C157: National | D157: Kari Pederson | E157: 10105150 | F157: National | G157: 142 | H157: 188.6 | I157: 132.8 | J157: 158 | K157: 188.6 | L157: 119.4 | N157: =VLOOKUP(B157,'New Matches'!A:B,2,FALSE) -> Finance | O157: =VLOOKUP(B157, 'New Matches'!A:I, 5, FALSE) -> M2 | P157: =IFERROR(VLOOKUP(O157, Summary!T:U, 2, FALSE), "") -> 0.38 | Q157: =IFERROR(VLOOKUP(Employees!O157, Summary!T:V, 3, FALSE), "") -> Management
A158: Tax Senior Manager | B158: 100007 | C158: National | D158: Brett Wahl | E158: 10105148 | F158: National | G158: 142 | H158: 166.2 | I158: 117 | J158: 158 | K158: 166.2 | L158: 105.2 | N158: =VLOOKUP(B158,'New Matches'!A:B,2,FALSE) -> Finance | O158: =VLOOKUP(B158, 'New Matches'!A:I, 5, FALSE) -> M2 | P158: =IFERROR(VLOOKUP(O158, Summary!T:U, 2, FALSE), "") -> 0.38 | Q158: =IFERROR(VLOOKUP(Employees!O158, Summary!T:V, 3, FALSE), "") -> Management
A159: Financial Director | B159: 100391 | C159: National | D159: Tammy Knoblauch | E159: 10100034 | F159: National | G159: 178.4 | H159: 194.7 | I159: 109.1 | J159: 204.5 | K159: 194.7 | L159: 95.2 | N159: =VLOOKUP(B159,'New Matches'!A:B,2,FALSE) -> Finance | O159: =VLOOKUP(B159, 'New Matches'!A:I, 5, FALSE) -> M3 | P159: =IFERROR(VLOOKUP(O159, Summary!T:U, 2, FALSE), "") -> 0.31 | Q159: =IFERROR(VLOOKUP(Employees!O159, Summary!T:V, 3, FALSE), "") -> Management
A160: Financial Director | B160: 100391 | C160: National | D160: Logan McKenzie | E160: 15000956 | F160: National | G160: 178.4 | H160: 150 | I160: 84.1 | J160: 204.5 | K160: 150 | L160: 73.3 | N160: =VLOOKUP(B160,'New Matches'!A:B,2,FALSE) -> Finance | O160: =VLOOKUP(B160, 'New Matches'!A:I, 5, FALSE) -> M3 | P160: =IFERROR(VLOOKUP(O160, Summary!T:U, 2, FALSE), "") -> 0.31 | Q160: =IFERROR(VLOOKUP(Employees!O160, Summary!T:V, 3, FALSE), "") -> Management
A161: Tax Director | B161: 100004 | C161: National | D161: John Marchant | E161: 15007531 | F161: National | G161: 192.6 | H161: 195.7 | I161: 101.6 | J161: 219.3 | K161: 195.7 | L161: 89.2 | N161: =VLOOKUP(B161,'New Matches'!A:B,2,FALSE) -> Finance | O161: =VLOOKUP(B161, 'New Matches'!A:I, 5, FALSE) -> M3 | P161: =IFERROR(VLOOKUP(O161, Summary!T:U, 2, FALSE), "") -> 0.31 | Q161: =IFERROR(VLOOKUP(Employees!O161, Summary!T:V, 3, FALSE), "") -> Management
A162: Financial Director II | B162: 100392 | C162: National | D162: Tim Armbrustmacher | E162: 10101481 | F162: National | G162: 223.3 | H162: 202.5 | I162: 90.7 | J162: 271.8 | K162: 202.5 | L162: 74.5 | N162: =VLOOKUP(B162,'New Matches'!A:B,2,FALSE) -> Finance | O162: =VLOOKUP(B162, 'New Matches'!A:I, 5, FALSE) -> M4 | P162: =IFERROR(VLOOKUP(O162, Summary!T:U, 2, FALSE), "") -> 0.18 | Q162: =IFERROR(VLOOKUP(Employees!O162, Summary!T:V, 3, FALSE), "") -> Management
A163: Financial Director II | B163: 100392 | C163: National | D163: Dalton Boettcher | E163: 15000869 | F163: National | G163: 223.3 | H163: 188.5 | I163: 84.4 | J163: 271.8 | K163: 188.5 | L163: 69.4 | N163: =VLOOKUP(B163,'New Matches'!A:B,2,FALSE) -> Finance | O163: =VLOOKUP(B163, 'New Matches'!A:I, 5, FALSE) -> M4 | P163: =IFERROR(VLOOKUP(O163, Summary!T:U, 2, FALSE), "") -> 0.18 | Q163: =IFERROR(VLOOKUP(Employees!O163, Summary!T:V, 3, FALSE), "") -> Management
A164: Financial Director II | B164: 100392 | C164: National | D164: Amy Borden | E164: 10101502 | F164: National | G164: 223.3 | H164: 176.8 | I164: 79.2 | J164: 271.8 | K164: 176.8 | L164: 65 | M164: Evaluate if employee is leveled correctly based on market data | N164: =VLOOKUP(B164,'New Matches'!A:B,2,FALSE) -> Finance | O164: =VLOOKUP(B164, 'New Matches'!A:I, 5, FALSE) -> M4 | P164: =IFERROR(VLOOKUP(O164, Summary!T:U, 2, FALSE), "") -> 0.18 | Q164: =IFERROR(VLOOKUP(Employees!O164, Summary!T:V, 3, FALSE), "") -> Management
A165: Financial Director II | B165: 100392 | C165: National | D165: Daniel Eberhard | E165: 10101111 | F165: National | G165: 223.3 | H165: 185.3 | I165: 83 | J165: 271.8 | K165: 185.3 | L165: 68.2 | M165: Evaluate if employee is leveled correctly based on market data | N165: =VLOOKUP(B165,'New Matches'!A:B,2,FALSE) -> Finance | O165: =VLOOKUP(B165, 'New Matches'!A:I, 5, FALSE) -> M4 | P165: =IFERROR(VLOOKUP(O165, Summary!T:U, 2, FALSE), "") -> 0.18 | Q165: =IFERROR(VLOOKUP(Employees!O165, Summary!T:V, 3, FALSE), "") -> Management
A166: Financial Director II | B166: 100392 | C166: National | D166: Doug Ferderer | E166: 10100500 | F166: National | G166: 223.3 | H166: 185.2 | I166: 82.9 | J166: 271.8 | K166: 185.2 | L166: 68.1 | M166: Evaluate if employee is leveled correctly based on market data | N166: =VLOOKUP(B166,'New Matches'!A:B,2,FALSE) -> Finance | O166: =VLOOKUP(B166, 'New Matches'!A:I, 5, FALSE) -> M4 | P166: =IFERROR(VLOOKUP(O166, Summary!T:U, 2, FALSE), "") -> 0.18 | Q166: =IFERROR(VLOOKUP(Employees!O166, Summary!T:V, 3, FALSE), "") -> Management
A167: Financial Director II | B167: 100392 | C167: National | D167: Pete Hartley | E167: 10100524 | F167: National | G167: 223.3 | H167: 188.7 | I167: 84.5 | J167: 271.8 | K167: 188.7 | L167: 69.4 | M167: Evaluate if employee is leveled correctly based on market data | N167: =VLOOKUP(B167,'New Matches'!A:B,2,FALSE) -> Finance | O167: =VLOOKUP(B167, 'New Matches'!A:I, 5, FALSE) -> M4 | P167: =IFERROR(VLOOKUP(O167, Summary!T:U, 2, FALSE), "") -> 0.18 | Q167: =IFERROR(VLOOKUP(Employees!O167, Summary!T:V, 3, FALSE), "") -> Management
A168: Tax Senior Director | B168: 100006 | C168: National | D168: Shawn Abrams | E168: 10105155 | F168: National | G168: 235.4 | H168: 201.4 | I168: 85.6 | J168: 283.1 | K168: 201.4 | L168: 71.1 | N168: =VLOOKUP(B168,'New Matches'!A:B,2,FALSE) -> Finance | O168: =VLOOKUP(B168, 'New Matches'!A:I, 5, FALSE) -> M4 | P168: =IFERROR(VLOOKUP(O168, Summary!T:U, 2, FALSE), "") -> 0.18 | Q168: =IFERROR(VLOOKUP(Employees!O168, Summary!T:V, 3, FALSE), "") -> Management
A169: Accountant | B169: 100021 | C169: National | D169: Max Loesch | E169: 10135405 | F169: National | G169: 75 | H169: 60 | I169: 80 | J169: 78.5 | K169: 60 | L169: 76.4 | N169: =VLOOKUP(B169,'New Matches'!A:B,2,FALSE) -> Finance | O169: =VLOOKUP(B169, 'New Matches'!A:I, 5, FALSE) -> P2 | P169: =IFERROR(VLOOKUP(O169, Summary!T:U, 2, FALSE), "") -> 0.25 | Q169: =IFERROR(VLOOKUP(Employees!O169, Summary!T:V, 3, FALSE), "") -> Professional
A170: Accountant | B170: 100021 | C170: National | D170: Katie Riethmeier | E170: 10135150 | F170: National | G170: 75 | H170: 63 | I170: 84 | J170: 78.5 | K170: 63 | L170: 80.3 | N170: =VLOOKUP(B170,'New Matches'!A:B,2,FALSE) -> Finance | O170: =VLOOKUP(B170, 'New Matches'!A:I, 5, FALSE) -> P2 | P170: =IFERROR(VLOOKUP(O170, Summary!T:U, 2, FALSE), "") -> 0.25 | Q170: =IFERROR(VLOOKUP(Employees!O170, Summary!T:V, 3, FALSE), "") -> Professional
A171: Accountant | B171: 100021 | C171: National | D171: David Schotzko | E171: 10100088 | F171: National | G171: 75 | H171: 75 | I171: 100 | J171: 78.5 | K171: 75 | L171: 95.5 | N171: =VLOOKUP(B171,'New Matches'!A:B,2,FALSE) -> Finance | O171: =VLOOKUP(B171, 'New Matches'!A:I, 5, FALSE) -> P2 | P171: =IFERROR(VLOOKUP(O171, Summary!T:U, 2, FALSE), "") -> 0.25 | Q171: =IFERROR(VLOOKUP(Employees!O171, Summary!T:V, 3, FALSE), "") -> Professional
A172: Financial Systems Analyst | B172: 100402 | C172: National | D172: Luis Guerrero | E172: 10100148 | F172: National | G172: 87 | H172: 81 | I172: 93.1 | J172: 98.5 | K172: 81 | L172: 82.2 | N172: =VLOOKUP(B172,'New Matches'!A:B,2,FALSE) -> Finance | O172: =VLOOKUP(B172, 'New Matches'!A:I, 5, FALSE) -> P2 | P172: =IFERROR(VLOOKUP(O172, Summary!T:U, 2, FALSE), "") -> 0.25 | Q172: =IFERROR(VLOOKUP(Employees!O172, Summary!T:V, 3, FALSE), "") -> Professional
A173: Tax Analyst | B173: 100002 | C173: National | D173: Michelle Regnier | E173: 10101313 | F173: National | G173: 80 | H173: 73.5 | I173: 91.9 | J173: 86.4 | K173: 73.5 | L173: 85.1 | N173: =VLOOKUP(B173,'New Matches'!A:B,2,FALSE) -> Finance | O173: =VLOOKUP(B173, 'New Matches'!A:I, 5, FALSE) -> P2 | P173: =IFERROR(VLOOKUP(O173, Summary!T:U, 2, FALSE), "") -> 0.25 | Q173: =IFERROR(VLOOKUP(Employees!O173, Summary!T:V, 3, FALSE), "") -> Professional
A174: Treasury Analyst | B174: 100888 | C174: National | D174: Martin Cortes-Gutierrez | E174: 10133425 | F174: National | G174: 80.8 | H174: 66.7 | I174: 82.5 | J174: 85.9 | K174: 66.7 | L174: 77.6 | N174: =VLOOKUP(B174,'New Matches'!A:B,2,FALSE) -> Finance | O174: =VLOOKUP(B174, 'New Matches'!A:I, 5, FALSE) -> P2 | P174: =IFERROR(VLOOKUP(O174, Summary!T:U, 2, FALSE), "") -> 0.25 | Q174: =IFERROR(VLOOKUP(Employees!O174, Summary!T:V, 3, FALSE), "") -> Professional
A175: Treasury Analyst | B175: 100888 | C175: National | D175: Robin Glasser | E175: 10133777 | F175: National | G175: 80.8 | H175: 69.5 | I175: 86 | J175: 85.9 | K175: 69.5 | L175: 80.9 | N175: =VLOOKUP(B175,'New Matches'!A:B,2,FALSE) -> Finance | O175: =VLOOKUP(B175, 'New Matches'!A:I, 5, FALSE) -> P2 | P175: =IFERROR(VLOOKUP(O175, Summary!T:U, 2, FALSE), "") -> 0.25 | Q175: =IFERROR(VLOOKUP(Employees!O175, Summary!T:V, 3, FALSE), "") -> Professional
A176: Treasury Analyst | B176: 100888 | C176: National | D176: Sherri Guerrero | E176: 10100777 | F176: National | G176: 80.8 | H176: 71.3 | I176: 88.2 | J176: 85.9 | K176: 71.3 | L176: 83 | N176: =VLOOKUP(B176,'New Matches'!A:B,2,FALSE) -> Finance | O176: =VLOOKUP(B176, 'New Matches'!A:I, 5, FALSE) -> P2 | P176: =IFERROR(VLOOKUP(O176, Summary!T:U, 2, FALSE), "") -> 0.25 | Q176: =IFERROR(VLOOKUP(Employees!O176, Summary!T:V, 3, FALSE), "") -> Professional
A177: Treasury Analyst | B177: 100888 | C177: National | D177: Teddy Hamilton | E177: 10135173 | F177: National | G177: 80.8 | H177: 62 | I177: 76.7 | J177: 85.9 | K177: 62 | L177: 72.2 | N177: =VLOOKUP(B177,'New Matches'!A:B,2,FALSE) -> Finance | O177: =VLOOKUP(B177, 'New Matches'!A:I, 5, FALSE) -> P2 | P177: =IFERROR(VLOOKUP(O177, Summary!T:U, 2, FALSE), "") -> 0.25 | Q177: =IFERROR(VLOOKUP(Employees!O177, Summary!T:V, 3, FALSE), "") -> Professional
A178: Treasury Analyst | B178: 100888 | C178: National | D178: Andrew Horvat | E178: 10107525 | F178: National | G178: 80.8 | H178: 60 | I178: 74.3 | J178: 85.9 | K178: 60 | L178: 69.8 | N178: =VLOOKUP(B178,'New Matches'!A:B,2,FALSE) -> Finance | O178: =VLOOKUP(B178, 'New Matches'!A:I, 5, FALSE) -> P2 | P178: =IFERROR(VLOOKUP(O178, Summary!T:U, 2, FALSE), "") -> 0.25 | Q178: =IFERROR(VLOOKUP(Employees!O178, Summary!T:V, 3, FALSE), "") -> Professional
A179: Treasury Analyst | B179: 100888 | C179: National | D179: Tiffanie Mullins | E179: 15018257 | F179: National | G179: 80.8 | H179: 63.4 | I179: 78.5 | J179: 85.9 | K179: 63.4 | L179: 73.8 | N179: =VLOOKUP(B179,'New Matches'!A:B,2,FALSE) -> Finance | O179: =VLOOKUP(B179, 'New Matches'!A:I, 5, FALSE) -> P2 | P179: =IFERROR(VLOOKUP(O179, Summary!T:U, 2, FALSE), "") -> 0.25 | Q179: =IFERROR(VLOOKUP(Employees!O179, Summary!T:V, 3, FALSE), "") -> Professional
... A194: Accountant Senior | B194: 100023 | C194: National | D194: Greg Weigel | E194: 10134345 | F194: National | G194: 95.3 | H194: 85 | I194: 89.2 | J194: 101.3 | K194: 85 | L194: 83.9 | N194: =VLOOKUP(B194,'New Matches'!A:B,2,FALSE) -> Finance | O194: =VLOOKUP(B194, 'New Matches'!A:I, 5, FALSE) -> P3 | P194: =IFERROR(VLOOKUP(O194, Summary!T:U, 2, FALSE), "") -> 0.33 | Q194: =IFERROR(VLOOKUP(Employees!O194, Summary!T:V, 3, FALSE), "") -> Professional
A195: Business Financial Analyst Senior | B195: 100194 | C195: National | D195: Timothy Filreis | E195: 15014667 | F195: National | G195: 103.8 | H195: 81.4 | I195: 78.4 | J195: 110.3 | K195: 81.4 | L195: 73.8 | M195: Evaluate if employee is leveled correctly based on market data | N195: =VLOOKUP(B195,'New Matches'!A:B,2,FALSE) -> Finance | O195: =VLOOKUP(B195, 'New Matches'!A:I, 5, FALSE) -> P3 | P195: =IFERROR(VLOOKUP(O195, Summary!T:U, 2, FALSE), "") -> 0.33 | Q195: =IFERROR(VLOOKUP(Employees!O195, Summary!T:V, 3, FALSE), "") -> Professional
A196: Business Financial Analyst Senior | B196: 100194 | C196: National | D196: Katherine McMillan | E196: 15006626 | F196: National | G196: 103.8 | H196: 80.1 | I196: 77.2 | J196: 110.3 | K196: 80.1 | L196: 72.6 | M196: Evaluate if employee is leveled correctly based on market data | N196: =VLOOKUP(B196,'New Matches'!A:B,2,FALSE) -> Finance | O196: =VLOOKUP(B196, 'New Matches'!A:I, 5, FALSE) -> P3 | P196: =IFERROR(VLOOKUP(O196, Summary!T:U, 2, FALSE), "") -> 0.33 | Q196: =IFERROR(VLOOKUP(Employees!O196, Summary!T:V, 3, FALSE), "") -> Professional
A197: Business Financial Analyst Senior | B197: 100194 | C197: National | D197: January Wry | E197: 10100174 | F197: National | G197: 103.8 | H197: 100.5 | I197: 96.8 | J197: 110.3 | K197: 100.5 | L197: 91.1 | N197: =VLOOKUP(B197,'New Matches'!A:B,2,FALSE) -> Finance | O197: =VLOOKUP(B197, 'New Matches'!A:I, 5, FALSE) -> P3 | P197: =IFERROR(VLOOKUP(O197, Summary!T:U, 2, FALSE), "") -> 0.33 | Q197: =IFERROR(VLOOKUP(Employees!O197, Summary!T:V, 3, FALSE), "") -> Professional
A198: Financial Systems Analyst Senior | B198: 100404 | C198: National | D198: Natalya Davydova | E198: 10100758 | F198: National | G198: 106.9 | H198: 106.1 | I198: 99.3 | J198: 115.2 | K198: 106.1 | L198: 92.1 | N198: =VLOOKUP(B198,'New Matches'!A:B,2,FALSE) -> Finance | O198: =VLOOKUP(B198, 'New Matches'!A:I, 5, FALSE) -> P3 | P198: =IFERROR(VLOOKUP(O198, Summary!T:U, 2, FALSE), "") -> 0.33 | Q198: =IFERROR(VLOOKUP(Employees!O198, Summary!T:V, 3, FALSE), "") -> Professional
A199: Tax Analyst Senior | B199: 100003 | C199: National | D199: Haley Burd | E199: 10136178 | F199: National | G199: 102.7 | H199: 105 | I199: 102.2 | J199: 112.7 | K199: 105 | L199: 93.2 | N199: =VLOOKUP(B199,'New Matches'!A:B,2,FALSE) -> Finance | O199: =VLOOKUP(B199, 'New Matches'!A:I, 5, FALSE) -> P3 | P199: =IFERROR(VLOOKUP(O199, Summary!T:U, 2, FALSE), "") -> 0.33 | Q199: =IFERROR(VLOOKUP(Employees!O199, Summary!T:V, 3, FALSE), "") -> Professional
A200: Tax Analyst Senior | B200: 100003 | C200: National | D200: Sarah Davey | E200: 10105154 | F200: National | G200: 102.7 | H200: 93.3 | I200: 90.8 | J200: 112.7 | K200: 93.3 | L200: 82.8 | N200: =VLOOKUP(B200,'New Matches'!A:B,2,FALSE) -> Finance | O200: =VLOOKUP(B200, 'New Matches'!A:I, 5, FALSE) -> P3 | P200: =IFERROR(VLOOKUP(O200, Summary!T:U, 2, FALSE), "") -> 0.33 | Q200: =IFERROR(VLOOKUP(Employees!O200, Summary!T:V, 3, FALSE), "") -> Professional
A201: Tax Analyst Senior | B201: 100003 | C201: National | D201: Megan Kovacs | E201: 10135714 | F201: National | G201: 102.7 | H201: 100 | I201: 97.4 | J201: 112.7 | K201: 100 | L201: 88.7 | N201: =VLOOKUP(B201,'New Matches'!A:B,2,FALSE) -> Finance | O201: =VLOOKUP(B201, 'New Matches'!A:I, 5, FALSE) -> P3 | P201: =IFERROR(VLOOKUP(O201, Summary!T:U, 2, FALSE), "") -> 0.33 | Q201: =IFERROR(VLOOKUP(Employees!O201, Summary!T:V, 3, FALSE), "") -> Professional
A202: Tax Analyst Senior | B202: 100003 | C202: National | D202: Amanda Ludtke | E202: 10131006 | F202: National | G202: 102.7 | H202: 108.8 | I202: 105.9 | J202: 112.7 | K202: 108.8 | L202: 96.5 | N202: =VLOOKUP(B202,'New Matches'!A:B,2,FALSE) -> Finance | O202: =VLOOKUP(B202, 'New Matches'!A:I, 5, FALSE) -> P3 | P202: =IFERROR(VLOOKUP(O202, Summary!T:U, 2, FALSE), "") -> 0.33 | Q202: =IFERROR(VLOOKUP(Employees!O202, Summary!T:V, 3, FALSE), "") -> Professional
A203: Tax Analyst Senior | B203: 100003 | C203: National | D203: Logan Miller | E203: 10135977 | F203: National | G203: 102.7 | H203: 105 | I203: 102.2 | J203: 112.7 | K203: 105 | L203: 93.2 | N203: =VLOOKUP(B203,'New Matches'!A:B,2,FALSE) -> Finance | O203: =VLOOKUP(B203, 'New Matches'!A:I, 5, FALSE) -> P3 | P203: =IFERROR(VLOOKUP(O203, Summary!T:U, 2, FALSE), "") -> 0.33 | Q203: =IFERROR(VLOOKUP(Employees!O203, Summary!T:V, 3, FALSE), "") -> Professional
A204: Tax Analyst Senior | B204: 100003 | C204: National | D204: Stacy Pumper | E204: 13030071 | F204: National | G204: 102.7 | H204: 105.1 | I204: 102.3 | J204: 112.7 | K204: 105.1 | L204: 93.3 | N204: =VLOOKUP(B204,'New Matches'!A:B,2,FALSE) -> Finance | O204: =VLOOKUP(B204, 'New Matches'!A:I, 5, FALSE) -> P3 | P204: =IFERROR(VLOOKUP(O204, Summary!T:U, 2, FALSE), "") -> 0.33 | Q204: =IFERROR(VLOOKUP(Employees!O204, Summary!T:V, 3, FALSE), "") -> Professional
A205: Tax Analyst Senior | B205: 100003 | C205: National | D205: Erin Sharp | E205: 10135338 | F205: National | G205: 102.7 | H205: 105 | I205: 102.2 | J205: 112.7 | K205: 105 | L205: 93.2 | N205: =VLOOKUP(B205,'New Matches'!A:B,2,FALSE) -> Finance | O205: =VLOOKUP(B205, 'New Matches'!A:I, 5, FALSE) -> P3 | P205: =IFERROR(VLOOKUP(O205, Summary!T:U, 2, FALSE), "") -> 0.33 | Q205: =IFERROR(VLOOKUP(Employees!O205, Summary!T:V, 3, FALSE), "") -> Professional
A206: Tax Analyst Senior | B206: 100003 | C206: National | D206: Linda Stebor | E206: 10105151 | F206: National | G206: 102.7 | H206: 101.3 | I206: 98.6 | J206: 112.7 | K206: 101.3 | L206: 89.9 | N206: =VLOOKUP(B206,'New Matches'!A:B,2,FALSE) -> Finance | O206: =VLOOKUP(B206, 'New Matches'!A:I, 5, FALSE) -> P3 | P206: =IFERROR(VLOOKUP(O206, Summary!T:U, 2, FALSE), "") -> 0.33 | Q206: =IFERROR(VLOOKUP(Employees!O206, Summary!T:V, 3, FALSE), "") -> Professional
A207: Treasury Accountant Senior | B207: 100887 | C207: National | D207: Cristina Kannegiesser | E207: 10101029 | F207: National | G207: 104.6 | H207: 85 | I207: 81.3 | J207: 113.1 | K207: 85 | L207: 75.2 | M207: Evaluate if employee is leveled correctly based on market data | N207: =VLOOKUP(B207,'New Matches'!A:B,2,FALSE) -> Finance | O207: =VLOOKUP(B207, 'New Matches'!A:I, 5, FALSE) -> P3 | P207: =IFERROR(VLOOKUP(O207, Summary!T:U, 2, FALSE), "") -> 0.33 | Q207: =IFERROR(VLOOKUP(Employees!O207, Summary!T:V, 3, FALSE), "") -> Professional
A208: Accountant Principal | B208: 100022 | C208: National | D208: Ryan Battist | E208: 15023047 | F208: National | G208: 114.8 | H208: 95 | I208: 82.8 | J208: 124.9 | K208: 95 | L208: 76.1 | N208: =VLOOKUP(B208,'New Matches'!A:B,2,FALSE) -> Finance | O208: =VLOOKUP(B208, 'New Matches'!A:I, 5, FALSE) -> P4 | P208: =IFERROR(VLOOKUP(O208, Summary!T:U, 2, FALSE), "") -> 0.21 | Q208: =IFERROR(VLOOKUP(Employees!O208, Summary!T:V, 3, FALSE), "") -> Professional
A209: Accountant Principal | B209: 100022 | C209: National | D209: Mark Digre | E209: 10102090 | F209: National | G209: 114.8 | H209: 104.6 | I209: 91.1 | J209: 124.9 | K209: 104.6 | L209: 83.7 | N209: =VLOOKUP(B209,'New Matches'!A:B,2,FALSE) -> Finance | O209: =VLOOKUP(B209, 'New Matches'!A:I, 5, FALSE) -> P4 | P209: =IFERROR(VLOOKUP(O209, Summary!T:U, 2, FALSE), "") -> 0.21 | Q209: =IFERROR(VLOOKUP(Employees!O209, Summary!T:V, 3, FALSE), "") -> Professional
A210: Accountant Principal | B210: 100022 | C210: National | D210: Shaun Grabow | E210: 10100027 | F210: National | G210: 114.8 | H210: 136.1 | I210: 118.6 | J210: 124.9 | K210: 136.1 | L210: 109 | N210: =VLOOKUP(B210,'New Matches'!A:B,2,FALSE) -> Finance | O210: =VLOOKUP(B210, 'New Matches'!A:I, 5, FALSE) -> P4 | P210: =IFERROR(VLOOKUP(O210, Summary!T:U, 2, FALSE), "") -> 0.21 | Q210: =IFERROR(VLOOKUP(Employees!O210, Summary!T:V, 3, FALSE), "") -> Professional
A211: Accountant Principal | B211: 100022 | C211: National | D211: Chris Hochsprung | E211: 10100757 | F211: National | G211: 114.8 | H211: 104.5 | I211: 91 | J211: 124.9 | K211: 104.5 | L211: 83.7 | N211: =VLOOKUP(B211,'New Matches'!A:B,2,FALSE) -> Finance | O211: =VLOOKUP(B211, 'New Matches'!A:I, 5, FALSE) -> P4 | P211: =IFERROR(VLOOKUP(O211, Summary!T:U, 2, FALSE), "") -> 0.21 | Q211: =IFERROR(VLOOKUP(Employees!O211, Summary!T:V, 3, FALSE), "") -> Professional
A212: Accountant Principal | B212: 100022 | C212: National | D212: Amanda Jackson | E212: 10101870 | F212: National | G212: 114.8 | H212: 104.6 | I212: 91.1 | J212: 124.9 | K212: 104.6 | L212: 83.7 | N212: =VLOOKUP(B212,'New Matches'!A:B,2,FALSE) -> Finance | O212: =VLOOKUP(B212, 'New Matches'!A:I, 5, FALSE) -> P4 | P212: =IFERROR(VLOOKUP(O212, Summary!T:U, 2, FALSE), "") -> 0.21 | Q212: =IFERROR(VLOOKUP(Employees!O212, Summary!T:V, 3, FALSE), "") -> Professional
...

Sheet Summary
K1: Avg Employee Pay | N1: Avg Market Rate | Q1: Incumbent Count
A2: Job Family | B2: Information Technology | K2: Row Labels | L2: Average of Employee Annual Rate | N2: Row Labels | O2: Average of Base 50th | Q2: Row Labels | R2: Count of Employee ID | T2: Chart Guidelines
K3: 100002 | L3: 73.5 | N3: 100135 | O3: 67.75 | Q3: 100002 | R3: 1 | T3: Level | U3: WTW Guidelines | V3: Chart
A4: Row Labels | B4: Count of Job Code | C4: Min of Base 50th2 | D4: Average of Base 50th | E4: Max of Base 50th2 | F4: Spread - Below | G4: Spread - Above | H4: Level Progression | K4: 100003 | L4: 102.9375 | N4: 100136 | O4: 101.25 | Q4: 100003 | R4: 8 | T4: P1 | U4: 0.13 | V4: Professional
A5: Business Systems Analysis | K5: 100004 | L5: 195.7 | N5: 100137 | O5: 186.95 | Q5: 100004 | R5: 1 | T5: P2 | U5: 0.25 | V5: Professional
A6: M2-Senior Manager Business Systems Analysis | B6: 3 | C6: 138.5 | D6: 145.6 | E6: 152.5 | F6: =IFERROR((C6-D6)/C6, "") -> -0.051263538 | G6: =IFERROR((D6-E6)/D6, "") -> -0.04739011 | H6: =(D6-D5)/D5 -> #DIV/0! | K6: 100005 | L6: 133.56 | N6: 100138 | O6: 127.125 | Q6: 100005 | R6: 5 | T6: P3 | U6: 0.33 | V6: Professional
A7: P1-Business Systems Analysis Consultant Associate | B7: 4 | C7: 62.8 | D7: 70 | E7: 73.2 | F7: =IFERROR((C7-D7)/C7, "") -> -0.11464968 | G7: =IFERROR((D7-E7)/D7, "") -> -0.045714286 | H7: =(D7-D6)/D6 -> -0.51923077 | K7: 100006 | L7: 201.4 | N7: 100140 | O7: 130.5 | Q7: 100006 | R7: 1 | T7: P4 | U7: 0.21 | V7: Professional
A8: P2-Business Systems Analysis Consultant | B8: 4 | C8: 75.9 | D8: 84.275 | E8: 89.5 | F8: =IFERROR((C8-D8)/C8, "") -> -0.11034256 | G8: =IFERROR((D8-E8)/D8, "") -> -0.061999407 | H8: =(D8-D7)/D7 -> 0.20392857 | K8: 100007 | L8: 177.4 | N8: 100141 | O8: 226.9 | Q8: 100007 | R8: 2 | T8: P5 | U8: 0.07 | V8: Professional
A9: P3-Business Systems Analysis Consultant Senior | B9: 4 | C9: 99.4 | D9: 109.125 | E9: 117.5 | F9: =IFERROR((C9-D9)/C9, "") -> -0.097837022 | G9: =IFERROR((D9-E9)/D9, "") -> -0.07674685 | H9: =(D9-D8)/D8 -> 0.29486799 | K9: 100018 | L9: 58.270833 | N9: 101026 | O9: 82.9 | Q9: 100018 | R9: 72 | T9: M1 | U9: 0.13 | V9: Management
A10: P4-Business Systems Analysis Consultant Principal | B10: 3 | C10: 129.4 | D10: 131.8 | E10: 135.6 | F10: =IFERROR((C10-D10)/C10, "") -> -0.018547141 | G10: =IFERROR((D10-E10)/D10, "") -> -0.028831563 | H10: =(D10-D9)/D9 -> 0.20778923 | K10: 100019 | L10: 50.845312 | N10: 100394 | O10: 127.075 | Q10: 100019 | R10: 64 | T10: M2 | U10: 0.38 | V10: Management
A11: Data Governance | F11: =IFERROR((C11-D11)/C11, "") | G11: =IFERROR((D11-E11)/D11, "") | H11: =(D11-D10)/D10 -> -1 | K11: 100020 | L11: 66.03125 | N11: 100391 | O11: 171.96667 | Q11: 100020 | R11: 16 | T11: M3 | U11: 0.31 | V11: Management
A12: M2-Senior Manager Data Governance | B12: 3 | C12: 138.8 | D12: 146.8 | E12: 155.1 | F12: =IFERROR((C12-D12)/C12, "") -> -0.057636888 | G12: =IFERROR((D12-E12)/D12, "") -> -0.05653951 | H12: =(D12-D11)/D11 -> #DIV/0! | K12: 100021 | L12: 66 | N12: 100392 | O12: 223.26667 | Q12: 100021 | R12: 3 | T12: M4 | U12: =18% -> 0.18 | V12: Management
A13: M4-Senior Director Data Governance | B13: 2 | C13: 227.2 | D13: 231.8 | E13: 236.4 | F13: =IFERROR((C13-D13)/C13, "") -> -0.020246479 | G13: =IFERROR((D13-E13)/D13, "") -> -0.019844694 | H13: =(D13-D12)/D12 -> 0.57901907 | K13: 100022 | L13: 106.925 | N13: FI-AC-P1 | O13: 65.7 | Q13: 100022 | R13: 8
A14: P1-Data Governance Analyst Associate | B14: 3 | C14: 63.2 | D14: 66.833333 | E14: 73.7 | F14: =IFERROR((C14-D14)/C14, "") -> -0.057489451 | G14: =IFERROR((D14-E14)/D14, "") -> -0.10274314 | H14: =(D14-D13)/D13 -> -0.71167673 | K14: 100023 | L14: 85.508333 | N14: 100021 | O14: 75 | Q14: 100023 | R14: 12
A15: P2-Data Governance Analyst | B15: 3 | C15: 81.4 | D15: 85.633333 | E15: 88 | F15: =IFERROR((C15-D15)/C15, "") -> -0.052006552 | G15: =IFERROR((D15-E15)/D15, "") -> -0.027637213 | H15: =(D15-D14)/D14 -> 0.28129676 | K15: 100024 | L15: 91.613333 | N15: 100023 | O15: 95.325 | Q15: 100024 | R15: 15
A16: P3-Data Governance Analyst Senior | B16: 3 | C16: 107.9 | D16: 115.23333 | E16: 121.2 | F16: =IFERROR((C16-D16)/C16, "") -> -0.067964164 | G16: =IFERROR((D16-E16)/D16, "") -> -0.051778999 | H16: =(D16-D15)/D15 -> 0.34565979 | K16: 100025 | L16: 185.225 | N16: 100022 | O16: 114.775 | Q16: 100025 | R16: 8
A17: P4-Data Governance Analyst Principal | B17: 3 | C17: 108.4 | D17: 136.5 | E17: 153.9 | F17: =IFERROR((C17-D17)/C17, "") -> -0.25922509 | G17: =IFERROR((D17-E17)/D17, "") -> -0.12747253 | H17: =(D17-D16)/D16 -> 0.18455308 | K17: 100026 | L17: 86.871429 | N17: FI-AC-P5 | O17: 153.7 | Q17: 100026 | R17: 7
A18: Information Security | F18: =IFERROR((C18-D18)/C18, "") | G18: =IFERROR((D18-E18)/D18, "") | H18: =(D18-D17)/D17 -> -1 | K18: 100028 | L18: 99.22 | N18: FI-AP-M2 | O18: 145.3 | Q18: 100028 | R18: 5
A19: M3-Director Information Security | B19: 2 | C19: 191.9 | D19: 201.25 | E19: 210.6 | F19: =IFERROR((C19-D19)/C19, "") -> -0.048723293 | G19: =IFERROR((D19-E19)/D19, "") -> -0.046459627 | H19: =(D19-D18)/D18 -> #DIV/0! | K19: 100132 | L19: 143.28667 | N19: FI-AP-M4 | O19: 243.1 | Q19: 100132 | R19: 15
A20: M4-Senior Director Information Security | B20: 1 | C20: 228.3 | D20: 228.3 | E20: 228.3 | F20: =IFERROR((C20-D20)/C20, "") -> 0 | G20: =IFERROR((D20-E20)/D20, "") -> 0 | H20: =(D20-D19)/D19 -> 0.13440994 | K20: 100133 | L20: 165.58333 | N20: FI-AP-P3 | O20: 105.8 | Q20: 100133 | R20: 6
A21: P1-Information Security Consultant Associate | B21: 3 | C21: 76.1 | D21: 77.3 | E21: 78.6 | F21: =IFERROR((C21-D21)/C21, "") -> -0.015768725 | G21: =IFERROR((D21-E21)/D21, "") -> -0.016817594 | H21: =(D21-D20)/D20 -> -0.66141042 | K21: 100136 | L21: 84.45 | N21: FI-AP-P4 | O21: 185.6 | Q21: 100136 | R21: 2
A22: P2-Information Security Consultant | B22: 3 | C22: 94.4 | D22: 96.5 | E22: 100.1 | F22: =IFERROR((C22-D22)/C22, "") -> -0.022245763 | G22: =IFERROR((D22-E22)/D22, "") -> -0.037305699 | H22: =(D22-D21)/D21 -> 0.24838292 | K22: 100137 | L22: 157.6 | N22: FI-FP-M2 | O22: 141.85 | Q22: 100137 | R22: 3
A23: P3-Information Security Consultant Senior | B23: 2 | C23: 121.4 | D23: 124.1 | E23: 126.8 | F23: =IFERROR((C23-D23)/C23, "") -> -0.022240527 | G23: =IFERROR((D23-E23)/D23, "") -> -0.021756648 | H23: =(D23-D22)/D22 -> 0.28601036 | K23: 100138 | L23: 106.8375 | N23: FI-FP-M3 | O23: 199.575 | Q23: 100138 | R23: 8
A24: P4-Information Security Consultant Principal | B24: 2 | C24: 147.2 | D24: 148.35 | E24: 149.5 | F24: =IFERROR((C24-D24)/C24, "") -> -0.0078125 | G24: =IFERROR((D24-E24)/D24, "") -> -0.007751938 | H24: =(D24-D23)/D23 -> 0.19540693 | K24: 100140 | L24: 140.93333 | N24: FI-FP-M4 | O24: 237 | Q24: 100140 | R24: 3
A25: P5-Information Security Director | B25: 2 | C25: 175.2 | D25: 177.65 | E25: 180.1 | F25: =IFERROR((C25-D25)/C25, "") -> -0.013984018 | G25: =IFERROR((D25-E25)/D25, "") -> -0.013791162 | H25: =(D25-D24)/D24 -> 0.1975059 | K25: 100183 | L25: 72.35 | N25: 100388 | O25: 69.275 | Q25: 100183 | R25: 6
A26: IT Architecture | F26: =IFERROR((C26-D26)/C26, "") | G26: =IFERROR((D26-E26)/D26, "") | H26: =(D26-D25)/D25 -> -1 | K26: 100186 | L26: 84.521429 | N26: 100192 | O26: 82.325 | Q26: 100186 | R26: 14
A27: M4-Senior Director IT Architecture | B27: 2 | C27: 238.6 | D27: 251.2 | E27: 263.8 | F27: =IFERROR((C27-D27)/C27, "") -> -0.052808047 | G27: =IFERROR((D27-E27)/D27, "") -> -0.050159236 | H27: =(D27-D26)/D26 -> #DIV/0! | K27: 100187 | L27: 104.41 | N27: 100194 | O27: 103.825 | Q27: 100187 | R27: 20
A28: P3-IT Architect Senior | B28: 2 | C28: 136.8 | D28: 142.5 | E28: 148.2 | F28: =IFERROR((C28-D28)/C28, "") -> -0.041666667 | G28: =IFERROR((D28-E28)/D28, "") -> -0.04 | H28: =(D28-D27)/D27 -> -0.43272293 | K28: 100193 | L28: 128.58 | N28: 100193 | O28: 127.075 | Q28: 100193 | R28: 10
A29: P4-IT Architect Principal | B29: 3 | C29: 167.4 | D29: 168.6 | E29: 170.6 | F29: =IFERROR((C29-D29)/C29, "") -> -0.0071684588 | G29: =IFERROR((D29-E29)/D29, "") -> -0.011862396 | H29: =(D29-D28)/D28 -> 0.18315789 | K29: 100194 | L29: 87.333333 | N29: FI-FP-P5 | O29: 156.93333 | Q29: 100194 | R29: 3
A30: P5-IT Architect Director | B30: 2 | C30: 184.4 | D30: 190.25 | E30: 196.1 | F30: =IFERROR((C30-D30)/C30, "") -> -0.031724512 | G30: =IFERROR((D30-E30)/D30, "") -> -0.030749014 | H30: =(D30-D29)/D29 -> 0.12841044 | K30: 100199 | L30: 63.478261 | N30: FI-FR-P2 | O30: 80.325 | Q30: 100199 | R30: 23
A31: IT Development | F31: =IFERROR((C31-D31)/C31, "") | G31: =IFERROR((D31-E31)/D31, "") | H31: =(D31-D30)/D30 -> -1 | K31: 100201 | L31: 75.508333 | N31: FI-FR-P3 | O31: 100.83333 | Q31: 100201 | R31: 12
A32: M2-Senior Manager IT Development | B32: 1 | C32: 161.4 | D32: 161.4 | E32: 161.4 | F32: =IFERROR((C32-D32)/C32, "") -> 0 | G32: =IFERROR((D32-E32)/D32, "") -> 0 | H32: =(D32-D31)/D31 -> #DIV/0! | K32: 100202 | L32: 99.829412 | N32: FI-FR-M4 | O32: 226.6 | Q32: 100202 | R32: 17
A33: M3-Director IT Development | B33: 6 | C33: 188.1 | D33: 194.5 | E33: 205.5 | F33: =IFERROR((C33-D33)/C33, "") -> -0.034024455 | G33: =IFERROR((D33-E33)/D33, "") -> -0.05655527 | H33: =(D33-D32)/D32 -> 0.20508055 | K33: 100203 | L33: 184.1 | N33: FI-FR-M2 | O33: 136.63333 | Q33: 100203 | R33: 2
A34: P1-IT Developer Associate | B34: 4 | C34: 74.9 | D34: 80.625 | E34: 93.4 | F34: =IFERROR((C34-D34)/C34, "") -> -0.076435247 | G34: =IFERROR((D34-E34)/D34, "") -> -0.15844961 | H34: =(D34-D33)/D33 -> -0.58547558 | K34: 100249 | L34: 59.666667 | N34: FI-FS-M2 | O34: 139.65 | Q34: 100249 | R34: 3
A35: P2-IT Developer | B35: 4 | C35: 92.1 | D35: 99.125 | E35: 105.5 | F35: =IFERROR((C35-D35)/C35, "") -> -0.076275787 | G35: =IFERROR((D35-E35)/D35, "") -> -0.064312736 | H35: =(D35-D34)/D34 -> 0.22945736 | K35: 100250 | L35: 55.5 | N35: 100402 | O35: 82.2 | Q35: 100250 | R35: 3
A36: P3-IT Developer Senior | B36: 3 | C36: 117.8 | D36: 124.66667 | E36: 138 | F36: =IFERROR((C36-D36)/C36, "") -> -0.058290889 | G36: =IFERROR((D36-E36)/D36, "") -> -0.10695187 | H36: =(D36-D35)/D35 -> 0.25767129 | K36: 100263 | L36: 112.5 | N36: 100404 | O36: 106.35 | Q36: 100263 | R36: 2
A37: P4-IT Developer Principal | B37: 3 | C37: 140.7 | D37: 146.96667 | E37: 153.8 | F37: =IFERROR((C37-D37)/C37, "") -> -0.044539209 | G37: =IFERROR((D37-E37)/D37, "") -> -0.046495804 | H37: =(D37-D36)/D36 -> 0.17887701 | K37: 100271 | L37: 44.357143 | N37: 100002 | O37: 79.95 | Q37: 100271 | R37: 7
A38: IT Service Management | F38: =IFERROR((C38-D38)/C38, "") | G38: =IFERROR((D38-E38)/D38, "") | H38: =(D38-D37)/D37 -> -1 | K38: 100272 | L38: 49.4375 | N38: 100003 | O38: 102.65 | Q38: 100272 | R38: 8
A39: M3-Director IT Service Management | B39: 1 | C39: 181.7 | D39: 181.7 | E39: 181.7 | F39: =IFERROR((C39-D39)/C39, "") -> 0 | G39: =IFERROR((D39-E39)/D39, "") -> 0 | H39: =(D39-D38)/D38 -> #DIV/0! | K39: 100277 | L39: 72 | N39: FI-TX-P4 | O39: 131.725 | Q39: 100277 | R39: 2
A40: M4-Senior Director IT Service Management | B40: 1 | C40: 213.2 | D40: 213.2 | E40: 213.2 | F40: =IFERROR((C40-D40)/C40, "") -> 0 | G40: =IFERROR((D40-E40)/D40, "") -> 0 | H40: =(D40-D39)/D39 -> 0.17336269 | K40: 100278 | L40: 103.325 | N40: FI-TX-P5 | O40: 180.53333 | Q40: 100278 | R40: 4
A41: P3-IT Service Management Consultant Senior | B41: 1 | C41: 122.9 | D41: 122.9 | E41: 122.9 | F41: =IFERROR((C41-D41)/C41, "") -> 0 | G41: =IFERROR((D41-E41)/D41, "") -> 0 | K41: 100279 | L41: 133.425 | N41: FI-TX-U3 | Q41: 100279 | R41: 4
A42: P4-Family | B42: 1 | C42: 139.6 | D42: 139.6 | E42: 139.6 | F42: =IFERROR((C42-D42)/C42, "") -> 0 | G42: =IFERROR((D42-E42)/D42, "") -> 0 | K42: 100284 | L42: 206 | N42: 100891 | O42: 61 | Q42: 100284 | R42: 1
A43: P5-IT Service Management Director | B43: 1 | C43: 155.7 | D43: 155.7 | E43: 155.7 | F43: =IFERROR((C43-D43)/C43, "") -> 0 | G43: =IFERROR((D43-E43)/D43, "") -> 0 | K43: 100294 | L43: 44.072727 | N43: 101370 | O43: 63.4 | Q43: 100294 | R43: 11
A44: Grand Total | B44: 85 | C44: 62.8 | D44: 134.16353 | E44: 263.8 | F44: =IFERROR((C44-D44)/C44, "") -> -1.1363619 | G44: =IFERROR((D44-E44)/D44, "") -> -0.96625716 | K44: 100295 | L44: 46.259615 | N44: 100892 | O44: 69.1 | Q44: 100295 | R44: 52
F45: =IFERROR((C45-D45)/C45, "") | G45: =IFERROR((D45-E45)/D45, "") | K45: 100296 | L45: 52.69 | N45: FI-TR-M3 | O45: 201.7 | Q45: 100296 | R45: 10
F46: =IFERROR((C46-D46)/C46, "") | G46: =IFERROR((D46-E46)/D46, "") | K46: 100297 | L46: 58.9125 | N46: 100403 | O46: 133.9 | Q46: 100297 | R46: 32
F47: =IFERROR((C47-D47)/C47, "") | G47: =IFERROR((D47-E47)/D47, "") | K47: 100298 | L47: 108.2 | N47: FI-TR-M1 | O47: 105.16667 | Q47: 100298 | R47: 3
F48: =IFERROR((C48-D48)/C48, "") | G48: =IFERROR((D48-E48)/D48, "") | K48: 100300 | L48: 122.8 | N48: FI-TR-M4 | Q48: 100300 | R48: 3
F49: =IFERROR((C49-D49)/C49, "") | G49: =IFERROR((D49-E49)/D49, "") | K49: 100349 | L49: 195.8 | N49: FI-TR-M2 | O49: 139.06667 | Q49: 100349 | R49: 1
F50: =IFERROR((C50-D50)/C50, "") | G50: =IFERROR((D50-E50)/D50, "") | K50: 100360 | L50: 209.75 | N50: 100004 | O50: 192.575 | Q50: 100360 | R50: 6
F51: =IFERROR((C51-D51)/C51, "") | G51: =IFERROR((D51-E51)/D51, "") | K51: 100366 | L51: 88 | N51: 100005 | O51: 115.1 | Q51: 100366 | R51: 1
F52: =IFERROR((C52-D52)/C52, "") | G52: =IFERROR((D52-E52)/D52, "") | K52: 100367 | L52: 168.8 | N52: 100006 | O52: 235.43333 | Q52: 100367 | R52: 1
F53: =IFERROR((C53-D53)/C53, "") | G53: =IFERROR((D53-E53)/D53, "") | K53: 100368 | L53: 136.2 | N53: 100007 | O53: 142.025 | Q53: 100368 | R53: 1
F54: =IFERROR((C54-D54)/C54, "") | G54: =IFERROR((D54-E54)/D54, "") | K54: 100391 | L54: 172.35 | N54: 100886 | O54: 67.333333 | Q54: 100391 | R54: 2
F55: =IFERROR((C55-D55)/C55, "") | G55: =IFERROR((D55-E55)/D55, "") | K55: 100392 | L55: 187.83333 | N55: 100887 | O55: 104.6 | Q55: 100392 | R55: 6
F56: =IFERROR((C56-D56)/C56, "") | G56: =IFERROR((D56-E56)/D56, "") | K56: 100394 | L56: 146.275 | N56: 100888 | O56: 80.766667 | Q56: 100394 | R56: 4
F57: =IFERROR((C57-D57)/C57, "") | G57: =IFERROR((D57-E57)/D57, "") | K57: 100399 | L57: 146.35 | N57: 101637 | O57: 163.9 | Q57: 100399 | R57: 2
F58: =IFERROR((C58-D58)/C58, "") | G58: =IFERROR((D58-E58)/D58, "") | K58: 100402 | L58: 81 | N58: DA-DE-M4 | O58: 239.45 | Q58: 100402 | R58: 1
F59: =IFERROR((C59-D59)/C59, "") | G59: =IFERROR((D59-E59)/D59, "") | K59: 100403 | L59: 121.8 | N59: 101629 | O59: 80.466667 | Q59: 100403 | R59: 4
F60: =IFERROR((C60-D60)/C60, "") | G60: =IFERROR((D60-E60)/D60, "") | K60: 100404 | L60: 106.1 | N60: 101442 | O60: 112.3 | Q60: 100404 | R60: 1
... F64: =IFERROR((C64-D64)/C64, "") | G64: =IFERROR((D64-E64)/D64, "") | K64: 100518 | L64: 93.9 | N64: 100665 | O64: 199.575 | Q64: 100518 | R64: 1
K65: 100520 | L65: 190.2 | N65: 101643 | O65: 229.06667 | Q65: 100520 | R65: 1
K66: 100548 | L66: 140.825 | N66: 101565 | O66: 70.575 | Q66: 100548 | R66: 4
K67: 100549 | L67: 120.8625 | N67: 101566 | O67: 86.225 | Q67: 100549 | R67: 8
K68: 100553 | L68: 222.5 | N68: 101567 | O68: 107.875 | Q68: 100553 | R68: 3
F69: =IFERROR((C69-D69)/C69, "") | G69: =IFERROR((D69-E69)/D69, "") | K69: 100554 | L69: 176 | N69: 100933 | O69: 132.8 | Q69: 100554 | R69: 1
F70: =IFERROR((C70-D70)/C70, "") | G70: =IFERROR((D70-E70)/D70, "") | K70: 100651 | L70: 50.2 | N70: 101568 | O70: 135.9 | Q70: 100651 | R70: 1
F71: =IFERROR((C71-D71)/C71, "") | G71: =IFERROR((D71-E71)/D71, "") | K71: 100663 | L71: 144.91429 | N71: DA-DR-P5 | O71: 165.93333 | Q71: 100663 | R71: 7
F72: =IFERROR((C72-D72)/C72, "") | G72: =IFERROR((D72-E72)/D72, "") | K72: 100665 | L72: 165.8 | N72: 101540 | O72: 164.825 | Q72: 100665 | R72: 3
F73: =IFERROR((C73-D73)/C73, "") | G73: =IFERROR((D73-E73)/D73, "") | K73: 100668 | L73: 76.79375 | N73: 100349 | O73: 216.075 | Q73: 100668 | R73: 16
F74: =IFERROR((C74-D74)/C74, "") | G74: =IFERROR((D74-E74)/D74, "") | K74: 100672 | L74: 172.325 | N74: 101514 | O74: 83.425 | Q74: 100672 | R74: 8
F75: =IFERROR((C75-D75)/C75, "") | G75: =IFERROR((D75-E75)/D75, "") | K75: 100675 | L75: 105.89032 | N75: 100298 | O75: 108.375 | Q75: 100675 | R75: 31
F76: =IFERROR((C76-D76)/C76, "") | G76: =IFERROR((D76-E76)/D76, "") | K76: 100679 | L76: 64 | N76: 100300 | O76: 133.85 | Q76: 100679 | R76: 1
F77: =IFERROR((C77-D77)/C77, "") | G77: =IFERROR((D77-E77)/D77, "") | K77: 100702 | L77: 123.31875 | N77: 100299 | O77: 159.525 | Q77: 100702 | R77: 16
F78: =IFERROR((C78-D78)/C78, "") | G78: =IFERROR((D78-E78)/D78, "") | K78: 100752 | L78: 62.6 | N78: 101936 | O78: 175.5 | Q78: 100752 | R78: 3
F79: =IFERROR((C79-D79)/C79, "") | G79: =IFERROR((D79-E79)/D79, "") | K79: 100774 | L79: 67.018182 | N79: 100795 | O79: 140.7 | Q79: 100774 | R79: 11
K80: 100775 | L80: 59.066667 | N80: 101291 | O80: 181.6 | Q80: 100775 | R80: 3
K81: 100776 | L81: 120.6 | N81: 100798 | O81: 230.5 | Q81: 100776 | R81: 1
K82: 100777 | L82: 77.8 | N82: 100794 | O82: 78.45 | Q82: 100777 | R82: 5
K83: 100794 | L83: 84.4 | N83: 100797 | O83: 109.8 | Q83: 100794 | R83: 5
K84: 100798 | L84: 125.1 | N84: DA-SE-P4 | O84: 132.45 | Q84: 100798 | R84: 1
K85: 100807 | L85: 104.95357 | N85: DA-SE-P5 | O85: 169.8 | Q85: 100807 | R85: 28
K86: 100808 | L86: 210 | N86: 100937 | O86: 145.6 | Q86: 100808 | R86: 1
K87: 100811 | L87: 226.9 | N87: 100562 | O87: 70 | Q87: 100811 | R87: 4
K88: 100826 | L88: 76.8 | N88: 100026 | O88: 84.275 | Q88: 100826 | R88: 1
K89: 100840 | L89: 71.05 | N89: 100028 | O89: 109.125 | Q89: 100840 | R89: 4
K90: 100846 | L90: 60.184615 | N90: 100027 | O90: 131.8 | Q90: 100846 | R90: 13
F91: =IFERROR((C91-D91)/C91, "") | G91: =IFERROR((D91-E91)/D91, "") | K91: 100887 | L91: 85 | N91: 101681 | O91: 146.8 | Q91: 100887 | R91: 1
F92: =IFERROR((C92-D92)/C92, "") | G92: =IFERROR((D92-E92)/D92, "") | H92: =(D92-D91)/D91 -> #DIV/0! | K92: 100888 | L92: 67.477778 | N92: IT-DG-M4 | O92: 231.8 | Q92: 100888 | R92: 9
F93: =IFERROR((C93-D93)/C93, "") | G93: =IFERROR((D93-E93)/D93, "") | K93: 100891 | L93: 49.3 | N93: 101693 | O93: 66.833333 | Q93: 100891 | R93: 1
F94: =IFERROR((C94-D94)/C94, "") | G94: =IFERROR((D94-E94)/D94, "") | H94: =(D94-D93)/D93 -> #DIV/0! | K94: 100892 | L94: 69.533333 | N94: 101309 | O94: 85.633333 | Q94: 100892 | R94: 3
F95: =IFERROR((C95-D95)/C95, "") | G95: =IFERROR((D95-E95)/D95, "") | H95: =(D95-D94)/D94 -> #DIV/0! | K95: 100895 | L95: 127.175 | N95: 101695 | O95: 115.23333 | Q95: 100895 | R95: 4
F96: =IFERROR((C96-D96)/C96, "") | G96: =IFERROR((D96-E96)/D96, "") | H96: =(D96-D95)/D95 -> #DIV/0! | K96: 100896 | L96: 86.8 | N96: 101310 | O96: 136.5 | Q96: 100896 | R96: 7
F97: =IFERROR((C97-D97)/C97, "") | G97: =IFERROR((D97-E97)/D97, "") | H97: =(D97-D96)/D96 -> #DIV/0! | K97: 100899 | L97: 150 | N97: IT-IN-M3 | O97: 201.25 | Q97: 100899 | R97: 1
K98: 100900 | L98: 140.4 | N98: 101617 | O98: 228.3 | Q98: 100900 | R98: 2
K99: 100903 | L99: 123.73333 | N99: 101405 | O99: 77.3 | Q99: 100903 | R99: 3
K100: 100933 | L100: 130.7 | N100: 100547 | O100: 96.5 | Q100: 100933 | R100: 1
K101: 100937 | L101: 130.3 | N101: 100549 | O101: 124.1 | Q101: 100937 | R101: 2
K102: 101291 | L102: 182.1 | N102: 100548 | O102: 148.35 | Q102: 101291 | R102: 1
K103: 101309 | L103: 77 | N103: 101499 | O103: 177.65 | Q103: 101309 | R103: 1
...

Sheet Job Code Table
A1: effectiveStartDate | B1: effectiveEndDate | C1: effectiveStatus | D1: externalCode | E1: Local Job Title (Label) | F1: Workers Comp Code | G1: Job Level (Picklist Label) | H1: Permanent / Temporary (Picklist Label) | I1: Employee Class (Picklist Label) | J1: Employee Type (Picklist Label) | K1: Pay Band (Name) | L1: Zone (Picklist Label) | M1: Sales Comp Target | N1: Officer (Picklist Label) | O1: Local Function (Label) | P1: Local Sub-Function (Name) | Q1: Global Functional Area (Picklist Label) | R1: Global Function (Picklist Label) | S1: Global Talent Segment (Picklist Label) | T1: Global Cluster (Picklist Label) | U1: Global Grade (Picklist Label) | V1: Global Job Code | W1: EEO Category 1 (Picklist Label) | X1: flsaStatusUSA (Picklist Label) | Y1: Employing Entity ID
A2: 45382 | B2: 2958465 | C2: A | D2: 100000 | E2: AVP Tax | F2: 8810 | G2: AVP | H2: Permanent | I2: Employee | J2: Salaried | K2: E1 | N2: No | O2: Executive | P2: Other OE | Q2: Central Functions | R2: Finance | S2: Tax | T2: Allianz Executive | U2: AGS 13 | V2: FIN-TAX-AE13 | W2: 1.2 First/ Mid-Level Officials and Managers | X2: Exempt | Y2: US0003
A3: 45382 | B3: 2958465 | C3: A | D3: 100001 | E3: AZSC Intern | F3: 8810 | G3: NA | H3: Temporary | I3: Intern | J3: Hourly | K3: Z | N3: No | O3: Out of Scope | P3: Out of Scope | Q3: Operations | R3: Z Out of Scope | S3: Out of scope | T3: Not Applicable | U3: Not Applicable | V3: ZOS-OOS-NA | W3: No EEO-1 Reporting | X3: Nonexempt | Y3: US0003
A4: 45382 | B4: 2958465 | C4: A | D4: 100002 | E4: Tax Analyst | F4: 8810 | G4: Ind Contributor - Journey | H4: Permanent | I4: Employee | J4: Salaried | K4: 3 | L4: 2 | N4: No | O4: Finance | P4: Tax | Q4: Central Functions | R4: Finance | S4: Tax | T4: Associate | U4: AGS 9 | V4: FIN-TAX-AS09 | W4: 2. Professionals | X4: Exempt | Y4: US0003
A5: 45382 | B5: 2958465 | C5: A | D5: 100003 | E5: Tax Analyst Senior | F5: 8810 | G5: Ind Contributor - Senior | H5: Permanent | I5: Employee | J5: Salaried | K5: 4 | L5: 2 | N5: No | O5: Finance | P5: Tax | Q5: Central Functions | R5: Finance | S5: Tax | T5: Associate | U5: AGS 10 | V5: FIN-TAX-AS10 | W5: 2. Professionals | X5: Exempt | Y5: US0003
A6: 45382 | B6: 2958465 | C6: A | D6: 100004 | E6: Tax Director | F6: 8810 | G6: Director | H6: Permanent | I6: Employee | J6: Salaried | K6: 8 | L6: 2 | N6: No | O6: Finance | P6: Tax | Q6: Central Functions | R6: Finance | S6: Tax | T6: Senior Associate | U6: AGS 12 | V6: FIN-TAX-SA12 | W6: 1.2 First/ Mid-Level Officials and Managers | X6: Exempt | Y6: US0003
A7: 45382 | B7: 2958465 | C7: A | D7: 100005 | E7: Tax Manager | F7: 8810 | G7: Ind Contributor - Specialist | H7: Permanent | I7: Employee | J7: Salaried | K7: 6 | L7: 2 | N7: No | O7: Finance | P7: Tax | Q7: Central Functions | R7: Finance | S7: Tax | T7: Senior Associate | U7: AGS 11 | V7: FIN-TAX-SA11 | W7: 1.2 First/ Mid-Level Officials and Managers | X7: Exempt | Y7: US0003
A8: 45382 | B8: 2958465 | C8: A | D8: 100006 | E8: Tax Senior Director | F8: 8810 | G8: Senior Director | H8: Permanent | I8: Employee | J8: Salaried | K8: 9 | L8: 2 | N8: No | O8: Finance | P8: Tax | Q8: Central Functions | R8: Finance | S8: Tax | T8: Senior Associate | U8: AGS 12 | V8: FIN-TAX-SA12 | W8: 1.2 First/ Mid-Level Officials and Managers | X8: Exempt | Y8: US0003
A9: 45382 | B9: 2958465 | C9: A | D9: 100007 | E9: Tax Senior Manager | F9: 8810 | G9: Manager | H9: Permanent | I9: Employee | J9: Salaried | K9: 7 | L9: 2 | N9: No | O9: Finance | P9: Tax | Q9: Central Functions | R9: Finance | S9: Tax | T9: Senior Associate | U9: AGS 11 | V9: FIN-TAX-SA11 | W9: 1.2 First/ Mid-Level Officials and Managers | X9: Exempt | Y9: US0003
A10: 45382 | B10: 2958465 | C10: A | D10: 100008 | E10: VP Tax | F10: 8810 | G10: VP | H10: Permanent | I10: Employee | J10: Salaried | K10: E3 | N10: No | O10: Executive | P10: Other OE | Q10: Central Functions | R10: Finance | S10: Tax | T10: Allianz Executive | U10: AGS 15 | V10: FIN-TAX-AE15 | W10: 1.2 First/ Mid-Level Officials and Managers | X10: Exempt | Y10: US0003
A11: 45040 | B11: 2958465 | C11: A | D11: 100009 | E11: C-Consultant | F11: 8810 | G11: NA | H11: Temporary | I11: Non-employee / Externals | J11: Salaried | K11: Z | N11: No | O11: Temporary | Q11: Operations | R11: Z Out of Scope | S11: Out of scope | T11: Not Applicable | U11: Not Applicable | V11: ZOS-OOS-NA | W11: No EEO-1 Reporting | X11: No FLSA Required | Y11: US0728,US0821,US0006,US0003,US0009
A12: 45040 | B12: 2958465 | C12: A | D12: 100009 | E12: C-Consultant | F12: 8810 | G12: NA | H12: Temporary | I12: Non-employee / Externals | J12: Salaried | K12: Z | N12: No | O12: Temporary | Q12: Operations | R12: Z Out of Scope | S12: Out of scope | T12: Not Applicable | U12: Not Applicable | V12: ZOS-OOS-NA | W12: No EEO-1 Reporting | X12: No FLSA Required | Y12: US0728,US0821,US0006,US0003,US0009
A13: 45040 | B13: 2958465 | C13: A | D13: 100009 | E13: C-Consultant | F13: 8810 | G13: NA | H13: Temporary | I13: Non-employee / Externals | J13: Salaried | K13: Z | N13: No | O13: Temporary | Q13: Operations | R13: Z Out of Scope | S13: Out of scope | T13: Not Applicable | U13: Not Applicable | V13: ZOS-OOS-NA | W13: No EEO-1 Reporting | X13: No FLSA Required | Y13: US0728,US0821,US0006,US0003,US0009
A14: 45040 | B14: 2958465 | C14: A | D14: 100009 | E14: C-Consultant | F14: 8810 | G14: NA | H14: Temporary | I14: Non-employee / Externals | J14: Salaried | K14: Z | N14: No | O14: Temporary | Q14: Operations | R14: Z Out of Scope | S14: Out of scope | T14: Not Applicable | U14: Not Applicable | V14: ZOS-OOS-NA | W14: No EEO-1 Reporting | X14: No FLSA Required | Y14: US0728,US0821,US0006,US0003,US0009
A15: 45040 | B15: 2958465 | C15: A | D15: 100009 | E15: C-Consultant | F15: 8810 | G15: NA | H15: Temporary | I15: Non-employee / Externals | J15: Salaried | K15: Z | N15: No | O15: Temporary | Q15: Operations | R15: Z Out of Scope | S15: Out of scope | T15: Not Applicable | U15: Not Applicable | V15: ZOS-OOS-NA | W15: No EEO-1 Reporting | X15: No FLSA Required | Y15: US0728,US0821,US0006,US0003,US0009
A16: 45323 | B16: 2958465 | C16: A | D16: 100010 | E16: Expatriate | F16: 8810 | G16: NA | H16: Permanent | I16: Expatriate | J16: Salaried | K16: Z | N16: No | O16: Temporary | Q16: Operations | R16: Z Out of Scope | S16: Out of scope | T16: Not Applicable | U16: Not Applicable | V16: ZOS-OOS-NA | W16: 2. Professionals | X16: Exempt | Y16: US0003,US0821,US0006,US0728,US0009,US0967,US0330
A17: 45323 | B17: 2958465 | C17: A | D17: 100010 | E17: Expatriate | F17: 8810 | G17: NA | H17: Permanent | I17: Expatriate | J17: Salaried | K17: Z | N17: No | O17: Temporary | Q17: Operations | R17: Z Out of Scope | S17: Out of scope | T17: Not Applicable | U17: Not Applicable | V17: ZOS-OOS-NA | W17: 2. Professionals | X17: Exempt | Y17: US0003,US0821,US0006,US0728,US0009,US0967,US0330
A18: 45323 | B18: 2958465 | C18: A | D18: 100010 | E18: Expatriate | F18: 8810 | G18: NA | H18: Permanent | I18: Expatriate | J18: Salaried | K18: Z | N18: No | O18: Temporary | Q18: Operations | R18: Z Out of Scope | S18: Out of scope | T18: Not Applicable | U18: Not Applicable | V18: ZOS-OOS-NA | W18: 2. Professionals | X18: Exempt | Y18: US0003,US0821,US0006,US0728,US0009,US0967,US0330
A19: 45323 | B19: 2958465 | C19: A | D19: 100010 | E19: Expatriate | F19: 8810 | G19: NA | H19: Permanent | I19: Expatriate | J19: Salaried | K19: Z | N19: No | O19: Temporary | Q19: Operations | R19: Z Out of Scope | S19: Out of scope | T19: Not Applicable | U19: Not Applicable | V19: ZOS-OOS-NA | W19: 2. Professionals | X19: Exempt | Y19: US0003,US0821,US0006,US0728,US0009,US0967,US0330
A20: 45323 | B20: 2958465 | C20: A | D20: 100010 | E20: Expatriate | F20: 8810 | G20: NA | H20: Permanent | I20: Expatriate | J20: Salaried | K20: Z | N20: No | O20: Temporary | Q20: Operations | R20: Z Out of Scope | S20: Out of scope | T20: Not Applicable | U20: Not Applicable | V20: ZOS-OOS-NA | W20: 2. Professionals | X20: Exempt | Y20: US0003,US0821,US0006,US0728,US0009,US0967,US0330
A21: 45323 | B21: 2958465 | C21: A | D21: 100010 | E21: Expatriate | F21: 8810 | G21: NA | H21: Permanent | I21: Expatriate | J21: Salaried | K21: Z | N21: No | O21: Temporary | Q21: Operations | R21: Z Out of Scope | S21: Out of scope | T21: Not Applicable | U21: Not Applicable | V21: ZOS-OOS-NA | W21: 2. Professionals | X21: Exempt | Y21: US0003,US0821,US0006,US0728,US0009,US0967,US0330
A22: 45323 | B22: 2958465 | C22: A | D22: 100010 | E22: Expatriate | F22: 8810 | G22: NA | H22: Permanent | I22: Expatriate | J22: Salaried | K22: Z | N22: No | O22: Temporary | Q22: Operations | R22: Z Out of Scope | S22: Out of scope | T22: Not Applicable | U22: Not Applicable | V22: ZOS-OOS-NA | W22: 2. Professionals | X22: Exempt | Y22: US0003,US0821,US0006,US0728,US0009,US0967,US0330
... A39: 45040 | B39: 2958465 | C39: A | D39: 100013 | E39: Temporary | F39: 8810 | G39: NA | H39: Temporary | I39: Non-employee / Externals | J39: Salaried | K39: Z | N39: No | O39: Temporary | Q39: Operations | R39: Z Out of Scope | S39: Out of scope | T39: Not Applicable | U39: Not Applicable | V39: ZOS-OOS-NA | W39: No EEO-1 Reporting | X39: Nonexempt | Y39: US0003,US0821,US0728,US0006,US0009
A40: 45502 | B40: 2958465 | C40: A | D40: 100014 | E40: Administrative Assistant | F40: 8810 | G40: Ind Contributor - Associate | H40: Permanent | I40: Employee | J40: Salaried | K40: 2 | L40: 1 | N40: No | O40: Administrative Services | Q40: Operations | R40: Management Support | S40: Personal Assistant | T40: Support | U40: AGS 5 | V40: MS-PEA-SU05 | W40: 5. Administrative Support Workers | X40: Nonexempt | Y40: US0009,US0003
A41: 45502 | B41: 2958465 | C41: A | D41: 100014 | E41: Administrative Assistant | F41: 8810 | G41: Ind Contributor - Associate | H41: Permanent | I41: Employee | J41: Salaried | K41: 2 | L41: 1 | N41: No | O41: Administrative Services | Q41: Operations | R41: Management Support | S41: Personal Assistant | T41: Support | U41: AGS 5 | V41: MS-PEA-SU05 | W41: 5. Administrative Support Workers | X41: Nonexempt | Y41: US0009,US0003
A42: 45382 | B42: 2958465 | C42: A | D42: 100015 | E42: Compliance Principal | F42: 8810 | G42: Ind Contributor - Specialist | H42: Permanent | I42: Employee | J42: Salaried | K42: 7 | L42: 1 | N42: No | O42: Compliance | P42: Compliance | Q42: Central Functions | R42: Compliance | S42: Compliance | T42: Senior Associate | U42: AGS 11 | V42: COMP-COM-SA11 | W42: 2. Professionals | X42: Exempt | Y42: US0006,US0009
A43: 45382 | B43: 2958465 | C43: A | D43: 100015 | E43: Compliance Principal | F43: 8810 | G43: Ind Contributor - Specialist | H43: Permanent | I43: Employee | J43: Salaried | K43: 7 | L43: 1 | N43: No | O43: Compliance | P43: Compliance | Q43: Central Functions | R43: Compliance | S43: Compliance | T43: Senior Associate | U43: AGS 11 | V43: COMP-COM-SA11 | W43: 2. Professionals | X43: Exempt | Y43: US0006,US0009
A44: 45382 | B44: 2958465 | C44: A | D44: 100016 | E44: Account Manager - Global Programs | F44: 8810 | G44: Ind Contributor - Senior | H44: Permanent | I44: Employee | J44: Salaried | K44: Z | N44: No | O44: Human Resources | P44: Total Rewards | Q44: Operations | R44: Z Out of Scope | S44: Out of scope | T44: Associate | U44: AGS 10 | V44: ZOS-OOS-AS10 | W44: 2. Professionals | X44: Exempt | Y44: US0009
A45: 45382 | B45: 2958465 | C45: A | D45: 100017 | E45: Account Manager Senior | F45: 8810 | G45: Ind Contributor - Senior | H45: Permanent | I45: Employee | J45: Salaried | K45: Z | N45: No | O45: Insurance Distribution | P45: National Accounts | Q45: Sales/Distribution | R45: Cross-Channel Management | S45: Account Management | T45: Associate | U45: AGS 10 | V45: CCM-ACM-AS10 | W45: 2. Professionals | X45: Exempt | Y45: US0009
A46: 45382 | B46: 2958465 | C46: A | D46: 100018 | E46: Account Services Rep | F46: 8810 | G46: Ind Contributor - Associate | H46: Permanent | I46: Employee | J46: Salaried | K46: 3 | L46: 1 | N46: No | O46: Operations | P46: Case Management | Q46: Operations | R46: Policy Management / Underwriting | S46: Standard Policy Administration | T46: Support | U46: AGS 7 | V46: PMUW-SPA-SU07 | W46: 5. Administrative Support Workers | X46: Nonexempt | Y46: US0009
A47: 45382 | B47: 2958465 | C47: A | D47: 100019 | E47: Account Services Rep Associate | F47: 8810 | G47: Ind Contributor - Associate | H47: Permanent | I47: Employee | J47: Salaried | K47: 2 | L47: 1 | N47: No | O47: Operations | P47: Case Management | Q47: Operations | R47: Policy Management / Underwriting | S47: Standard Policy Administration | T47: Support | U47: AGS 6 | V47: PMUW-SPA-SU06 | W47: 5. Administrative Support Workers | X47: Nonexempt | Y47: US0009
A48: 45382 | B48: 2958465 | C48: A | D48: 100020 | E48: Account Services Rep Senior | F48: 8810 | G48: Ind Contributor - Journey | H48: Permanent | I48: Employee | J48: Salaried | K48: 4 | L48: 1 | N48: No | O48: Operations | P48: Case Management | Q48: Operations | R48: Policy Management / Underwriting | S48: Policy Administration | T48: Associate | U48: AGS 8 | V48: PMUW-POL-AS08 | W48: 2. Professionals | X48: Exempt | Y48: US0009
A49: 45382 | B49: 2958465 | C49: A | D49: 100021 | E49: Accountant | F49: 8810 | G49: Ind Contributor - Journey | H49: Permanent | I49: Employee | J49: Salaried | K49: 3 | L49: 2 | N49: No | O49: Finance | P49: Accounting | Q49: Central Functions | R49: Finance | S49: Accounting Closing, Reporting and Policies | T49: Associate | U49: AGS 9 | V49: FIN-ACR-AS09 | W49: 2. Professionals | X49: Exempt | Y49: US0009
A50: 45502 | B50: 2958465 | C50: A | D50: 100022 | E50: Accountant Principal | F50: 8810 | G50: Ind Contributor - Specialist | H50: Permanent | I50: Employee | J50: Salaried | K50: 6 | L50: 2 | N50: No | O50: Accounting | Q50: Central Functions | R50: Finance | S50: Accounting Closing, Reporting and Policies | T50: Senior Associate | U50: AGS 11 | V50: FIN-ACR-SA11 | W50: 2. Professionals | X50: Exempt | Y50: US0009
A51: 45382 | B51: 2958465 | C51: A | D51: 100023 | E51: Accountant Senior | F51: 8810 | G51: Ind Contributor - Senior | H51: Permanent | I51: Employee | J51: Salaried | K51: 5 | L51: 2 | N51: No | O51: Finance | P51: Accounting | Q51: Central Functions | R51: Finance | S51: Accounting Closing, Reporting and Policies | T51: Associate | U51: AGS 10 | V51: FIN-ACR-AS10 | W51: 2. Professionals | X51: Exempt | Y51: US0009,US0003
A52: 45382 | B52: 2958465 | C52: A | D52: 100023 | E52: Accountant Senior | F52: 8810 | G52: Ind Contributor - Senior | H52: Permanent | I52: Employee | J52: Salaried | K52: 5 | L52: 2 | N52: No | O52: Finance | P52: Accounting | Q52: Central Functions | R52: Finance | S52: Accounting Closing, Reporting and Policies | T52: Associate | U52: AGS 10 | V52: FIN-ACR-AS10 | W52: 2. Professionals | X52: Exempt | Y52: US0009,US0003
A53: 45382 | B53: 2958465 | C53: A | D53: 100024 | E53: Actuarial Analyst | F53: 8810 | G53: Ind Contributor - Journey | H53: Permanent | I53: Employee | J53: Salaried | K53: 3 | L53: 2 | N53: No | O53: Actuarial | P53: Actuarial | Q53: Product Provider | R53: Actuarial | S53: Actuary L&H Finance/Reserving | T53: Associate | U53: AGS 8 | V53: ACT-AFL-AS08 | W53: 2. Professionals | X53: Exempt | Y53: US0009
A54: 45382 | B54: 2958465 | C54: A | D54: 100025 | E54: Actuary | F54: 8810 | G54: Director | H54: Permanent | I54: Employee | J54: Salaried | K54: 8 | L54: 1 | N54: No | O54: Actuarial | P54: Actuarial | Q54: Product Provider | R54: Actuarial | S54: Management | T54: Senior Associate | U54: AGS 11 | V54: ACT-MAN-SA11 | W54: 1.2 First/ Mid-Level Officials and Managers | X54: Exempt | Y54: US0009
A55: 45382 | B55: 2958465 | C55: A | D55: 100026 | E55: Admin System Testing Analyst | F55: 8810 | G55: Ind Contributor - Journey | H55: Permanent | I55: Employee | J55: Salaried | K55: 4 | L55: 3 | N55: No | O55: Actuarial | P55: Systems Actuary | Q55: Product Provider | R55: Actuarial | S55: Actuary L&H Finance/Reserving | T55: Associate | U55: AGS 9 | V55: ACT-AFL-AS09 | W55: 2. Professionals | X55: Exempt | Y55: US0009
A56: 45382 | B56: 2958465 | C56: A | D56: 100027 | E56: Admin System Testing Analyst Principal | F56: 8810 | G56: Ind Contributor - Specialist | H56: Permanent | I56: Employee | J56: Salaried | K56: 6 | L56: 3 | N56: No | O56: Actuarial | P56: Systems Actuary | Q56: Product Provider | R56: Actuarial | S56: Actuary L&H Finance/Reserving | T56: Senior Associate | U56: AGS 11 | V56: ACT-AFL-SA11 | W56: 2. Professionals | X56: Exempt | Y56: US0009
A57: 45382 | B57: 2958465 | C57: A | D57: 100028 | E57: Admin System Testing Analyst Senior | F57: 8810 | G57: Ind Contributor - Senior | H57: Permanent | I57: Employee | J57: Salaried | K57: 5 | L57: 3 | N57: No | O57: Actuarial | P57: Systems Actuary | Q57: Product Provider | R57: Actuarial | S57: Actuary L&H Finance/Reserving | T57: Associate | U57: AGS 10 | V57: ACT-AFL-AS10 | W57: 2. Professionals | X57: Exempt | Y57: US0009
A58: 45552 | B58: 2958465 | C58: A | D58: 100029 | E58: Administrative Assistant Senior | F58: 8810 | G58: Ind Contributor - Journey | H58: Permanent | I58: Employee | J58: Salaried | K58: 2 | L58: 2 | N58: No | O58: Administrative Services | Q58: Operations | R58: Management Support | S58: Personal Assistant | T58: Support | U58: AGS 6 | V58: MS-PEA-SU06 | W58: 5. Administrative Support Workers | X58: Nonexempt | Y58: US0009
A59: 45382 | B59: 2958465 | C59: A | D59: 100030 | E59: Advanced Markets Consultant | F59: 8810 | G59: Ind Contributor - Senior | H59: Permanent | I59: Employee | J59: Salaried | K59: 6 | L59: 1 | N59: No | O59: Insurance Distribution | P59: Advanced Markets | Q59: Central Functions | R59: XX_All Others | S59: Center of Expertise | T59: Associate | U59: AGS 9 | V59: AOT-COE-AS09 | W59: 2. Professionals | X59: Exempt | Y59: US0009
A60: 45382 | B60: 2958465 | C60: A | D60: 100031 | E60: Advanced Markets Consultant Senior | F60: 8810 | G60: Ind Contributor - Specialist | H60: Permanent | I60: Employee | J60: Salaried | K60: 7 | L60: 1 | N60: No | O60: Insurance Distribution | P60: Advanced Markets | Q60: Central Functions | R60: XX_All Others | S60: Center of Expertise | T60: Associate | U60: AGS 10 | V60: AOT-COE-AS10 | W60: 2. Professionals | X60: Exempt | Y60: US0009
A61: 45382 | B61: 2958465 | C61: A | D61: 100032 | E61: Advanced Markets Director | F61: 8810 | G61: Director | H61: Permanent | I61: Employee | J61: Salaried | K61: 8 | L61: 1 | N61: No | O61: Insurance Distribution | P61: Advanced Markets | Q61: Central Functions | R61: XX_All Others | S61: Center of Expertise | T61: Senior Associate | U61: AGS 11 | V61: AOT-COE-SA11 | W61: 2. Professionals | X61: Exempt | Y61: US0009
A62: 45382 | B62: 2958465 | C62: A | D62: 100033 | E62: Advanced Markets Manager | F62: 8810 | G62: Ind Contributor - Specialist | H62: Permanent | I62: Employee | J62: Salaried | K62: 6 | L62: 2 | N62: No | O62: Insurance Distribution | P62: Advanced Markets | Q62: Market Management | R62: Operational Market Management | S62: Content Marketing | T62: Senior Associate | U62: AGS 11 | V62: OMM-CON-SA11 | W62: 1.2 First/ Mid-Level Officials and Managers | X62: Exempt | Y62: US0009
A63: 45382 | B63: 2958465 | C63: A | D63: 100034 | E63: Advanced Markets Senior Director | F63: 8810 | G63: Senior Director | H63: Permanent | I63: Employee | J63: Salaried | K63: 9 | L63: 2 | N63: No | O63: Insurance Distribution | P63: Advanced Markets | Q63: Central Functions | R63: XX_All Others | S63: Center of Expertise | T63: Senior Associate | U63: AGS 12 | V63: AOT-COE-SA12 | W63: 1.2 First/ Mid-Level Officials and Managers | X63: Exempt | Y63: US0009
A64: 45382 | B64: 2958465 | C64: A | D64: 100035 | E64: Advanced Strategies & Planning Platforms Director | F64: 8810 | G64: Director | H64: Permanent | I64: Employee | J64: Salaried | K64: 8 | L64: 1 | N64: No | O64: Insurance Distribution | P64: Sales Tools & Platforms | Q64: Central Functions | R64: XX_All Others | S64: Center of Expertise | T64: Senior Associate | U64: AGS 11 | V64: AOT-COE-SA11 | W64: 1.2 First/ Mid-Level Officials and Managers | X64: Exempt | Y64: US0009
A65: 45382 | B65: 2958465 | C65: A | D65: 100036 | E65: Agile Coach | F65: 8810 | G65: Ind Contributor - Specialist | H65: Permanent | I65: Employee | J65: Salaried | K65: 7 | L65: 3 | N65: No | O65: Project Management/Agile | P65: Agile | Q65: Central Functions | R65: Other Central Functions | S65: Agile Master and Agile Coach | T65: Associate | U65: AGS 10 | V65: OCF-AGI-AS10 | W65: 2. Professionals | X65: Exempt | Y65: US0009
A66: 45382 | B66: 2958465 | C66: A | D66: 100037 | E66: Agile Coach Senior | F66: 8810 | G66: Ind Contributor - Specialist | H66: Permanent | I66: Employee | J66: Salaried | K66: 8 | L66: 3 | N66: No | O66: Project Management/Agile | P66: Agile | Q66: Central Functions | R66: Other Central Functions | S66: Agile Master and Agile Coach | T66: Senior Associate | U66: AGS 11 | V66: OCF-AGI-SA11 | W66: 2. Professionals | X66: Exempt | Y66: US0009
A67: 45382 | B67: 2958465 | C67: A | D67: 100039 | E67: Agile Technical Director | F67: 8810 | G67: Director | H67: Permanent | I67: Employee | J67: Salaried | K67: 8 | L67: 1 | N67: No | O67: Project Management/Agile | P67: Agile | Q67: Central Functions | R67: Other Central Functions | S67: Agile Master and Agile Coach | T67: Senior Associate | U67: AGS 12 | V67: OCF-AGI-SA12 | W67: 2. Professionals | X67: Exempt | Y67: US0009
A68: 45566 | B68: 2958465 | C68: A | D68: 100041 | E68: AIM Senior Analyst-Investments | F68: 8810 | G68: Ind Contributor - Journey | H68: Permanent | I68: Employee | J68: Salaried | K68: I-1 | L68: 2 | N68: No | O68: Investment Management | P68: Investment Operations | Q68: Central Functions | R68: Investment Management (AIM) | S68: Investment Strategist | T68: Associate | U68: AGS 9 | V68: IM-INS-AS09 | W68: 2. Professionals | X68: Exempt | Y68: US0009
A69: 45489 | B69: 2958465 | C69: A | D69: 100046 | E69: AIM Analyst-Investment Operations | F69: 8810 | G69: Ind Contributor - Journey | H69: Permanent | I69: Employee | J69: Salaried | K69: I-1 | L69: 1 | N69: No | O69: Investment Management | P69: Investment Operations | Q69: Central Functions | R69: Investment Management (AIM) | S69: Investment Operations Specialist | T69: Associate | U69: AGS 8 | V69: IM-IOS-AS08 | W69: 2. Professionals | X69: Exempt | Y69: US0009
A70: 45489 | B70: 2958465 | C70: A | D70: 100054 | E70: AIM Associate-Investment Operations | F70: 8810 | G70: Ind Contributor - Senior | H70: Permanent | I70: Employee | J70: Salaried | K70: I-2 | L70: 2 | N70: No | O70: Investment Management | P70: Investment Operations | Q70: Central Functions | R70: Investment Management (AIM) | S70: Investment Operations Specialist | T70: Associate | U70: AGS 9 | V70: IM-IOS-AS09 | W70: 2. Professionals | X70: Exempt | Y70: US0009
... A82: 45382 | B82: 2958465 | C82: A | D82: 100106 | E82: AIM VP/AZL Director II-Investment Operations | F82: 8810 | G82: Senior Director | H82: Permanent | I82: Employee | J82: Salaried | K82: I-5 | L82: 2 | N82: No | O82: Investment Management | P82: Investment Operations | Q82: Central Functions | R82: Investment Management (AIM) | S82: Investment Operations | T82: Senior Associate | U82: AGS 12 | V82: IM-INO-SA12 | W82: 1.2 First/ Mid-Level Officials and Managers | X82: Exempt | Y82: US0009
A83: 45382 | B83: 2958465 | C83: A | D83: 100107 | E83: FAVP Business Development | F83: 8810 | G83: Senior Director | H83: Permanent | I83: Sales Employee | J83: Salaried | K83: S3 | M83: 125000 | N83: No | O83: Insurance Distribution | P83: National Sales Manager | Q83: Central Functions | R83: XX_All Others | S83: Center of Expertise | T83: Senior Associate | U83: AGS 11 | V83: AOT-COE-SA11 | W83: 4. Sales Workers | X83: Exempt | Y83: US0009
A84: 45382 | B84: 2958465 | C84: A | D84: 100114 | E84: AIM VP/AZL Director II-Trading | F84: 8810 | G84: Senior Director | H84: Permanent | I84: Employee | J84: Salaried | K84: I-5 | L84: 2 | N84: No | O84: Investment Management | P84: Trading | Q84: Central Functions | R84: Investment Management (AIM) | S84: Investment Implementation | T84: Senior Associate | U84: AGS 12 | V84: IM-INI-SA12 | W84: 1.2 First/ Mid-Level Officials and Managers | X84: Exempt | Y84: US0009
A85: 45382 | B85: 2958465 | C85: A | D85: 100115 | E85: ALFS Supervision Senior Director | F85: 8810 | G85: Senior Director | H85: Permanent | I85: Employee | J85: Salaried | K85: 9 | L85: 1 | N85: No | O85: Insurance Distribution | P85: Sales Strategy & Operations | Q85: Central Functions | R85: XX_All Others | S85: Management | T85: Senior Associate | U85: AGS 12 | V85: AOT-MAN-SA12 | W85: 1.2 First/ Mid-Level Officials and Managers | X85: Exempt | Y85: US0009
A86: 45040 | B86: 45688 | C86: A | D86: 100118 | E86: Application Support Team Lead | F86: 8810 | G86: Ind Contributor - Specialist | H86: Permanent | I86: Employee | J86: Salaried | K86: 6 | L86: 2 | N86: No | O86: IT Development | Q86: Operations | R86: IT | S86: Application Development | T86: Associate | U86: AGS 10 | V86: IT-APD-AS10 | W86: 2. Professionals | X86: Exempt | Y86: US0821
A87: 45382 | B87: 2958465 | C87: A | D87: 100119 | E87: Art Director I | F87: 8810 | G87: Ind Contributor - Journey | H87: Permanent | I87: Employee | J87: Salaried | K87: 4 | L87: 2 | N87: No | O87: Communications | P87: Design Services | Q87: Market Management | R87: Operational Market Management | S87: Content Marketing | T87: Associate | U87: AGS 8 | V87: OMM-CON-AS08 | W87: 2. Professionals | X87: Exempt | Y87: US0009
A88: 45382 | B88: 2958465 | C88: A | D88: 100120 | E88: Art Director II | F88: 8810 | G88: Ind Contributor - Senior | H88: Permanent | I88: Employee | J88: Salaried | K88: 5 | L88: 2 | N88: No | O88: Communications | P88: Design Services | Q88: Market Management | R88: Operational Market Management | S88: Content Marketing | T88: Associate | U88: AGS 9 | V88: OMM-CON-AS09 | W88: 2. Professionals | X88: Exempt | Y88: US0009
A89: 45382 | B89: 2958465 | C89: A | D89: 100121 | E89: Art Director III | F89: 8810 | G89: Ind Contributor - Specialist | H89: Permanent | I89: Employee | J89: Salaried | K89: 6 | L89: 2 | N89: No | O89: Communications | P89: Design Services | Q89: Market Management | R89: Operational Market Management | S89: Content Marketing | T89: Associate | U89: AGS 10 | V89: OMM-CON-AS10 | W89: 2. Professionals | X89: Exempt | Y89: US0009
A90: 45382 | B90: 2958465 | C90: A | D90: 100122 | E90: Art Director III-Brand Principal | F90: 8810 | G90: Ind Contributor - Specialist | H90: Permanent | I90: Employee | J90: Salaried | K90: 6 | L90: 2 | N90: No | O90: Marketing | P90: Brand Marketing | Q90: Market Management | R90: Operational Market Management | S90: Content Marketing | T90: Associate | U90: AGS 10 | V90: OMM-CON-AS10 | W90: 2. Professionals | X90: Exempt | Y90: US0009
A91: 45565 | B91: 2958465 | C91: A | D91: 100123 | E91: National Accounts Associate | F91: 8810 | G91: Ind Contributor - Journey | H91: Permanent | I91: Sales Employee | J91: Salaried | K91: S3 | M91: 30000 | N91: No | O91: Insurance Distribution | P91: National Accounts | Q91: Sales/Distribution | R91: Cross-Channel Management | S91: Account Management | T91: Associate | U91: AGS 9 | V91: CCM-ACM-AS09 | W91: 4. Sales Workers | X91: Exempt | Y91: US0009
A92: 45565 | B92: 2958465 | C92: A | D92: 100124 | E92: National Accounts Associate Senior | F92: 8810 | G92: Ind Contributor - Senior | H92: Permanent | I92: Sales Employee | J92: Salaried | K92: S3 | M92: 45000 | N92: No | O92: Insurance Distribution | P92: National Accounts | Q92: Sales/Distribution | R92: Cross-Channel Management | S92: Account Management | T92: Associate | U92: AGS 10 | V92: CCM-ACM-AS10 | W92: 4. Sales Workers | X92: Exempt | Y92: US0009
A93: 45382 | B93: 2958465 | C93: A | D93: 100125 | E93: ASA Director | F93: 8810 | G93: Director | H93: Permanent | I93: Employee | J93: Salaried | K93: 8 | L93: 2 | N93: No | O93: Insurance Distribution | P93: National Accounts | Q93: Sales/Distribution | R93: Cross-Channel Management | S93: Management | T93: Senior Associate | U93: AGS 12 | V93: CCM-MAN-SA12 | W93: 1.2 First/ Mid-Level Officials and Managers | X93: Exempt | Y93: US0009
A94: 45489 | B94: 2958465 | C94: A | D94: 100126 | E94: Distribution Program Coordinator Senior | F94: 8810 | G94: Ind Contributor - Journey | H94: Permanent | I94: Employee | J94: Salaried | K94: 4 | L94: 2 | N94: No | O94: Administrative Services | P94: Administrative/Executive Assistant | Q94: Sales/Distribution | R94: Cross-Channel Management | S94: Personal Assistant | T94: Associate | U94: AGS 8 | V94: CCM-PEA-AS08 | W94: 2. Professionals | X94: Exempt | Y94: US0009
A95: 45565 | B95: 2958465 | C95: A | D95: 100127 | E95: National Accounts Relationship Manager | F95: 8810 | G95: Ind Contributor - Senior | H95: Permanent | I95: Sales Employee | J95: Salaried | K95: S3 | M95: 100000 | N95: No | O95: Insurance Distribution | P95: National Accounts | Q95: Sales/Distribution | R95: Cross-Channel Management | S95: Account Management | T95: Senior Associate | U95: AGS 11 | V95: CCM-ACM-SA11 | W95: 4. Sales Workers | X95: Exempt | Y95: US0009
A96: 45565 | B96: 2958465 | C96: A | D96: 100128 | E96: National Accounts Relationship Senior Manager | F96: 8810 | G96: Ind Contributor - Specialist | H96: Permanent | I96: Sales Employee | J96: Salaried | K96: S2 | M96: 125000 | N96: No | O96: Insurance Distribution | P96: National Accounts | Q96: Sales/Distribution | R96: Cross-Channel Management | S96: Account Management | T96: Senior Associate | U96: AGS 12 | V96: CCM-ACM-SA12 | W96: 4. Sales Workers | X96: Exempt | Y96: US0009
A97: 45382 | B97: 2958465 | C97: A | D97: 100129 | E97: ASaM Manager | F97: 8810 | G97: Manager | H97: Permanent | I97: Employee | J97: Salaried | K97: 6 | L97: 1 | N97: No | O97: Operations | P97: Quality Assurance | Q97: Operations | R97: Organizational Management | S97: Management | T97: Senior Associate | U97: AGS 11 | V97: OM-MAN-SA11 | W97: 1.2 First/ Mid-Level Officials and Managers | X97: Exempt | Y97: US0009
A98: 45040 | B98: 2958465 | C98: A | D98: 100131 | E98: ASaM Manager Senior | F98: 8810 | G98: Manager | H98: Permanent | I98: Employee | J98: Salaried | K98: 7 | L98: 1 | N98: No | O98: Operations | Q98: Operations | R98: Organizational Management | S98: Management | T98: Senior Associate | U98: AGS 11 | V98: OM-MAN-SA11 | W98: 1.2 First/ Mid-Level Officials and Managers | X98: Exempt | Y98: US0821
A99: 45382 | B99: 2958465 | C99: A | D99: 100132 | E99: Assistant Actuary | F99: 8810 | G99: Ind Contributor - Specialist | H99: Permanent | I99: Employee | J99: Salaried | K99: 6 | L99: 2 | N99: No | O99: Actuarial | P99: Actuarial | Q99: Product Provider | R99: Actuarial | S99: Actuary L&H Finance/Reserving | T99: Associate | U99: AGS 10 | V99: ACT-AFL-AS10 | W99: 2. Professionals | X99: Exempt | Y99: US0009
A100: 45382 | B100: 2958465 | C100: A | D100: 100133 | E100: Associate Actuary | F100: 8810 | G100: Ind Contributor - Specialist | H100: Permanent | I100: Employee | J100: Salaried | K100: 7 | L100: 1 | N100: No | O100: Actuarial | P100: Actuarial | Q100: Product Provider | R100: Actuarial | S100: Management | T100: Senior Associate | U100: AGS 11 | V100: ACT-MAN-SA11 | W100: 1.2 First/ Mid-Level Officials and Managers | X100: Exempt | Y100: US0009
A101: 45382 | B101: 2958465 | C101: A | D101: 100134 | E101: Attorney | F101: 8810 | G101: Ind Contributor - Specialist | H101: Permanent | I101: Employee | J101: Salaried | K101: 7 | L101: 2 | N101: No | O101: Legal | P101: Legal | Q101: Central Functions | R101: Legal | S101: Legal | T101: Senior Associate | U101: AGS 11 | V101: LEG-LEG-SA11 | W101: 2. Professionals | X101: Exempt | Y101: US0009
A102: 45382 | B102: 2958465 | C102: A | D102: 100135 | E102: Audit Analyst Associate | F102: 8810 | G102: Ind Contributor - Associate | H102: Permanent | I102: Employee | J102: Salaried | K102: 3 | L102: 2 | N102: No | O102: Audit | P102: Audit | Q102: Central Functions | R102: Audit | S102: Internal Audit | T102: Associate | U102: AGS 8 | V102: AUDIT-INA-AS08 | W102: 2. Professionals | X102: Exempt | Y102: US0009
A103: 45552 | B103: 2958465 | C103: A | D103: 100136 | E103: Audit Analyst Senior | F103: 8810 | G103: Ind Contributor - Senior | H103: Permanent | I103: Employee | J103: Salaried | K103: 5 | L103: 2 | N103: No | O103: Audit | Q103: Central Functions | R103: Audit | S103: Internal Audit | T103: Associate | U103: AGS 10 | V103: AUDIT-INA-AS10 | W103: 2. Professionals | X103: Exempt | Y103: US0009
A104: 45382 | B104: 2958465 | C104: A | D104: 100137 | E104: Audit Director | F104: 8810 | G104: Director | H104: Permanent | I104: Employee | J104: Salaried | K104: 8 | L104: 2 | N104: No | O104: Audit | P104: Audit | Q104: Central Functions | R104: Audit | S104: Management | T104: Senior Associate | U104: AGS 12 | V104: AUDIT-MAN-SA12 | W104: 1.2 First/ Mid-Level Officials and Managers | X104: Exempt | Y104: US0009
A105: 45552 | B105: 2958465 | C105: A | D105: 100138 | E105: Audit Principal | F105: 8810 | G105: Ind Contributor - Specialist | H105: Permanent | I105: Employee | J105: Salaried | K105: 6 | L105: 2 | N105: No | O105: Audit | Q105: Central Functions | R105: Audit | S105: Internal Audit | T105: Senior Associate | U105: AGS 11 | V105: AUDIT-INA-SA11 | W105: 2. Professionals | X105: Exempt | Y105: US0009
A106: 45382 | B106: 2958465 | C106: A | D106: 100139 | E106: Audit Principal-Actuarial | F106: 8810 | G106: Ind Contributor - Specialist | H106: Permanent | I106: Employee | J106: Salaried | K106: 8 | L106: 1 | N106: No | O106: Audit | P106: Audit | Q106: Central Functions | R106: Audit | S106: Internal Audit | T106: Senior Associate | U106: AGS 11 | V106: AUDIT-INA-SA11 | W106: 2. Professionals | X106: Exempt | Y106: US0009
A107: 45382 | B107: 2958465 | C107: A | D107: 100140 | E107: Audit Program Manager | F107: 8810 | G107: Ind Contributor - Specialist | H107: Permanent | I107: Employee | J107: Salaried | K107: 7 | L107: 1 | N107: No | O107: Audit | P107: Audit | Q107: Central Functions | R107: Audit | S107: Internal Audit | T107: Senior Associate | U107: AGS 11 | V107: AUDIT-INA-SA11 | W107: 2. Professionals | X107: Exempt | Y107: US0009
A108: 45382 | B108: 2958465 | C108: A | D108: 100141 | E108: Audit Senior Director | F108: 8810 | G108: Senior Director | H108: Permanent | I108: Employee | J108: Salaried | K108: 9 | L108: 2 | N108: No | O108: Audit | P108: Audit | Q108: Central Functions | R108: Audit | S108: Management | T108: Senior Associate | U108: AGS 12 | V108: AUDIT-MAN-SA12 | W108: 1.2 First/ Mid-Level Officials and Managers | X108: Exempt | Y108: US0009
A109: 45382 | B109: 2958465 | C109: A | D109: 100142 | E109: Automation Analyst | F109: 8810 | G109: Ind Contributor - Journey | H109: Permanent | I109: Employee | J109: Salaried | K109: 4 | L109: 2 | N109: No | O109: Project Management/Agile | P109: Program & Project Management | Q109: Operations | R109: Organizational Management | S109: Business Analysis And Solution Design | T109: Associate | U109: AGS 8 | V109: OM-BAS-AS08 | W109: 2. Professionals | X109: Exempt | Y109: US0009
A110: 45382 | B110: 2958465 | C110: A | D110: 100144 | E110: Automation Analyst Senior | F110: 8810 | G110: Ind Contributor - Senior | H110: Permanent | I110: Employee | J110: Salaried | K110: 5 | L110: 2 | N110: No | O110: Project Management/Agile | P110: Program & Project Management | Q110: Operations | R110: Organizational Management | S110: Business Analysis And Solution Design | T110: Associate | U110: AGS 9 | V110: OM-BAS-AS09 | W110: 2. Professionals | X110: Exempt | Y110: US0009
A111: 45382 | B111: 2958465 | C111: A | D111: 100145 | E111: AVP Actuary | F111: 8810 | G111: AVP | H111: Permanent | I111: Employee | J111: Salaried | K111: E1 | N111: Yes | O111: Executive | P111: Executive | Q111: Product Provider | R111: Actuarial | S111: Senior Management | T111: Allianz Executive | U111: AGS 13 | V111: ACT-SEN-AE13 | W111: 1.2 First/ Mid-Level Officials and Managers | X111: Exempt | Y111: US0009
A112: 45382 | B112: 2958465 | C112: A | D112: 100147 | E112: AVP Associate General Counsel | F112: 8810 | G112: AVP | H112: Permanent | I112: Employee | J112: Salaried | K112: E1 | N112: Yes | O112: Executive | P112: Executive | Q112: Central Functions | R112: Legal | S112: Senior Management | T112: Allianz Executive | U112: AGS 13 | V112: LEG-SEN-AE13 | W112: 1.2 First/ Mid-Level Officials and Managers | X112: Exempt | Y112: US0009
A113: 45382 | B113: 2958465 | C113: A | D113: 100150 | E113: AVP Diversity Equity & Inclusion | F113: 8810 | G113: AVP | H113: Permanent | I113: Employee | J113: Salaried | K113: E1 | N113: Yes | O113: Executive | P113: Executive | Q113: Central Functions | R113: HR | S113: Senior Management | T113: Allianz Executive | U113: AGS 13 | V113: HR-SEN-AE13 | W113: 1.2 First/ Mid-Level Officials and Managers | X113: Exempt | Y113: US0009
A114: 45382 | B114: 2958465 | C114: A | D114: 100152 | E114: AVP Contact Center & Service Recovery | F114: 8810 | G114: AVP | H114: Permanent | I114: Employee | J114: Salaried | K114: E1 | N114: Yes | O114: Executive | P114: Executive | Q114: Operations | R114: Policy Management / Underwriting | S114: Senior Management | T114: Allianz Executive | U114: AGS 13 | V114: PMUW-SEN-AE13 | W114: 1.2 First/ Mid-Level Officials and Managers | X114: Exempt | Y114: US0009
A115: 45382 | B115: 2958465 | C115: A | D115: 100156 | E115: AVP Agile | F115: 8810 | G115: AVP | H115: Permanent | I115: Employee | J115: Salaried | K115: E1 | L115: Null | N115: Yes | O115: Executive | P115: Executive | Q115: Central Functions | R115: Other Central Functions | S115: Agile Master and Agile Coach | T115: Allianz Executive | U115: AGS 13 | V115: OCF-AGI-AE13 | W115: 1.2 First/ Mid-Level Officials and Managers | X115: Exempt | Y115: US0009
A116: 45275 | B116: 2958465 | C116: A | D116: 100159 | E116: AVP Infrastructure Services | F116: 8810 | G116: AVP | H116: Permanent | I116: Employee | J116: Salaried | K116: E1 | N116: Yes | O116: Executive | Q116: Operations | R116: IT | S116: IT Governance, Risk and Compliance | T116: Allianz Executive | U116: AGS 13 | V116: IT-IGR-AE13 | W116: 1.2 First/ Mid-Level Officials and Managers | X116: Exempt | Y116: US0821
A117: 45382 | B117: 2958465 | C117: A | D117: 100161 | E117: AVP IT Security & Risk Management CISO | F117: 8810 | G117: AVP | H117: Permanent | I117: Employee | J117: Salaried | K117: E1 | N117: Yes | O117: Executive | P117: Executive | Q117: Operations | R117: Information Security | S117: Information Security Officer | T117: Allianz Executive | U117: AGS 13 | V117: IS-ISO-AE13 | W117: 1.2 First/ Mid-Level Officials and Managers | X117: Exempt | Y117: US0009
A118: 45382 | B118: 2958465 | C118: A | D118: 100163 | E118: AVP Life Product Innovation | F118: 8810 | G118: AVP | H118: Permanent | I118: Employee | J118: Salaried | K118: E1 | N118: Yes | O118: Executive | P118: Executive | Q118: Product Provider | R118: Products | S118: Management | T118: Allianz Executive | U118: AGS 13 | V118: PROD-MAN-AE13 | W118: 1.2 First/ Mid-Level Officials and Managers | X118: Exempt | Y118: US0009
A119: 45382 | B119: 2958465 | C119: A | D119: 100164 | E119: AVP Privacy & Information Compliance | F119: 8810 | G119: AVP | H119: Permanent | I119: Employee | J119: Salaried | K119: E1 | N119: Yes | O119: Executive | P119: Executive | Q119: Central Functions | R119: Compliance | S119: Senior Management | T119: Allianz Executive | U119: AGS 13 | V119: COMP-SEN-AE13 | W119: 1.2 First/ Mid-Level Officials and Managers | X119: Exempt | Y119: US0009
A120: 45382 | B120: 2958465 | C120: A | D120: 100168 | E120: AVP Sponsorships | F120: 8810 | G120: AVP | H120: Permanent | I120: Employee | J120: Salaried | K120: E1 | N120: Yes | O120: Executive | P120: Executive | Q120: Market Management | R120: Operational Market Management | S120: Brand Management | T120: Allianz Executive | U120: AGS 13 | V120: OMM-BRM-AE13 | W120: 1.2 First/ Mid-Level Officials and Managers | X120: Exempt | Y120: US0009
A121: 45382 | B121: 2958465 | C121: A | D121: 100171 | E121: AVP Worksite & Middle Markets | F121: 8810 | G121: AVP | H121: Permanent | I121: Employee | J121: Salaried | K121: E1 | N121: Yes | O121: Executive | P121: Executive | Q121: Product Provider | R121: Products | S121: Product Specialist | T121: Allianz Executive | U121: AGS 13 | V121: PROD-PSP-AE13 | W121: 1.2 First/ Mid-Level Officials and Managers | X121: Exempt | Y121: US0009
A122: 45382 | B122: 2958465 | C122: A | D122: 100172 | E122: AZLife College Intern | F122: 8810 | G122: NA | H122: Temporary | I122: Intern | J122: Hourly | K122: Z | N122: No | O122: Temporary | P122: Internships | Q122: Operations | R122: Z Out of Scope | S122: Out of scope | T122: Not Applicable | U122: Not Applicable | V122: ZOS-OOS-NA | W122: No EEO-1 Reporting | X122: Nonexempt | Y122: US0009
A123: 45382 | B123: 2958465 | C123: A | D123: 100173 | E123: AZLife Intern-International | F123: 8810 | G123: NA | H123: Temporary | I123: Intern | J123: Hourly | K123: Z | N123: No | O123: Temporary | P123: Internships | Q123: Operations | R123: Z Out of Scope | S123: Out of scope | T123: Not Applicable | U123: Not Applicable | V123: ZOS-OOS-NA | W123: 2. Professionals | X123: Nonexempt | Y123: US0009
A124: 45382 | B124: 2958465 | C124: A | D124: 100174 | E124: AZLife Step-Up Intern | F124: 8810 | G124: NA | H124: Temporary | I124: Intern | J124: Hourly | K124: Z | N124: No | O124: Temporary | P124: Internships | Q124: Operations | R124: Z Out of Scope | S124: Out of scope | T124: Not Applicable | U124: Not Applicable | V124: ZOS-OOS-NA | W124: No EEO-1 Reporting | X124: Nonexempt | Y124: US0009
A125: 45382 | B125: 2958465 | C125: A | D125: 100175 | E125: BD Regional VP | F125: 8810 | G125: Director | H125: Permanent | I125: Sales Employee | J125: Salaried | K125: S2 | M125: 515000 | N125: No | O125: Insurance Distribution | P125: External Wholesaler | Q125: Sales/Distribution | R125: Distributors | S125: Account Management | T125: Senior Associate | U125: AGS 11 | V125: DIST-ACM-SA11 | W125: 4. Sales Workers | X125: Exempt | Y125: US0009
A126: 45382 | B126: 2958465 | C126: A | D126: 100177 | E126: Benefits Consultant | F126: 8810 | G126: Ind Contributor - Journey | H126: Permanent | I126: Employee | J126: Salaried | K126: 4 | L126: 1 | N126: No | O126: Human Resources | P126: Total Rewards | Q126: Central Functions | R126: HR | S126: HR Compensation & Benefits, Rewards & Performance | T126: Associate | U126: AGS 9 | V126: HR-HRC-AS09 | W126: 2. Professionals | X126: Exempt | Y126: US0009
A127: 45382 | B127: 2958465 | C127: A | D127: 100178 | E127: Benefits Consultant Senior | F127: 8810 | G127: Ind Contributor - Senior | H127: Permanent | I127: Employee | J127: Salaried | K127: 5 | L127: 2 | N127: No | O127: Human Resources | P127: Total Rewards | Q127: Central Functions | R127: HR | S127: HR Compensation & Benefits, Rewards & Performance | T127: Associate | U127: AGS 10 | V127: HR-HRC-AS10 | W127: 2. Professionals | X127: Exempt | Y127: US0009
...

Sheet Job Curves
A1: Overall | N1: Actuarial | W1: Audit | AF1: Data Analytics | AO1: Finance | AX1: Information Technology | BG1: Operations | BP1: Operations
N2: Chart | O2: Management | R2: Chart | S2: Professional | W2: Chart | X2: Management | AA2: Chart | AB2: Professional | AF2: Chart | AG2: Management | AJ2: Chart | AK2: Professional | AO2: Chart | AP2: Management | AS2: Chart | AT2: Professional | AX2: Chart | AY2: Management | BB2: Chart | BC2: Professional | BG2: Chart | BH2: Management | BK2: Chart | BL2: Professional | BP2: Chart | BQ2: Management | BT2: Chart | BU2: Professional
B3: Chart | C3: Professional | N3: Job Family | O3: Actuarial | R3: Job Family | S3: Actuarial | W3: Job Family | X3: Audit | AA3: Job Family | AB3: Audit | AF3: Job Family | AG3: Data Analytics | AJ3: Job Family | AK3: Data Analytics | AO3: Job Family | AP3: Finance | AS3: Job Family | AT3: Finance | AX3: Job Family | AY3: Information Technology | BB3: Job Family | BC3: Information Technology | BG3: Job Family | BH3: Operations | BK3: Job Family | BL3: Operations | BP3: Job Family | BQ3: Risk Management | BT3: Job Family | BU3: Risk Management
B5: Row Labels | C5: Count of Employee ID | D5: Average of WTW Benchmark | N5: Row Labels | O5: Count of Employee ID | P5: Average of WTW Benchmark | R5: Row Labels | S5: Count of Employee ID | T5: Average of WTW Benchmark | W5: Row Labels | X5: Count of Employee ID | Y5: Average of WTW Benchmark | AA5: Row Labels | AB5: Count of Employee ID | AC5: Average of WTW Benchmark | AF5: Row Labels | AG5: Count of Employee ID | AH5: Average of WTW Benchmark | AJ5: Row Labels | AK5: Count of Employee ID | AL5: Average of WTW Benchmark | AO5: Row Labels | AP5: Count of Employee ID | AQ5: Average of WTW Benchmark | AS5: Row Labels | AT5: Count of Employee ID | AU5: Average of WTW Benchmark | AX5: Row Labels | AY5: Count of Employee ID | AZ5: Average of WTW Benchmark | BB5: Row Labels | BC5: Count of Employee ID | BD5: Average of WTW Benchmark | BG5: Row Labels | BH5: Count of Employee ID | BI5: Average of WTW Benchmark | BK5: Row Labels | BL5: Count of Employee ID | BM5: Average of WTW Benchmark | BP5: Row Labels | BQ5: Count of Employee ID | BR5: Average of WTW Benchmark | BT5: Row Labels | BU5: Count of Employee ID | BV5: Average of WTW Benchmark
B6: P1 | C6: 0.10313901 | D6: 0.13 | N6: M4 | O6: 1 | P6: 0.18 | R6: P1 | S6: 0.16853933 | T6: 0.13 | W6: M3 | X6: 1 | Y6: 0.31 | AA6: P3 | AB6: 0.15384615 | AC6: 0.33 | AF6: M2 | AG6: 0.27272727 | AH6: 0.38 | AJ6: P2 | AK6: 0.3030303 | AL6: 0.25 | AO6: M1 | AP6: 0.23809524 | AQ6: 0.13 | AS6: P2 | AT6: 0.2295082 | AU6: 0.25 | AX6: M2 | AY6: 0.44444444 | AZ6: 0.38 | BB6: P1 | BC6: 0.034482759 | BD6: 0.13 | BG6: M1 | BH6: 0.24242424 | BI6: 0.13 | BK6: P1 | BL6: 0.15263158 | BM6: 0.13 | BP6: M2 | BQ6: 0.4 | BR6: 0.38 | BT6: P3 | BU6: 0.5 | BV6: 0.33
B7: P2 | C7: 0.3206278 | D7: 0.25 | R7: P2 | S7: 0.49438202 | T7: 0.25 | AA7: P4 | AB7: 0.84615385 | AC7: 0.21 | AF7: M3 | AG7: 0.45454545 | AH7: 0.31 | AJ7: P3 | AK7: 0.48484848 | AL7: 0.33 | AO7: M2 | AP7: 0.28571429 | AQ7: 0.38 | AS7: P3 | AT7: 0.40983607 | AU7: 0.33 | AX7: M3 | AY7: 0.44444444 | AZ7: 0.31 | BB7: P2 | BC7: 0.27586207 | BD7: 0.25 | BG7: M2 | BH7: 0.5 | BI7: 0.38 | BK7: P2 | BL7: 0.31052632 | BM7: 0.25 | BP7: M3 | BQ7: 0.4 | BR7: 0.31 | BT7: P4 | BU7: 0.5 | BV7: 0.21
B8: P3 | C8: 0.28251121 | D8: 0.33 | R8: P3 | S8: 0.16853933 | T8: 0.33 | AF8: M4 | AG8: 0.27272727 | AH8: 0.18 | AJ8: P4 | AK8: 0.21212121 | AL8: 0.21 | AO8: M3 | AP8: 0.14285714 | AQ8: 0.31 | AS8: P4 | AT8: 0.36065574 | AU8: 0.21 | AX8: M4 | AY8: 0.11111111 | AZ8: 0.18 | BB8: P3 | BC8: 0.27586207 | BD8: 0.33 | BG8: M3 | BH8: 0.13636364 | BI8: 0.31 | BK8: P3 | BL8: 0.26842105 | BM8: 0.33 | BP8: M4 | BQ8: 0.2 | BR8: 0.18
B9: P4 | C9: 0.24887892 | D9: 0.21 | R9: P4 | S9: 0.06741573 | T9: 0.21 | AO9: M4 | AP9: 0.33333333 | AQ9: 0.18 | BB9: P4 | BC9: 0.22413793 | BD9: 0.21 | BG9: M4 | BH9: 0.12121212 | BI9: 0.18 | BK9: P4 | BL9: 0.26842105 | BM9: 0.21
B10: P5 | C10: 0.044843049 | D10: 0.07 | R10: P5 | S10: 0.1011236 | T10: 0.07 | BB10: P5 | BC10: 0.18965517 | BD10: 0.07
B17: Chart | C17: Management
B19: Row Labels | C19: Count of Employee ID | D19: Average of WTW Benchmark
B20: M1 | C20: 0.17647059 | D20: 0.13
B21: M2 | C21: 0.40336134 | D21: 0.38
B22: M3 | C22: 0.21848739 | D22: 0.31
B23: M4 | C23: 0.20168067 | D23: 0.18
